Workbook
Name SegmentaciónDeDatos_ACUM: #N/A
Name SegmentaciónDeDatos_FECHA: #N/A
Name SegmentaciónDeDatos_FECHA1: #N/A
Name SegmentaciónDeDatos_M_E: #N/A
Name SegmentaciónDeDatos_MAQUINA_AREA_EQUIPO: #N/A
Name SegmentaciónDeDatos_MAQUINA_AREA_EQUIPO1: #N/A
Name SegmentaciónDeDatos_P_NP: #N/A
Name SegmentaciónDeDatos_PIEZA___PARTE: #N/A
Name SegmentaciónDeDatos_TIPO_ACTIVIDAD: #N/A
Name Tecnicos: DATOS!$G$3:$G$5

Sheet REGISTRO
A3: REPORTE DIARIO DE TÉCNICOS
A4: FECHA | B4: TECNICO | C4: TURNO | D4: HR. INICIO | E4: HR. FIN | F4: T.Total | G4: MAQUINA/AREA/EQUIPO | H4: CLASIFICACIÓN | I4: TIPO ACTIVIDAD | J4: P/NP | K4: M/E | L4: DESCRIPCION DE TRABAJO | M4: ACTIVIDAD CORRECTIVO | N4: PIEZA | O4: PARTE | P4: PARTE 1 | Q4: PARTE 2 | R4: PARTE 3 | S4: DETALLE | T4: PIEZA - PARTE | U4: ACUM
A5: 45659 | B5: Carlos Puma | C5: TARDE | D5: 0.95833333 | E5: 0.16666667 | F5: =+MOD(Tabla8[[#This Row],[HR. FIN]]-Tabla8[[#This Row],[HR. INICIO]],1) -> 0.20833333 | G5: EMP. SACMI | H5: =IFERROR(VLOOKUP(G5,DATOS!$M$2:$N$219,2,FALSE),"") -> Maquinaria | I5: Trabajos menores | J5: =+VLOOKUP($I5,Tabla7[#All],2,FALSE) -> PROGRAMADA | K5: =IF(VLOOKUP(I5,Tabla7[#All],3,FALSE)=0,"",VLOOKUP(I5,Tabla7[#All],3,FALSE)) | L5: Apoyo a personal tercero retirando polin dañado para toma de medidas | N5: {=IFERROR(IF(Tabla8[[#This Row],[P/NP]]="NO PROGRAMADA","",_xlfn.TEXTJOIN(", ",TRUE,_xlfn._xlws.FILTER(Tabla4[[#All],[PIEZA]],ISNUMBER(SEARCH(Tabla4[[#All],[PCLAVE]],Tabla8[[#This Row],[DESCRIPCION DE TRABAJO]])),""))),"")} -> Polin De Arrastre | O5: {=_xlfn.TEXTJOIN(", ",TRUE,_xlfn._xlws.FILTER(Tabla28[[#All],[PARTE]],ISNUMBER(SEARCH(Tabla28[[#All],[PCLAVE2]],Tabla8[[#This Row],[DESCRIPCION DE TRABAJO]])),""))} | P5: =IFERROR(LEFT(O5, FIND(",", O5)-1), O5) | Q5: =IFERROR(IF(ISERROR(FIND(",", O5, FIND(",", O5)+1)), RIGHT(O5, LEN(O5)-FIND(",", O5)-1), MID(O5, FIND(",", O5)+2, FIND(",", O5, FIND(",", O5)+1)-FIND(",", O5)-2)), "") | R5: =IFERROR(RIGHT(O5, LEN(O5)-FIND(",", O5, FIND(",", O5)+1)-1), "") | S5: {=_xlfn.TEXTJOIN(", ",TRUE,_xlfn._xlws.FILTER(Tabla29[[#All],[PARTE]],ISNUMBER(SEARCH(Tabla29[[#All],[PCLAVE3]],Tabla8[[#This Row],[DESCRIPCION DE TRABAJO]])),""))} -> Dañado, Sustitucion | T5: =IF(AND(Tabla8[[#This Row],[PIEZA]]="",Tabla8[[#This Row],[PARTE]]=""),"VACIO","OK") -> OK | U5: =+CONCATENATE(WEEKNUM(Tabla8[[#This Row],[FECHA]]),"-",YEAR(Tabla8[[#This Row],[FECHA]])) -> 1-2025
A6: 45659 | B6: Carlos Puma | C6: TARDE | D6: 0.61111111 | E6: 0.71875 | F6: =+MOD(Tabla8[[#This Row],[HR. FIN]]-Tabla8[[#This Row],[HR. INICIO]],1) -> 0.10763889 | G6: HACOS 1 | H6: =IFERROR(VLOOKUP(G6,DATOS!$M$2:$N$219,2,FALSE),"") -> Maquinaria | I6: Sustitucion | J6: =+VLOOKUP($I6,Tabla7[#All],2,FALSE) -> NO PROGRAMADA | K6: =IF(VLOOKUP(I6,Tabla7[#All],3,FALSE)=0,"",VLOOKUP(I6,Tabla7[#All],3,FALSE)) -> ELÉCTRICA | L6: Error en C-14 | M6: Se hizo cambio de resorte de empujador de moldes, se reemplaza piston, se calibro sensores y se regulo el recorrido y velocidad de piston | N6: {=IFERROR(IF(Tabla8[[#This Row],[P/NP]]="NO PROGRAMADA","",_xlfn.TEXTJOIN(", ",TRUE,_xlfn._xlws.FILTER(Tabla4[[#All],[PIEZA]],ISNUMBER(SEARCH(Tabla4[[#All],[PCLAVE]],Tabla8[[#This Row],[DESCRIPCION DE TRABAJO]])),""))),"")} | O6: {=_xlfn.TEXTJOIN(", ",TRUE,_xlfn._xlws.FILTER(Tabla28[[#All],[PARTE]],ISNUMBER(SEARCH(Tabla28[[#All],[PCLAVE2]],Tabla8[[#This Row],[DESCRIPCION DE TRABAJO]])),""))} | P6: =IFERROR(LEFT(O6, FIND(",", O6)-1), O6) | Q6: =IFERROR(IF(ISERROR(FIND(",", O6, FIND(",", O6)+1)), RIGHT(O6, LEN(O6)-FIND(",", O6)-1), MID(O6, FIND(",", O6)+2, FIND(",", O6, FIND(",", O6)+1)-FIND(",", O6)-2)), "") | R6: =IFERROR(RIGHT(O6, LEN(O6)-FIND(",", O6, FIND(",", O6)+1)-1), "") | S6: {=_xlfn.TEXTJOIN(", ",TRUE,_xlfn._xlws.FILTER(Tabla29[[#All],[PARTE]],ISNUMBER(SEARCH(Tabla29[[#All],[PCLAVE3]],Tabla8[[#This Row],[DESCRIPCION DE TRABAJO]])),""))} -> Error | T6: =IF(AND(Tabla8[[#This Row],[PIEZA]]="",Tabla8[[#This Row],[PARTE]]=""),"VACIO","OK") -> VACIO | U6: =+CONCATENATE(WEEKNUM(Tabla8[[#This Row],[FECHA]]),"-",YEAR(Tabla8[[#This Row],[FECHA]])) -> 1-2025
A7: 45659 | B7: Carlos Puma | C7: TARDE | D7: 0.79861111 | E7: 0.84722222 | F7: =+MOD(Tabla8[[#This Row],[HR. FIN]]-Tabla8[[#This Row],[HR. INICIO]],1) -> 0.048611111 | G7: EMP. FLOWPACK 2 | H7: =IFERROR(VLOOKUP(G7,DATOS!$M$2:$N$219,2,FALSE),"") -> Maquinaria | I7: SET UP | J7: =+VLOOKUP($I7,Tabla7[#All],2,FALSE) -> PROGRAMADA | K7: =IF(VLOOKUP(I7,Tabla7[#All],3,FALSE)=0,"",VLOOKUP(I7,Tabla7[#All],3,FALSE)) | L7: Cambio de formato bitesize | M7: Se cambio cadena, empujadores y mordaza | N7: {=IFERROR(IF(Tabla8[[#This Row],[P/NP]]="NO PROGRAMADA","",_xlfn.TEXTJOIN(", ",TRUE,_xlfn._xlws.FILTER(Tabla4[[#All],[PIEZA]],ISNUMBER(SEARCH(Tabla4[[#All],[PCLAVE]],Tabla8[[#This Row],[DESCRIPCION DE TRABAJO]])),""))),"")} | O7: {=_xlfn.TEXTJOIN(", ",TRUE,_xlfn._xlws.FILTER(Tabla28[[#All],[PARTE]],ISNUMBER(SEARCH(Tabla28[[#All],[PCLAVE2]],Tabla8[[#This Row],[DESCRIPCION DE TRABAJO]])),""))} | P7: =IFERROR(LEFT(O7, FIND(",", O7)-1), O7) | Q7: =IFERROR(IF(ISERROR(FIND(",", O7, FIND(",", O7)+1)), RIGHT(O7, LEN(O7)-FIND(",", O7)-1), MID(O7, FIND(",", O7)+2, FIND(",", O7, FIND(",", O7)+1)-FIND(",", O7)-2)), "") | R7: =IFERROR(RIGHT(O7, LEN(O7)-FIND(",", O7, FIND(",", O7)+1)-1), "") | S7: {=_xlfn.TEXTJOIN(", ",TRUE,_xlfn._xlws.FILTER(Tabla29[[#All],[PARTE]],ISNUMBER(SEARCH(Tabla29[[#All],[PCLAVE3]],Tabla8[[#This Row],[DESCRIPCION DE TRABAJO]])),""))} -> Cambio De Formato | T7: =IF(AND(Tabla8[[#This Row],[PIEZA]]="",Tabla8[[#This Row],[PARTE]]=""),"VACIO","OK") -> VACIO | U7: =+CONCATENATE(WEEKNUM(Tabla8[[#This Row],[FECHA]]),"-",YEAR(Tabla8[[#This Row],[FECHA]])) -> 1-2025
A8: 45659 | B8: Cesar Quiroz | C8: MAÑANA | D8: 0.32291667 | E8: 0.36527778 | F8: =+MOD(Tabla8[[#This Row],[HR. FIN]]-Tabla8[[#This Row],[HR. INICIO]],1) -> 0.042361111 | G8: EMP. FLOWPACK 2 | H8: =IFERROR(VLOOKUP(G8,DATOS!$M$2:$N$219,2,FALSE),"") -> Maquinaria | I8: SET UP | J8: =+VLOOKUP($I8,Tabla7[#All],2,FALSE) -> PROGRAMADA | K8: =IF(VLOOKUP(I8,Tabla7[#All],3,FALSE)=0,"",VLOOKUP(I8,Tabla7[#All],3,FALSE)) | L8: Cambio de mordaza para minimilky | N8: {=IFERROR(IF(Tabla8[[#This Row],[P/NP]]="NO PROGRAMADA","",_xlfn.TEXTJOIN(", ",TRUE,_xlfn._xlws.FILTER(Tabla4[[#All],[PIEZA]],ISNUMBER(SEARCH(Tabla4[[#All],[PCLAVE]],Tabla8[[#This Row],[DESCRIPCION DE TRABAJO]])),""))),"")} -> Mordaza | O8: {=_xlfn.TEXTJOIN(", ",TRUE,_xlfn._xlws.FILTER(Tabla28[[#All],[PARTE]],ISNUMBER(SEARCH(Tabla28[[#All],[PCLAVE2]],Tabla8[[#This Row],[DESCRIPCION DE TRABAJO]])),""))} | P8: =IFERROR(LEFT(O8, FIND(",", O8)-1), O8) | Q8: =IFERROR(IF(ISERROR(FIND(",", O8, FIND(",", O8)+1)), RIGHT(O8, LEN(O8)-FIND(",", O8)-1), MID(O8, FIND(",", O8)+2, FIND(",", O8, FIND(",", O8)+1)-FIND(",", O8)-2)), "") | R8: =IFERROR(RIGHT(O8, LEN(O8)-FIND(",", O8, FIND(",", O8)+1)-1), "") | S8: {=_xlfn.TEXTJOIN(", ",TRUE,_xlfn._xlws.FILTER(Tabla29[[#All],[PARTE]],ISNUMBER(SEARCH(Tabla29[[#All],[PCLAVE3]],Tabla8[[#This Row],[DESCRIPCION DE TRABAJO]])),""))} | T8: =IF(AND(Tabla8[[#This Row],[PIEZA]]="",Tabla8[[#This Row],[PARTE]]=""),"VACIO","OK") -> OK | U8: =+CONCATENATE(WEEKNUM(Tabla8[[#This Row],[FECHA]]),"-",YEAR(Tabla8[[#This Row],[FECHA]])) -> 1-2025
A9: 45659 | B9: Omar Nina | C9: NOCHE | D9: 0.97222222 | E9: 1.0118056 | F9: =+MOD(Tabla8[[#This Row],[HR. FIN]]-Tabla8[[#This Row],[HR. INICIO]],1) -> 0.039583333 | G9: HACOS 1 | H9: =IFERROR(VLOOKUP(G9,DATOS!$M$2:$N$219,2,FALSE),"") -> Maquinaria | I9: SET UP | J9: =+VLOOKUP($I9,Tabla7[#All],2,FALSE) -> PROGRAMADA | K9: =IF(VLOOKUP(I9,Tabla7[#All],3,FALSE)=0,"",VLOOKUP(I9,Tabla7[#All],3,FALSE)) | L9: Cambio de formato a crema ovalada | M9: Se retiro plancha y usillo para lavar y se cambio cuchilla | N9: {=IFERROR(IF(Tabla8[[#This Row],[P/NP]]="NO PROGRAMADA","",_xlfn.TEXTJOIN(", ",TRUE,_xlfn._xlws.FILTER(Tabla4[[#All],[PIEZA]],ISNUMBER(SEARCH(Tabla4[[#All],[PCLAVE]],Tabla8[[#This Row],[DESCRIPCION DE TRABAJO]])),""))),"")} | O9: {=_xlfn.TEXTJOIN(", ",TRUE,_xlfn._xlws.FILTER(Tabla28[[#All],[PARTE]],ISNUMBER(SEARCH(Tabla28[[#All],[PCLAVE2]],Tabla8[[#This Row],[DESCRIPCION DE TRABAJO]])),""))} | P9: =IFERROR(LEFT(O9, FIND(",", O9)-1), O9) | Q9: =IFERROR(IF(ISERROR(FIND(",", O9, FIND(",", O9)+1)), RIGHT(O9, LEN(O9)-FIND(",", O9)-1), MID(O9, FIND(",", O9)+2, FIND(",", O9, FIND(",", O9)+1)-FIND(",", O9)-2)), "") | R9: =IFERROR(RIGHT(O9, LEN(O9)-FIND(",", O9, FIND(",", O9)+1)-1), "") | S9: {=_xlfn.TEXTJOIN(", ",TRUE,_xlfn._xlws.FILTER(Tabla29[[#All],[PARTE]],ISNUMBER(SEARCH(Tabla29[[#All],[PCLAVE3]],Tabla8[[#This Row],[DESCRIPCION DE TRABAJO]])),""))} -> Cambio De Formato | T9: =IF(AND(Tabla8[[#This Row],[PIEZA]]="",Tabla8[[#This Row],[PARTE]]=""),"VACIO","OK") -> VACIO | U9: =+CONCATENATE(WEEKNUM(Tabla8[[#This Row],[FECHA]]),"-",YEAR(Tabla8[[#This Row],[FECHA]])) -> 1-2025
A10: 45659 | B10: Cesar Quiroz | C10: MAÑANA | D10: 0.23333333 | E10: 0.26458333 | F10: =+MOD(Tabla8[[#This Row],[HR. FIN]]-Tabla8[[#This Row],[HR. INICIO]],1) -> 0.03125 | G10: MAQUINARIA DE PLANTA | H10: =IFERROR(VLOOKUP(G10,DATOS!$M$2:$N$219,2,FALSE),"") -> Maquinaria | I10: Encendido / Arranque de linea | J10: =+VLOOKUP($I10,Tabla7[#All],2,FALSE) -> PROGRAMADA | K10: =IF(VLOOKUP(I10,Tabla7[#All],3,FALSE)=0,"",VLOOKUP(I10,Tabla7[#All],3,FALSE)) | L10: Arranque de equipos de planta | N10: {=IFERROR(IF(Tabla8[[#This Row],[P/NP]]="NO PROGRAMADA","",_xlfn.TEXTJOIN(", ",TRUE,_xlfn._xlws.FILTER(Tabla4[[#All],[PIEZA]],ISNUMBER(SEARCH(Tabla4[[#All],[PCLAVE]],Tabla8[[#This Row],[DESCRIPCION DE TRABAJO]])),""))),"")} | O10: {=_xlfn.TEXTJOIN(", ",TRUE,_xlfn._xlws.FILTER(Tabla28[[#All],[PARTE]],ISNUMBER(SEARCH(Tabla28[[#All],[PCLAVE2]],Tabla8[[#This Row],[DESCRIPCION DE TRABAJO]])),""))} | P10: =IFERROR(LEFT(O10, FIND(",", O10)-1), O10) | Q10: =IFERROR(IF(ISERROR(FIND(",", O10, FIND(",", O10)+1)), RIGHT(O10, LEN(O10)-FIND(",", O10)-1), MID(O10, FIND(",", O10)+2, FIND(",", O10, FIND(",", O10)+1)-FIND(",", O10)-2)), "") | R10: =IFERROR(RIGHT(O10, LEN(O10)-FIND(",", O10, FIND(",", O10)+1)-1), "") | S10: {=_xlfn.TEXTJOIN(", ",TRUE,_xlfn._xlws.FILTER(Tabla29[[#All],[PARTE]],ISNUMBER(SEARCH(Tabla29[[#All],[PCLAVE3]],Tabla8[[#This Row],[DESCRIPCION DE TRABAJO]])),""))} | T10: =IF(AND(Tabla8[[#This Row],[PIEZA]]="",Tabla8[[#This Row],[PARTE]]=""),"VACIO","OK") -> VACIO | U10: =+CONCATENATE(WEEKNUM(Tabla8[[#This Row],[FECHA]]),"-",YEAR(Tabla8[[#This Row],[FECHA]])) -> 1-2025
A11: 45659 | B11: Cesar Quiroz | C11: MAÑANA | D11: 0.29861111 | E11: 0.32083333 | F11: =+MOD(Tabla8[[#This Row],[HR. FIN]]-Tabla8[[#This Row],[HR. INICIO]],1) -> 0.022222222 | G11: HACOS 1 | H11: =IFERROR(VLOOKUP(G11,DATOS!$M$2:$N$219,2,FALSE),"") -> Maquinaria | I11: SET UP | J11: =+VLOOKUP($I11,Tabla7[#All],2,FALSE) -> PROGRAMADA | K11: =IF(VLOOKUP(I11,Tabla7[#All],3,FALSE)=0,"",VLOOKUP(I11,Tabla7[#All],3,FALSE)) | L11: Armado de formato x50 agregados en MDS | N11: {=IFERROR(IF(Tabla8[[#This Row],[P/NP]]="NO PROGRAMADA","",_xlfn.TEXTJOIN(", ",TRUE,_xlfn._xlws.FILTER(Tabla4[[#All],[PIEZA]],ISNUMBER(SEARCH(Tabla4[[#All],[PCLAVE]],Tabla8[[#This Row],[DESCRIPCION DE TRABAJO]])),""))),"")} | O11: {=_xlfn.TEXTJOIN(", ",TRUE,_xlfn._xlws.FILTER(Tabla28[[#All],[PARTE]],ISNUMBER(SEARCH(Tabla28[[#All],[PCLAVE2]],Tabla8[[#This Row],[DESCRIPCION DE TRABAJO]])),""))} -> Mds | P11: =IFERROR(LEFT(O11, FIND(",", O11)-1), O11) -> Mds | Q11: =IFERROR(IF(ISERROR(FIND(",", O11, FIND(",", O11)+1)), RIGHT(O11, LEN(O11)-FIND(",", O11)-1), MID(O11, FIND(",", O11)+2, FIND(",", O11, FIND(",", O11)+1)-FIND(",", O11)-2)), "") | R11: =IFERROR(RIGHT(O11, LEN(O11)-FIND(",", O11, FIND(",", O11)+1)-1), "") | S11: {=_xlfn.TEXTJOIN(", ",TRUE,_xlfn._xlws.FILTER(Tabla29[[#All],[PARTE]],ISNUMBER(SEARCH(Tabla29[[#All],[PCLAVE3]],Tabla8[[#This Row],[DESCRIPCION DE TRABAJO]])),""))} -> Cambio De Formato | T11: =IF(AND(Tabla8[[#This Row],[PIEZA]]="",Tabla8[[#This Row],[PARTE]]=""),"VACIO","OK") -> OK | U11: =+CONCATENATE(WEEKNUM(Tabla8[[#This Row],[FECHA]]),"-",YEAR(Tabla8[[#This Row],[FECHA]])) -> 1-2025
A12: 45659 | B12: Cesar Quiroz | C12: MAÑANA | D12: 0.50694444 | E12: 0.52638889 | F12: =+MOD(Tabla8[[#This Row],[HR. FIN]]-Tabla8[[#This Row],[HR. INICIO]],1) -> 0.019444444 | G12: HACOS 1 | H12: =IFERROR(VLOOKUP(G12,DATOS!$M$2:$N$219,2,FALSE),"") -> Maquinaria | I12: SET UP | J12: =+VLOOKUP($I12,Tabla7[#All],2,FALSE) -> PROGRAMADA | K12: =IF(VLOOKUP(I12,Tabla7[#All],3,FALSE)=0,"",VLOOKUP(I12,Tabla7[#All],3,FALSE)) | L12: Armado de formato cremas en MDS | N12: {=IFERROR(IF(Tabla8[[#This Row],[P/NP]]="NO PROGRAMADA","",_xlfn.TEXTJOIN(", ",TRUE,_xlfn._xlws.FILTER(Tabla4[[#All],[PIEZA]],ISNUMBER(SEARCH(Tabla4[[#All],[PCLAVE]],Tabla8[[#This Row],[DESCRIPCION DE TRABAJO]])),""))),"")} | O12: {=_xlfn.TEXTJOIN(", ",TRUE,_xlfn._xlws.FILTER(Tabla28[[#All],[PARTE]],ISNUMBER(SEARCH(Tabla28[[#All],[PCLAVE2]],Tabla8[[#This Row],[DESCRIPCION DE TRABAJO]])),""))} -> Mds | P12: =IFERROR(LEFT(O12, FIND(",", O12)-1), O12) -> Mds | Q12: =IFERROR(IF(ISERROR(FIND(",", O12, FIND(",", O12)+1)), RIGHT(O12, LEN(O12)-FIND(",", O12)-1), MID(O12, FIND(",", O12)+2, FIND(",", O12, FIND(",", O12)+1)-FIND(",", O12)-2)), "") | R12: =IFERROR(RIGHT(O12, LEN(O12)-FIND(",", O12, FIND(",", O12)+1)-1), "") | S12: {=_xlfn.TEXTJOIN(", ",TRUE,_xlfn._xlws.FILTER(Tabla29[[#All],[PARTE]],ISNUMBER(SEARCH(Tabla29[[#All],[PCLAVE3]],Tabla8[[#This Row],[DESCRIPCION DE TRABAJO]])),""))} -> Cambio De Formato | T12: =IF(AND(Tabla8[[#This Row],[PIEZA]]="",Tabla8[[#This Row],[PARTE]]=""),"VACIO","OK") -> OK | U12: =+CONCATENATE(WEEKNUM(Tabla8[[#This Row],[FECHA]]),"-",YEAR(Tabla8[[#This Row],[FECHA]])) -> 1-2025
A13: 45659 | B13: Cesar Quiroz | C13: MAÑANA | D13: 0.48541667 | E13: 0.50486111 | F13: =+MOD(Tabla8[[#This Row],[HR. FIN]]-Tabla8[[#This Row],[HR. INICIO]],1) -> 0.019444444 | G13: HACOS 1 | H13: =IFERROR(VLOOKUP(G13,DATOS!$M$2:$N$219,2,FALSE),"") -> Maquinaria | I13: SET UP | J13: =+VLOOKUP($I13,Tabla7[#All],2,FALSE) -> PROGRAMADA | K13: =IF(VLOOKUP(I13,Tabla7[#All],3,FALSE)=0,"",VLOOKUP(I13,Tabla7[#All],3,FALSE)) | L13: Desarmado de formato agregados x50 MDS | N13: {=IFERROR(IF(Tabla8[[#This Row],[P/NP]]="NO PROGRAMADA","",_xlfn.TEXTJOIN(", ",TRUE,_xlfn._xlws.FILTER(Tabla4[[#All],[PIEZA]],ISNUMBER(SEARCH(Tabla4[[#All],[PCLAVE]],Tabla8[[#This Row],[DESCRIPCION DE TRABAJO]])),""))),"")} | O13: {=_xlfn.TEXTJOIN(", ",TRUE,_xlfn._xlws.FILTER(Tabla28[[#All],[PARTE]],ISNUMBER(SEARCH(Tabla28[[#All],[PCLAVE2]],Tabla8[[#This Row],[DESCRIPCION DE TRABAJO]])),""))} -> Mds | P13: =IFERROR(LEFT(O13, FIND(",", O13)-1), O13) -> Mds | Q13: =IFERROR(IF(ISERROR(FIND(",", O13, FIND(",", O13)+1)), RIGHT(O13, LEN(O13)-FIND(",", O13)-1), MID(O13, FIND(",", O13)+2, FIND(",", O13, FIND(",", O13)+1)-FIND(",", O13)-2)), "") | R13: =IFERROR(RIGHT(O13, LEN(O13)-FIND(",", O13, FIND(",", O13)+1)-1), "") | S13: {=_xlfn.TEXTJOIN(", ",TRUE,_xlfn._xlws.FILTER(Tabla29[[#All],[PARTE]],ISNUMBER(SEARCH(Tabla29[[#All],[PCLAVE3]],Tabla8[[#This Row],[DESCRIPCION DE TRABAJO]])),""))} -> Cambio De Formato | T13: =IF(AND(Tabla8[[#This Row],[PIEZA]]="",Tabla8[[#This Row],[PARTE]]=""),"VACIO","OK") -> OK | U13: =+CONCATENATE(WEEKNUM(Tabla8[[#This Row],[FECHA]]),"-",YEAR(Tabla8[[#This Row],[FECHA]])) -> 1-2025
A14: 45659 | B14: Cesar Quiroz | C14: MAÑANA | D14: 0.27569444 | E14: 0.29444444 | F14: =+MOD(Tabla8[[#This Row],[HR. FIN]]-Tabla8[[#This Row],[HR. INICIO]],1) -> 0.01875 | G14: HACOS 1 | H14: =IFERROR(VLOOKUP(G14,DATOS!$M$2:$N$219,2,FALSE),"") -> Maquinaria | I14: SET UP | J14: =+VLOOKUP($I14,Tabla7[#All],2,FALSE) -> PROGRAMADA | K14: =IF(VLOOKUP(I14,Tabla7[#All],3,FALSE)=0,"",VLOOKUP(I14,Tabla7[#All],3,FALSE)) | L14: Desarmado de formato x100 agregados en MDS | N14: {=IFERROR(IF(Tabla8[[#This Row],[P/NP]]="NO PROGRAMADA","",_xlfn.TEXTJOIN(", ",TRUE,_xlfn._xlws.FILTER(Tabla4[[#All],[PIEZA]],ISNUMBER(SEARCH(Tabla4[[#All],[PCLAVE]],Tabla8[[#This Row],[DESCRIPCION DE TRABAJO]])),""))),"")} | O14: {=_xlfn.TEXTJOIN(", ",TRUE,_xlfn._xlws.FILTER(Tabla28[[#All],[PARTE]],ISNUMBER(SEARCH(Tabla28[[#All],[PCLAVE2]],Tabla8[[#This Row],[DESCRIPCION DE TRABAJO]])),""))} -> Mds | P14: =IFERROR(LEFT(O14, FIND(",", O14)-1), O14) -> Mds | Q14: =IFERROR(IF(ISERROR(FIND(",", O14, FIND(",", O14)+1)), RIGHT(O14, LEN(O14)-FIND(",", O14)-1), MID(O14, FIND(",", O14)+2, FIND(",", O14, FIND(",", O14)+1)-FIND(",", O14)-2)), "") | R14: =IFERROR(RIGHT(O14, LEN(O14)-FIND(",", O14, FIND(",", O14)+1)-1), "") | S14: {=_xlfn.TEXTJOIN(", ",TRUE,_xlfn._xlws.FILTER(Tabla29[[#All],[PARTE]],ISNUMBER(SEARCH(Tabla29[[#All],[PCLAVE3]],Tabla8[[#This Row],[DESCRIPCION DE TRABAJO]])),""))} -> Cambio De Formato | T14: =IF(AND(Tabla8[[#This Row],[PIEZA]]="",Tabla8[[#This Row],[PARTE]]=""),"VACIO","OK") -> OK | U14: =+CONCATENATE(WEEKNUM(Tabla8[[#This Row],[FECHA]]),"-",YEAR(Tabla8[[#This Row],[FECHA]])) -> 1-2025
A15: 45659 | B15: Omar Nina | C15: NOCHE | D15: 0.14861111 | E15: 0.16666667 | F15: =+MOD(Tabla8[[#This Row],[HR. FIN]]-Tabla8[[#This Row],[HR. INICIO]],1) -> 0.018055556 | G15: 5TO PISO | H15: =IFERROR(VLOOKUP(G15,DATOS!$M$2:$N$219,2,FALSE),"") -> Area | I15: Trabajos menores | J15: =+VLOOKUP($I15,Tabla7[#All],2,FALSE) -> PROGRAMADA | K15: =IF(VLOOKUP(I15,Tabla7[#All],3,FALSE)=0,"",VLOOKUP(I15,Tabla7[#All],3,FALSE)) | L15: Apoyo a calidad colocando dispensado de papel | N15: {=IFERROR(IF(Tabla8[[#This Row],[P/NP]]="NO PROGRAMADA","",_xlfn.TEXTJOIN(", ",TRUE,_xlfn._xlws.FILTER(Tabla4[[#All],[PIEZA]],ISNUMBER(SEARCH(Tabla4[[#All],[PCLAVE]],Tabla8[[#This Row],[DESCRIPCION DE TRABAJO]])),""))),"")} -> Dispensador | O15: {=_xlfn.TEXTJOIN(", ",TRUE,_xlfn._xlws.FILTER(Tabla28[[#All],[PARTE]],ISNUMBER(SEARCH(Tabla28[[#All],[PCLAVE2]],Tabla8[[#This Row],[DESCRIPCION DE TRABAJO]])),""))} | P15: =IFERROR(LEFT(O15, FIND(",", O15)-1), O15) | Q15: =IFERROR(IF(ISERROR(FIND(",", O15, FIND(",", O15)+1)), RIGHT(O15, LEN(O15)-FIND(",", O15)-1), MID(O15, FIND(",", O15)+2, FIND(",", O15, FIND(",", O15)+1)-FIND(",", O15)-2)), "") | R15: =IFERROR(RIGHT(O15, LEN(O15)-FIND(",", O15, FIND(",", O15)+1)-1), "") | S15: {=_xlfn.TEXTJOIN(", ",TRUE,_xlfn._xlws.FILTER(Tabla29[[#All],[PARTE]],ISNUMBER(SEARCH(Tabla29[[#All],[PCLAVE3]],Tabla8[[#This Row],[DESCRIPCION DE TRABAJO]])),""))} | T15: =IF(AND(Tabla8[[#This Row],[PIEZA]]="",Tabla8[[#This Row],[PARTE]]=""),"VACIO","OK") -> OK | U15: =+CONCATENATE(WEEKNUM(Tabla8[[#This Row],[FECHA]]),"-",YEAR(Tabla8[[#This Row],[FECHA]])) -> 1-2025
A16: 45659 | B16: Omar Nina | C16: NOCHE | D16: 0.90972222 | E16: 0.92708333 | F16: =+MOD(Tabla8[[#This Row],[HR. FIN]]-Tabla8[[#This Row],[HR. INICIO]],1) -> 0.017361111 | G16: EMP. FLOWPACK 2 | H16: =IFERROR(VLOOKUP(G16,DATOS!$M$2:$N$219,2,FALSE),"") -> Maquinaria | I16: SET UP | J16: =+VLOOKUP($I16,Tabla7[#All],2,FALSE) -> PROGRAMADA | K16: =IF(VLOOKUP(I16,Tabla7[#All],3,FALSE)=0,"",VLOOKUP(I16,Tabla7[#All],3,FALSE)) | L16: Programa no responde | M16: Se reinicia ambos tableros y se probo. Queda operativo | N16: {=IFERROR(IF(Tabla8[[#This Row],[P/NP]]="NO PROGRAMADA","",_xlfn.TEXTJOIN(", ",TRUE,_xlfn._xlws.FILTER(Tabla4[[#All],[PIEZA]],ISNUMBER(SEARCH(Tabla4[[#All],[PCLAVE]],Tabla8[[#This Row],[DESCRIPCION DE TRABAJO]])),""))),"")} | O16: {=_xlfn.TEXTJOIN(", ",TRUE,_xlfn._xlws.FILTER(Tabla28[[#All],[PARTE]],ISNUMBER(SEARCH(Tabla28[[#All],[PCLAVE2]],Tabla8[[#This Row],[DESCRIPCION DE TRABAJO]])),""))} | P16: =IFERROR(LEFT(O16, FIND(",", O16)-1), O16) | Q16: =IFERROR(IF(ISERROR(FIND(",", O16, FIND(",", O16)+1)), RIGHT(O16, LEN(O16)-FIND(",", O16)-1), MID(O16, FIND(",", O16)+2, FIND(",", O16, FIND(",", O16)+1)-FIND(",", O16)-2)), "") | R16: =IFERROR(RIGHT(O16, LEN(O16)-FIND(",", O16, FIND(",", O16)+1)-1), "") | S16: {=_xlfn.TEXTJOIN(", ",TRUE,_xlfn._xlws.FILTER(Tabla29[[#All],[PARTE]],ISNUMBER(SEARCH(Tabla29[[#All],[PCLAVE3]],Tabla8[[#This Row],[DESCRIPCION DE TRABAJO]])),""))} -> No Responde | T16: =IF(AND(Tabla8[[#This Row],[PIEZA]]="",Tabla8[[#This Row],[PARTE]]=""),"VACIO","OK") -> VACIO | U16: =+CONCATENATE(WEEKNUM(Tabla8[[#This Row],[FECHA]]),"-",YEAR(Tabla8[[#This Row],[FECHA]])) -> 1-2025
A17: 45659 | B17: Omar Nina | C17: NOCHE | D17: 0.083333333 | E17: 0.10069444 | F17: =+MOD(Tabla8[[#This Row],[HR. FIN]]-Tabla8[[#This Row],[HR. INICIO]],1) -> 0.017361111 | G17: 5TO PISO | H17: =IFERROR(VLOOKUP(G17,DATOS!$M$2:$N$219,2,FALSE),"") -> Area | I17: Trabajos menores | J17: =+VLOOKUP($I17,Tabla7[#All],2,FALSE) -> PROGRAMADA | K17: =IF(VLOOKUP(I17,Tabla7[#All],3,FALSE)=0,"",VLOOKUP(I17,Tabla7[#All],3,FALSE)) | L17: Se apoya a calidad colocando dispensador | N17: {=IFERROR(IF(Tabla8[[#This Row],[P/NP]]="NO PROGRAMADA","",_xlfn.TEXTJOIN(", ",TRUE,_xlfn._xlws.FILTER(Tabla4[[#All],[PIEZA]],ISNUMBER(SEARCH(Tabla4[[#All],[PCLAVE]],Tabla8[[#This Row],[DESCRIPCION DE TRABAJO]])),""))),"")} -> Dispensador | O17: {=_xlfn.TEXTJOIN(", ",TRUE,_xlfn._xlws.FILTER(Tabla28[[#All],[PARTE]],ISNUMBER(SEARCH(Tabla28[[#All],[PCLAVE2]],Tabla8[[#This Row],[DESCRIPCION DE TRABAJO]])),""))} | P17: =IFERROR(LEFT(O17, FIND(",", O17)-1), O17) | Q17: =IFERROR(IF(ISERROR(FIND(",", O17, FIND(",", O17)+1)), RIGHT(O17, LEN(O17)-FIND(",", O17)-1), MID(O17, FIND(",", O17)+2, FIND(",", O17, FIND(",", O17)+1)-FIND(",", O17)-2)), "") | R17: =IFERROR(RIGHT(O17, LEN(O17)-FIND(",", O17, FIND(",", O17)+1)-1), "") | S17: {=_xlfn.TEXTJOIN(", ",TRUE,_xlfn._xlws.FILTER(Tabla29[[#All],[PARTE]],ISNUMBER(SEARCH(Tabla29[[#All],[PCLAVE3]],Tabla8[[#This Row],[DESCRIPCION DE TRABAJO]])),""))} | T17: =IF(AND(Tabla8[[#This Row],[PIEZA]]="",Tabla8[[#This Row],[PARTE]]=""),"VACIO","OK") -> OK | U17: =+CONCATENATE(WEEKNUM(Tabla8[[#This Row],[FECHA]]),"-",YEAR(Tabla8[[#This Row],[FECHA]])) -> 1-2025
A18: 45659 | B18: Omar Nina | C18: NOCHE | D18: 0.17708333 | E18: 0.19444444 | F18: =+MOD(Tabla8[[#This Row],[HR. FIN]]-Tabla8[[#This Row],[HR. INICIO]],1) -> 0.017361111 | G18: EMP. FLOWPACK 2 | H18: =IFERROR(VLOOKUP(G18,DATOS!$M$2:$N$219,2,FALSE),"") -> Maquinaria | I18: Inspección | J18: =+VLOOKUP($I18,Tabla7[#All],2,FALSE) -> PROGRAMADA | K18: =IF(VLOOKUP(I18,Tabla7[#All],3,FALSE)=0,"",VLOOKUP(I18,Tabla7[#All],3,FALSE)) | L18: Inspeccion de equipo | N18: {=IFERROR(IF(Tabla8[[#This Row],[P/NP]]="NO PROGRAMADA","",_xlfn.TEXTJOIN(", ",TRUE,_xlfn._xlws.FILTER(Tabla4[[#All],[PIEZA]],ISNUMBER(SEARCH(Tabla4[[#All],[PCLAVE]],Tabla8[[#This Row],[DESCRIPCION DE TRABAJO]])),""))),"")} | O18: {=_xlfn.TEXTJOIN(", ",TRUE,_xlfn._xlws.FILTER(Tabla28[[#All],[PARTE]],ISNUMBER(SEARCH(Tabla28[[#All],[PCLAVE2]],Tabla8[[#This Row],[DESCRIPCION DE TRABAJO]])),""))} | P18: =IFERROR(LEFT(O18, FIND(",", O18)-1), O18) | Q18: =IFERROR(IF(ISERROR(FIND(",", O18, FIND(",", O18)+1)), RIGHT(O18, LEN(O18)-FIND(",", O18)-1), MID(O18, FIND(",", O18)+2, FIND(",", O18, FIND(",", O18)+1)-FIND(",", O18)-2)), "") | R18: =IFERROR(RIGHT(O18, LEN(O18)-FIND(",", O18, FIND(",", O18)+1)-1), "") | S18: {=_xlfn.TEXTJOIN(", ",TRUE,_xlfn._xlws.FILTER(Tabla29[[#All],[PARTE]],ISNUMBER(SEARCH(Tabla29[[#All],[PCLAVE3]],Tabla8[[#This Row],[DESCRIPCION DE TRABAJO]])),""))} | T18: =IF(AND(Tabla8[[#This Row],[PIEZA]]="",Tabla8[[#This Row],[PARTE]]=""),"VACIO","OK") -> VACIO | U18: =+CONCATENATE(WEEKNUM(Tabla8[[#This Row],[FECHA]]),"-",YEAR(Tabla8[[#This Row],[FECHA]])) -> 1-2025
A19: 45659 | B19: Carlos Puma | C19: TARDE | D19: 0.55902778 | E19: 0.57638889 | F19: =+MOD(Tabla8[[#This Row],[HR. FIN]]-Tabla8[[#This Row],[HR. INICIO]],1) -> 0.017361111 | G19: FORRADORA AUTOMATICA | H19: =IFERROR(VLOOKUP(G19,DATOS!$M$2:$N$219,2,FALSE),"") -> Maquinaria | I19: Ajuste /Calibracion | J19: =+VLOOKUP($I19,Tabla7[#All],2,FALSE) -> NO PROGRAMADA | K19: =IF(VLOOKUP(I19,Tabla7[#All],3,FALSE)=0,"",VLOOKUP(I19,Tabla7[#All],3,FALSE)) -> MECÁNICA | L19: Faja detenida | M19: Se alineo faja y se dio seguimiento | N19: {=IFERROR(IF(Tabla8[[#This Row],[P/NP]]="NO PROGRAMADA","",_xlfn.TEXTJOIN(", ",TRUE,_xlfn._xlws.FILTER(Tabla4[[#All],[PIEZA]],ISNUMBER(SEARCH(Tabla4[[#All],[PCLAVE]],Tabla8[[#This Row],[DESCRIPCION DE TRABAJO]])),""))),"")} | O19: {=_xlfn.TEXTJOIN(", ",TRUE,_xlfn._xlws.FILTER(Tabla28[[#All],[PARTE]],ISNUMBER(SEARCH(Tabla28[[#All],[PCLAVE2]],Tabla8[[#This Row],[DESCRIPCION DE TRABAJO]])),""))} | P19: =IFERROR(LEFT(O19, FIND(",", O19)-1), O19) | Q19: =IFERROR(IF(ISERROR(FIND(",", O19, FIND(",", O19)+1)), RIGHT(O19, LEN(O19)-FIND(",", O19)-1), MID(O19, FIND(",", O19)+2, FIND(",", O19, FIND(",", O19)+1)-FIND(",", O19)-2)), "") | R19: =IFERROR(RIGHT(O19, LEN(O19)-FIND(",", O19, FIND(",", O19)+1)-1), "") | S19: {=_xlfn.TEXTJOIN(", ",TRUE,_xlfn._xlws.FILTER(Tabla29[[#All],[PARTE]],ISNUMBER(SEARCH(Tabla29[[#All],[PCLAVE3]],Tabla8[[#This Row],[DESCRIPCION DE TRABAJO]])),""))} -> Detenido, Detenido | T19: =IF(AND(Tabla8[[#This Row],[PIEZA]]="",Tabla8[[#This Row],[PARTE]]=""),"VACIO","OK") -> VACIO | U19: =+CONCATENATE(WEEKNUM(Tabla8[[#This Row],[FECHA]]),"-",YEAR(Tabla8[[#This Row],[FECHA]])) -> 1-2025
A20: 45659 | B20: Carlos Puma | C20: TARDE | D20: 0.72222222 | E20: 0.73611111 | F20: =+MOD(Tabla8[[#This Row],[HR. FIN]]-Tabla8[[#This Row],[HR. INICIO]],1) -> 0.013888889 | G20: NETCH | H20: =IFERROR(VLOOKUP(G20,DATOS!$M$2:$N$219,2,FALSE),"") -> Maquinaria | I20: Limpieza | J20: =+VLOOKUP($I20,Tabla7[#All],2,FALSE) -> PROGRAMADA | K20: =IF(VLOOKUP(I20,Tabla7[#All],3,FALSE)=0,"",VLOOKUP(I20,Tabla7[#All],3,FALSE)) | L20: Se desarma equipo para limpieza | N20: {=IFERROR(IF(Tabla8[[#This Row],[P/NP]]="NO PROGRAMADA","",_xlfn.TEXTJOIN(", ",TRUE,_xlfn._xlws.FILTER(Tabla4[[#All],[PIEZA]],ISNUMBER(SEARCH(Tabla4[[#All],[PCLAVE]],Tabla8[[#This Row],[DESCRIPCION DE TRABAJO]])),""))),"")} | O20: {=_xlfn.TEXTJOIN(", ",TRUE,_xlfn._xlws.FILTER(Tabla28[[#All],[PARTE]],ISNUMBER(SEARCH(Tabla28[[#All],[PCLAVE2]],Tabla8[[#This Row],[DESCRIPCION DE TRABAJO]])),""))} | P20: =IFERROR(LEFT(O20, FIND(",", O20)-1), O20) | Q20: =IFERROR(IF(ISERROR(FIND(",", O20, FIND(",", O20)+1)), RIGHT(O20, LEN(O20)-FIND(",", O20)-1), MID(O20, FIND(",", O20)+2, FIND(",", O20, FIND(",", O20)+1)-FIND(",", O20)-2)), "") | R20: =IFERROR(RIGHT(O20, LEN(O20)-FIND(",", O20, FIND(",", O20)+1)-1), "") | S20: {=_xlfn.TEXTJOIN(", ",TRUE,_xlfn._xlws.FILTER(Tabla29[[#All],[PARTE]],ISNUMBER(SEARCH(Tabla29[[#All],[PCLAVE3]],Tabla8[[#This Row],[DESCRIPCION DE TRABAJO]])),""))} | T20: =IF(AND(Tabla8[[#This Row],[PIEZA]]="",Tabla8[[#This Row],[PARTE]]=""),"VACIO","OK") -> VACIO | U20: =+CONCATENATE(WEEKNUM(Tabla8[[#This Row],[FECHA]]),"-",YEAR(Tabla8[[#This Row],[FECHA]])) -> 1-2025
A21: 45659 | B21: Omar Nina | C21: NOCHE | D21: 0.055555556 | E21: 0.069444444 | F21: =+MOD(Tabla8[[#This Row],[HR. FIN]]-Tabla8[[#This Row],[HR. INICIO]],1) -> 0.013888889 | G21: HACOS 1 | H21: =IFERROR(VLOOKUP(G21,DATOS!$M$2:$N$219,2,FALSE),"") -> Maquinaria | I21: Inspección | J21: =+VLOOKUP($I21,Tabla7[#All],2,FALSE) -> PROGRAMADA | K21: =IF(VLOOKUP(I21,Tabla7[#All],3,FALSE)=0,"",VLOOKUP(I21,Tabla7[#All],3,FALSE)) | L21: Inspeccion de funcionamiento de maquinas | N21: {=IFERROR(IF(Tabla8[[#This Row],[P/NP]]="NO PROGRAMADA","",_xlfn.TEXTJOIN(", ",TRUE,_xlfn._xlws.FILTER(Tabla4[[#All],[PIEZA]],ISNUMBER(SEARCH(Tabla4[[#All],[PCLAVE]],Tabla8[[#This Row],[DESCRIPCION DE TRABAJO]])),""))),"")} | O21: {=_xlfn.TEXTJOIN(", ",TRUE,_xlfn._xlws.FILTER(Tabla28[[#All],[PARTE]],ISNUMBER(SEARCH(Tabla28[[#All],[PCLAVE2]],Tabla8[[#This Row],[DESCRIPCION DE TRABAJO]])),""))} | P21: =IFERROR(LEFT(O21, FIND(",", O21)-1), O21) | Q21: =IFERROR(IF(ISERROR(FIND(",", O21, FIND(",", O21)+1)), RIGHT(O21, LEN(O21)-FIND(",", O21)-1), MID(O21, FIND(",", O21)+2, FIND(",", O21, FIND(",", O21)+1)-FIND(",", O21)-2)), "") | R21: =IFERROR(RIGHT(O21, LEN(O21)-FIND(",", O21, FIND(",", O21)+1)-1), "") | S21: {=_xlfn.TEXTJOIN(", ",TRUE,_xlfn._xlws.FILTER(Tabla29[[#All],[PARTE]],ISNUMBER(SEARCH(Tabla29[[#All],[PCLAVE3]],Tabla8[[#This Row],[DESCRIPCION DE TRABAJO]])),""))} | T21: =IF(AND(Tabla8[[#This Row],[PIEZA]]="",Tabla8[[#This Row],[PARTE]]=""),"VACIO","OK") -> VACIO | U21: =+CONCATENATE(WEEKNUM(Tabla8[[#This Row],[FECHA]]),"-",YEAR(Tabla8[[#This Row],[FECHA]])) -> 1-2025
A22: 45659 | B22: Omar Nina | C22: NOCHE | D22: 0.9375 | E22: 0.95138889 | F22: =+MOD(Tabla8[[#This Row],[HR. FIN]]-Tabla8[[#This Row],[HR. INICIO]],1) -> 0.013888889 | G22: HANSEL | H22: =IFERROR(VLOOKUP(G22,DATOS!$M$2:$N$219,2,FALSE),"") -> Maquinaria | I22: Inspección | J22: =+VLOOKUP($I22,Tabla7[#All],2,FALSE) -> PROGRAMADA | K22: =IF(VLOOKUP(I22,Tabla7[#All],3,FALSE)=0,"",VLOOKUP(I22,Tabla7[#All],3,FALSE)) | L22: Inspeccion de equipo | N22: {=IFERROR(IF(Tabla8[[#This Row],[P/NP]]="NO PROGRAMADA","",_xlfn.TEXTJOIN(", ",TRUE,_xlfn._xlws.FILTER(Tabla4[[#All],[PIEZA]],ISNUMBER(SEARCH(Tabla4[[#All],[PCLAVE]],Tabla8[[#This Row],[DESCRIPCION DE TRABAJO]])),""))),"")} | O22: {=_xlfn.TEXTJOIN(", ",TRUE,_xlfn._xlws.FILTER(Tabla28[[#All],[PARTE]],ISNUMBER(SEARCH(Tabla28[[#All],[PCLAVE2]],Tabla8[[#This Row],[DESCRIPCION DE TRABAJO]])),""))} | P22: =IFERROR(LEFT(O22, FIND(",", O22)-1), O22) | Q22: =IFERROR(IF(ISERROR(FIND(",", O22, FIND(",", O22)+1)), RIGHT(O22, LEN(O22)-FIND(",", O22)-1), MID(O22, FIND(",", O22)+2, FIND(",", O22, FIND(",", O22)+1)-FIND(",", O22)-2)), "") | R22: =IFERROR(RIGHT(O22, LEN(O22)-FIND(",", O22, FIND(",", O22)+1)-1), "") | S22: {=_xlfn.TEXTJOIN(", ",TRUE,_xlfn._xlws.FILTER(Tabla29[[#All],[PARTE]],ISNUMBER(SEARCH(Tabla29[[#All],[PCLAVE3]],Tabla8[[#This Row],[DESCRIPCION DE TRABAJO]])),""))} | T22: =IF(AND(Tabla8[[#This Row],[PIEZA]]="",Tabla8[[#This Row],[PARTE]]=""),"VACIO","OK") -> VACIO | U22: =+CONCATENATE(WEEKNUM(Tabla8[[#This Row],[FECHA]]),"-",YEAR(Tabla8[[#This Row],[FECHA]])) -> 1-2025
A23: 45659 | B23: Cesar Quiroz | C23: MAÑANA | D23: 0.37777778 | E23: 0.39097222 | F23: =+MOD(Tabla8[[#This Row],[HR. FIN]]-Tabla8[[#This Row],[HR. INICIO]],1) -> 0.013194444 | G23: EMP. FLOWPACK 2 | H23: =IFERROR(VLOOKUP(G23,DATOS!$M$2:$N$219,2,FALSE),"") -> Maquinaria | I23: Ajuste /Calibracion | J23: =+VLOOKUP($I23,Tabla7[#All],2,FALSE) -> NO PROGRAMADA | K23: =IF(VLOOKUP(I23,Tabla7[#All],3,FALSE)=0,"",VLOOKUP(I23,Tabla7[#All],3,FALSE)) -> MECÁNICA | L23: Laminado se mueve nose puede calibrar | M23: Se apoyo en la alineacion de laminado. Se realizo pruebas | N23: {=IFERROR(IF(Tabla8[[#This Row],[P/NP]]="NO PROGRAMADA","",_xlfn.TEXTJOIN(", ",TRUE,_xlfn._xlws.FILTER(Tabla4[[#All],[PIEZA]],ISNUMBER(SEARCH(Tabla4[[#All],[PCLAVE]],Tabla8[[#This Row],[DESCRIPCION DE TRABAJO]])),""))),"")} | O23: {=_xlfn.TEXTJOIN(", ",TRUE,_xlfn._xlws.FILTER(Tabla28[[#All],[PARTE]],ISNUMBER(SEARCH(Tabla28[[#All],[PCLAVE2]],Tabla8[[#This Row],[DESCRIPCION DE TRABAJO]])),""))} | P23: =IFERROR(LEFT(O23, FIND(",", O23)-1), O23) | Q23: =IFERROR(IF(ISERROR(FIND(",", O23, FIND(",", O23)+1)), RIGHT(O23, LEN(O23)-FIND(",", O23)-1), MID(O23, FIND(",", O23)+2, FIND(",", O23, FIND(",", O23)+1)-FIND(",", O23)-2)), "") | R23: =IFERROR(RIGHT(O23, LEN(O23)-FIND(",", O23, FIND(",", O23)+1)-1), "") | S23: {=_xlfn.TEXTJOIN(", ",TRUE,_xlfn._xlws.FILTER(Tabla29[[#All],[PARTE]],ISNUMBER(SEARCH(Tabla29[[#All],[PCLAVE3]],Tabla8[[#This Row],[DESCRIPCION DE TRABAJO]])),""))} -> Calibracion, Laminado | T23: =IF(AND(Tabla8[[#This Row],[PIEZA]]="",Tabla8[[#This Row],[PARTE]]=""),"VACIO","OK") -> VACIO | U23: =+CONCATENATE(WEEKNUM(Tabla8[[#This Row],[FECHA]]),"-",YEAR(Tabla8[[#This Row],[FECHA]])) -> 1-2025
A24: 45659 | B24: Omar Nina | C24: NOCHE | D24: 0.95555556 | E24: 0.96875 | F24: =+MOD(Tabla8[[#This Row],[HR. FIN]]-Tabla8[[#This Row],[HR. INICIO]],1) -> 0.013194444 | G24: MINIFLEX | H24: =IFERROR(VLOOKUP(G24,DATOS!$M$2:$N$219,2,FALSE),"") -> Maquinaria | I24: Ajuste /Calibracion | J24: =+VLOOKUP($I24,Tabla7[#All],2,FALSE) -> NO PROGRAMADA | K24: =IF(VLOOKUP(I24,Tabla7[#All],3,FALSE)=0,"",VLOOKUP(I24,Tabla7[#All],3,FALSE)) -> MECÁNICA | L24: Al sellar hace agujeros en la parte inferior de la caja | M24: Se cambio posicion de teflones de sellado, se hace preubas con producto. Queda operativo | N24: {=IFERROR(IF(Tabla8[[#This Row],[P/NP]]="NO PROGRAMADA","",_xlfn.TEXTJOIN(", ",TRUE,_xlfn._xlws.FILTER(Tabla4[[#All],[PIEZA]],ISNUMBER(SEARCH(Tabla4[[#All],[PCLAVE]],Tabla8[[#This Row],[DESCRIPCION DE TRABAJO]])),""))),"")} | O24: {=_xlfn.TEXTJOIN(", ",TRUE,_xlfn._xlws.FILTER(Tabla28[[#All],[PARTE]],ISNUMBER(SEARCH(Tabla28[[#All],[PCLAVE2]],Tabla8[[#This Row],[DESCRIPCION DE TRABAJO]])),""))} | P24: =IFERROR(LEFT(O24, FIND(",", O24)-1), O24) | Q24: =IFERROR(IF(ISERROR(FIND(",", O24, FIND(",", O24)+1)), RIGHT(O24, LEN(O24)-FIND(",", O24)-1), MID(O24, FIND(",", O24)+2, FIND(",", O24, FIND(",", O24)+1)-FIND(",", O24)-2)), "") | R24: =IFERROR(RIGHT(O24, LEN(O24)-FIND(",", O24, FIND(",", O24)+1)-1), "") | S24: {=_xlfn.TEXTJOIN(", ",TRUE,_xlfn._xlws.FILTER(Tabla29[[#All],[PARTE]],ISNUMBER(SEARCH(Tabla29[[#All],[PCLAVE3]],Tabla8[[#This Row],[DESCRIPCION DE TRABAJO]])),""))} -> Con Agujeros | T24: =IF(AND(Tabla8[[#This Row],[PIEZA]]="",Tabla8[[#This Row],[PARTE]]=""),"VACIO","OK") -> VACIO | U24: =+CONCATENATE(WEEKNUM(Tabla8[[#This Row],[FECHA]]),"-",YEAR(Tabla8[[#This Row],[FECHA]])) -> 1-2025
A25: 45659 | B25: Omar Nina | C25: NOCHE | D25: 1.0277778 | E25: 1.0402778 | F25: =+MOD(Tabla8[[#This Row],[HR. FIN]]-Tabla8[[#This Row],[HR. INICIO]],1) -> 0.0125 | G25: MOLINO REBOTE | H25: =IFERROR(VLOOKUP(G25,DATOS!$M$2:$N$219,2,FALSE),"") -> Maquinaria | I25: Limpieza | J25: =+VLOOKUP($I25,Tabla7[#All],2,FALSE) -> PROGRAMADA | K25: =IF(VLOOKUP(I25,Tabla7[#All],3,FALSE)=0,"",VLOOKUP(I25,Tabla7[#All],3,FALSE)) | L25: No deja encender, sale alarma | M25: Se limpio sensor y se encendio. Se deja trabajando | N25: {=IFERROR(IF(Tabla8[[#This Row],[P/NP]]="NO PROGRAMADA","",_xlfn.TEXTJOIN(", ",TRUE,_xlfn._xlws.FILTER(Tabla4[[#All],[PIEZA]],ISNUMBER(SEARCH(Tabla4[[#All],[PCLAVE]],Tabla8[[#This Row],[DESCRIPCION DE TRABAJO]])),""))),"")} | O25: {=_xlfn.TEXTJOIN(", ",TRUE,_xlfn._xlws.FILTER(Tabla28[[#All],[PARTE]],ISNUMBER(SEARCH(Tabla28[[#All],[PCLAVE2]],Tabla8[[#This Row],[DESCRIPCION DE TRABAJO]])),""))} | P25: =IFERROR(LEFT(O25, FIND(",", O25)-1), O25) | Q25: =IFERROR(IF(ISERROR(FIND(",", O25, FIND(",", O25)+1)), RIGHT(O25, LEN(O25)-FIND(",", O25)-1), MID(O25, FIND(",", O25)+2, FIND(",", O25, FIND(",", O25)+1)-FIND(",", O25)-2)), "") | R25: =IFERROR(RIGHT(O25, LEN(O25)-FIND(",", O25, FIND(",", O25)+1)-1), "") | S25: {=_xlfn.TEXTJOIN(", ",TRUE,_xlfn._xlws.FILTER(Tabla29[[#All],[PARTE]],ISNUMBER(SEARCH(Tabla29[[#All],[PCLAVE3]],Tabla8[[#This Row],[DESCRIPCION DE TRABAJO]])),""))} -> Alarma | T25: =IF(AND(Tabla8[[#This Row],[PIEZA]]="",Tabla8[[#This Row],[PARTE]]=""),"VACIO","OK") -> VACIO | U25: =+CONCATENATE(WEEKNUM(Tabla8[[#This Row],[FECHA]]),"-",YEAR(Tabla8[[#This Row],[FECHA]])) -> 1-2025
A26: 45659 | B26: Cesar Quiroz | C26: MAÑANA | D26: 0.47083333 | E26: 0.48333333 | F26: =+MOD(Tabla8[[#This Row],[HR. FIN]]-Tabla8[[#This Row],[HR. INICIO]],1) -> 0.0125 | G26: CYCLOP | H26: =IFERROR(VLOOKUP(G26,DATOS!$M$2:$N$219,2,FALSE),"") -> Maquinaria | I26: Inspección | J26: =+VLOOKUP($I26,Tabla7[#All],2,FALSE) -> PROGRAMADA | K26: =IF(VLOOKUP(I26,Tabla7[#All],3,FALSE)=0,"",VLOOKUP(I26,Tabla7[#All],3,FALSE)) | L26: Revision de funcionamiento | N26: {=IFERROR(IF(Tabla8[[#This Row],[P/NP]]="NO PROGRAMADA","",_xlfn.TEXTJOIN(", ",TRUE,_xlfn._xlws.FILTER(Tabla4[[#All],[PIEZA]],ISNUMBER(SEARCH(Tabla4[[#All],[PCLAVE]],Tabla8[[#This Row],[DESCRIPCION DE TRABAJO]])),""))),"")} | O26: {=_xlfn.TEXTJOIN(", ",TRUE,_xlfn._xlws.FILTER(Tabla28[[#All],[PARTE]],ISNUMBER(SEARCH(Tabla28[[#All],[PCLAVE2]],Tabla8[[#This Row],[DESCRIPCION DE TRABAJO]])),""))} | P26: =IFERROR(LEFT(O26, FIND(",", O26)-1), O26) | Q26: =IFERROR(IF(ISERROR(FIND(",", O26, FIND(",", O26)+1)), RIGHT(O26, LEN(O26)-FIND(",", O26)-1), MID(O26, FIND(",", O26)+2, FIND(",", O26, FIND(",", O26)+1)-FIND(",", O26)-2)), "") | R26: =IFERROR(RIGHT(O26, LEN(O26)-FIND(",", O26, FIND(",", O26)+1)-1), "") | S26: {=_xlfn.TEXTJOIN(", ",TRUE,_xlfn._xlws.FILTER(Tabla29[[#All],[PARTE]],ISNUMBER(SEARCH(Tabla29[[#All],[PCLAVE3]],Tabla8[[#This Row],[DESCRIPCION DE TRABAJO]])),""))} | T26: =IF(AND(Tabla8[[#This Row],[PIEZA]]="",Tabla8[[#This Row],[PARTE]]=""),"VACIO","OK") -> VACIO | U26: =+CONCATENATE(WEEKNUM(Tabla8[[#This Row],[FECHA]]),"-",YEAR(Tabla8[[#This Row],[FECHA]])) -> 1-2025
A27: 45659 | B27: Cesar Quiroz | C27: MAÑANA | D27: 0.39305556 | E27: 0.40555556 | F27: =+MOD(Tabla8[[#This Row],[HR. FIN]]-Tabla8[[#This Row],[HR. INICIO]],1) -> 0.0125 | G27: EMP. FLOWPACK 2 | H27: =IFERROR(VLOOKUP(G27,DATOS!$M$2:$N$219,2,FALSE),"") -> Maquinaria | I27: Ajuste /Calibracion | J27: =+VLOOKUP($I27,Tabla7[#All],2,FALSE) -> NO PROGRAMADA | K27: =IF(VLOOKUP(I27,Tabla7[#All],3,FALSE)=0,"",VLOOKUP(I27,Tabla7[#All],3,FALSE)) -> MECÁNICA | L27: Alineacion de guiadores, regularizacion de sensor | N27: {=IFERROR(IF(Tabla8[[#This Row],[P/NP]]="NO PROGRAMADA","",_xlfn.TEXTJOIN(", ",TRUE,_xlfn._xlws.FILTER(Tabla4[[#All],[PIEZA]],ISNUMBER(SEARCH(Tabla4[[#All],[PCLAVE]],Tabla8[[#This Row],[DESCRIPCION DE TRABAJO]])),""))),"")} | O27: {=_xlfn.TEXTJOIN(", ",TRUE,_xlfn._xlws.FILTER(Tabla28[[#All],[PARTE]],ISNUMBER(SEARCH(Tabla28[[#All],[PCLAVE2]],Tabla8[[#This Row],[DESCRIPCION DE TRABAJO]])),""))} | P27: =IFERROR(LEFT(O27, FIND(",", O27)-1), O27) | Q27: =IFERROR(IF(ISERROR(FIND(",", O27, FIND(",", O27)+1)), RIGHT(O27, LEN(O27)-FIND(",", O27)-1), MID(O27, FIND(",", O27)+2, FIND(",", O27, FIND(",", O27)+1)-FIND(",", O27)-2)), "") | R27: =IFERROR(RIGHT(O27, LEN(O27)-FIND(",", O27, FIND(",", O27)+1)-1), "") | S27: {=_xlfn.TEXTJOIN(", ",TRUE,_xlfn._xlws.FILTER(Tabla29[[#All],[PARTE]],ISNUMBER(SEARCH(Tabla29[[#All],[PCLAVE3]],Tabla8[[#This Row],[DESCRIPCION DE TRABAJO]])),""))} -> Desalineado | T27: =IF(AND(Tabla8[[#This Row],[PIEZA]]="",Tabla8[[#This Row],[PARTE]]=""),"VACIO","OK") -> VACIO | U27: =+CONCATENATE(WEEKNUM(Tabla8[[#This Row],[FECHA]]),"-",YEAR(Tabla8[[#This Row],[FECHA]])) -> 1-2025
A28: 45659 | B28: Carlos Puma | C28: TARDE | D28: 0.54166667 | E28: 0.55208333 | F28: =+MOD(Tabla8[[#This Row],[HR. FIN]]-Tabla8[[#This Row],[HR. INICIO]],1) -> 0.010416667 | G28: NETCH | H28: =IFERROR(VLOOKUP(G28,DATOS!$M$2:$N$219,2,FALSE),"") -> Maquinaria | I28: SET UP | J28: =+VLOOKUP($I28,Tabla7[#All],2,FALSE) -> PROGRAMADA | K28: =IF(VLOOKUP(I28,Tabla7[#All],3,FALSE)=0,"",VLOOKUP(I28,Tabla7[#All],3,FALSE)) | L28: Armado de equipo | N28: {=IFERROR(IF(Tabla8[[#This Row],[P/NP]]="NO PROGRAMADA","",_xlfn.TEXTJOIN(", ",TRUE,_xlfn._xlws.FILTER(Tabla4[[#All],[PIEZA]],ISNUMBER(SEARCH(Tabla4[[#All],[PCLAVE]],Tabla8[[#This Row],[DESCRIPCION DE TRABAJO]])),""))),"")} | O28: {=_xlfn.TEXTJOIN(", ",TRUE,_xlfn._xlws.FILTER(Tabla28[[#All],[PARTE]],ISNUMBER(SEARCH(Tabla28[[#All],[PCLAVE2]],Tabla8[[#This Row],[DESCRIPCION DE TRABAJO]])),""))} | P28: =IFERROR(LEFT(O28, FIND(",", O28)-1), O28) | Q28: =IFERROR(IF(ISERROR(FIND(",", O28, FIND(",", O28)+1)), RIGHT(O28, LEN(O28)-FIND(",", O28)-1), MID(O28, FIND(",", O28)+2, FIND(",", O28, FIND(",", O28)+1)-FIND(",", O28)-2)), "") | R28: =IFERROR(RIGHT(O28, LEN(O28)-FIND(",", O28, FIND(",", O28)+1)-1), "") | S28: {=_xlfn.TEXTJOIN(", ",TRUE,_xlfn._xlws.FILTER(Tabla29[[#All],[PARTE]],ISNUMBER(SEARCH(Tabla29[[#All],[PCLAVE3]],Tabla8[[#This Row],[DESCRIPCION DE TRABAJO]])),""))} | T28: =IF(AND(Tabla8[[#This Row],[PIEZA]]="",Tabla8[[#This Row],[PARTE]]=""),"VACIO","OK") -> VACIO | U28: =+CONCATENATE(WEEKNUM(Tabla8[[#This Row],[FECHA]]),"-",YEAR(Tabla8[[#This Row],[FECHA]])) -> 1-2025
A29: 45659 | B29: Carlos Puma | C29: TARDE | D29: 0.85416667 | E29: 0.86458333 | F29: =+MOD(Tabla8[[#This Row],[HR. FIN]]-Tabla8[[#This Row],[HR. INICIO]],1) -> 0.010416667 | G29: GIANINI 1 - FAMAIC | H29: =IFERROR(VLOOKUP(G29,DATOS!$M$2:$N$219,2,FALSE),"") -> Maquinaria | I29: Inspección | J29: =+VLOOKUP($I29,Tabla7[#All],2,FALSE) -> PROGRAMADA | K29: =IF(VLOOKUP(I29,Tabla7[#All],3,FALSE)=0,"",VLOOKUP(I29,Tabla7[#All],3,FALSE)) | L29: Ruido al girar | M29: Se realizo pruebas y del ruido nose manifesto (ruido intermitente) | N29: {=IFERROR(IF(Tabla8[[#This Row],[P/NP]]="NO PROGRAMADA","",_xlfn.TEXTJOIN(", ",TRUE,_xlfn._xlws.FILTER(Tabla4[[#All],[PIEZA]],ISNUMBER(SEARCH(Tabla4[[#All],[PCLAVE]],Tabla8[[#This Row],[DESCRIPCION DE TRABAJO]])),""))),"")} | O29: {=_xlfn.TEXTJOIN(", ",TRUE,_xlfn._xlws.FILTER(Tabla28[[#All],[PARTE]],ISNUMBER(SEARCH(Tabla28[[#All],[PCLAVE2]],Tabla8[[#This Row],[DESCRIPCION DE TRABAJO]])),""))} | P29: =IFERROR(LEFT(O29, FIND(",", O29)-1), O29) | Q29: =IFERROR(IF(ISERROR(FIND(",", O29, FIND(",", O29)+1)), RIGHT(O29, LEN(O29)-FIND(",", O29)-1), MID(O29, FIND(",", O29)+2, FIND(",", O29, FIND(",", O29)+1)-FIND(",", O29)-2)), "") | R29: =IFERROR(RIGHT(O29, LEN(O29)-FIND(",", O29, FIND(",", O29)+1)-1), "") | S29: {=_xlfn.TEXTJOIN(", ",TRUE,_xlfn._xlws.FILTER(Tabla29[[#All],[PARTE]],ISNUMBER(SEARCH(Tabla29[[#All],[PCLAVE3]],Tabla8[[#This Row],[DESCRIPCION DE TRABAJO]])),""))} -> Ruido | T29: =IF(AND(Tabla8[[#This Row],[PIEZA]]="",Tabla8[[#This Row],[PARTE]]=""),"VACIO","OK") -> VACIO | U29: =+CONCATENATE(WEEKNUM(Tabla8[[#This Row],[FECHA]]),"-",YEAR(Tabla8[[#This Row],[FECHA]])) -> 1-2025
A30: 45659 | B30: Carlos Puma | C30: TARDE | D30: 0.78125 | E30: 0.79166667 | F30: =+MOD(Tabla8[[#This Row],[HR. FIN]]-Tabla8[[#This Row],[HR. INICIO]],1) -> 0.010416667 | G30: HACOS 1 | H30: =IFERROR(VLOOKUP(G30,DATOS!$M$2:$N$219,2,FALSE),"") -> Maquinaria | I30: Inspección | J30: =+VLOOKUP($I30,Tabla7[#All],2,FALSE) -> PROGRAMADA | K30: =IF(VLOOKUP(I30,Tabla7[#All],3,FALSE)=0,"",VLOOKUP(I30,Tabla7[#All],3,FALSE)) | L30: Inspeccion de equipo (piston C-14) | N30: {=IFERROR(IF(Tabla8[[#This Row],[P/NP]]="NO PROGRAMADA","",_xlfn.TEXTJOIN(", ",TRUE,_xlfn._xlws.FILTER(Tabla4[[#All],[PIEZA]],ISNUMBER(SEARCH(Tabla4[[#All],[PCLAVE]],Tabla8[[#This Row],[DESCRIPCION DE TRABAJO]])),""))),"")} -> Piston(es) | O30: {=_xlfn.TEXTJOIN(", ",TRUE,_xlfn._xlws.FILTER(Tabla28[[#All],[PARTE]],ISNUMBER(SEARCH(Tabla28[[#All],[PCLAVE2]],Tabla8[[#This Row],[DESCRIPCION DE TRABAJO]])),""))} | P30: =IFERROR(LEFT(O30, FIND(",", O30)-1), O30) | Q30: =IFERROR(IF(ISERROR(FIND(",", O30, FIND(",", O30)+1)), RIGHT(O30, LEN(O30)-FIND(",", O30)-1), MID(O30, FIND(",", O30)+2, FIND(",", O30, FIND(",", O30)+1)-FIND(",", O30)-2)), "") | R30: =IFERROR(RIGHT(O30, LEN(O30)-FIND(",", O30, FIND(",", O30)+1)-1), "") | S30: {=_xlfn.TEXTJOIN(", ",TRUE,_xlfn._xlws.FILTER(Tabla29[[#All],[PARTE]],ISNUMBER(SEARCH(Tabla29[[#All],[PCLAVE3]],Tabla8[[#This Row],[DESCRIPCION DE TRABAJO]])),""))} | T30: =IF(AND(Tabla8[[#This Row],[PIEZA]]="",Tabla8[[#This Row],[PARTE]]=""),"VACIO","OK") -> OK | U30: =+CONCATENATE(WEEKNUM(Tabla8[[#This Row],[FECHA]]),"-",YEAR(Tabla8[[#This Row],[FECHA]])) -> 1-2025
A31: 45659 | B31: Omar Nina | C31: NOCHE | D31: 1.0138889 | E31: 1.0236111 | F31: =+MOD(Tabla8[[#This Row],[HR. FIN]]-Tabla8[[#This Row],[HR. INICIO]],1) -> 0.0097222222 | G31: EMP. AMP ROSE | H31: =IFERROR(VLOOKUP(G31,DATOS!$M$2:$N$219,2,FALSE),"") -> Maquinaria | I31: Ajuste /Calibracion | J31: =+VLOOKUP($I31,Tabla7[#All],2,FALSE) -> NO PROGRAMADA | K31: =IF(VLOOKUP(I31,Tabla7[#All],3,FALSE)=0,"",VLOOKUP(I31,Tabla7[#All],3,FALSE)) -> MECÁNICA | L31: Cuchilla no corta | M31: Se calibro cuchilla | N31: {=IFERROR(IF(Tabla8[[#This Row],[P/NP]]="NO PROGRAMADA","",_xlfn.TEXTJOIN(", ",TRUE,_xlfn._xlws.FILTER(Tabla4[[#All],[PIEZA]],ISNUMBER(SEARCH(Tabla4[[#All],[PCLAVE]],Tabla8[[#This Row],[DESCRIPCION DE TRABAJO]])),""))),"")} | O31: {=_xlfn.TEXTJOIN(", ",TRUE,_xlfn._xlws.FILTER(Tabla28[[#All],[PARTE]],ISNUMBER(SEARCH(Tabla28[[#All],[PCLAVE2]],Tabla8[[#This Row],[DESCRIPCION DE TRABAJO]])),""))} | P31: =IFERROR(LEFT(O31, FIND(",", O31)-1), O31) | Q31: =IFERROR(IF(ISERROR(FIND(",", O31, FIND(",", O31)+1)), RIGHT(O31, LEN(O31)-FIND(",", O31)-1), MID(O31, FIND(",", O31)+2, FIND(",", O31, FIND(",", O31)+1)-FIND(",", O31)-2)), "") | R31: =IFERROR(RIGHT(O31, LEN(O31)-FIND(",", O31, FIND(",", O31)+1)-1), "") | S31: {=_xlfn.TEXTJOIN(", ",TRUE,_xlfn._xlws.FILTER(Tabla29[[#All],[PARTE]],ISNUMBER(SEARCH(Tabla29[[#All],[PCLAVE3]],Tabla8[[#This Row],[DESCRIPCION DE TRABAJO]])),""))} -> No Corta | T31: =IF(AND(Tabla8[[#This Row],[PIEZA]]="",Tabla8[[#This Row],[PARTE]]=""),"VACIO","OK") -> VACIO | U31: =+CONCATENATE(WEEKNUM(Tabla8[[#This Row],[FECHA]]),"-",YEAR(Tabla8[[#This Row],[FECHA]])) -> 1-2025
A32: 45659 | B32: Cesar Quiroz | C32: MAÑANA | D32: 0.36666667 | E32: 0.37430556 | F32: =+MOD(Tabla8[[#This Row],[HR. FIN]]-Tabla8[[#This Row],[HR. INICIO]],1) -> 0.0076388889 | G32: HACOS 1 | H32: =IFERROR(VLOOKUP(G32,DATOS!$M$2:$N$219,2,FALSE),"") -> Maquinaria | I32: Inspección | J32: =+VLOOKUP($I32,Tabla7[#All],2,FALSE) -> PROGRAMADA | K32: =IF(VLOOKUP(I32,Tabla7[#All],3,FALSE)=0,"",VLOOKUP(I32,Tabla7[#All],3,FALSE)) | L32: Temperatura de columnas se baja | M32: Se reviso nivel de agua de tanque. Se reviso retorno, se modifico seteado de agua fria, se modifico velocidad de bomba | N32: {=IFERROR(IF(Tabla8[[#This Row],[P/NP]]="NO PROGRAMADA","",_xlfn.TEXTJOIN(", ",TRUE,_xlfn._xlws.FILTER(Tabla4[[#All],[PIEZA]],ISNUMBER(SEARCH(Tabla4[[#All],[PCLAVE]],Tabla8[[#This Row],[DESCRIPCION DE TRABAJO]])),""))),"")} | O32: {=_xlfn.TEXTJOIN(", ",TRUE,_xlfn._xlws.FILTER(Tabla28[[#All],[PARTE]],ISNUMBER(SEARCH(Tabla28[[#All],[PCLAVE2]],Tabla8[[#This Row],[DESCRIPCION DE TRABAJO]])),""))} -> Columna | P32: =IFERROR(LEFT(O32, FIND(",", O32)-1), O32) -> Columna | Q32: =IFERROR(IF(ISERROR(FIND(",", O32, FIND(",", O32)+1)), RIGHT(O32, LEN(O32)-FIND(",", O32)-1), MID(O32, FIND(",", O32)+2, FIND(",", O32, FIND(",", O32)+1)-FIND(",", O32)-2)), "") | R32: =IFERROR(RIGHT(O32, LEN(O32)-FIND(",", O32, FIND(",", O32)+1)-1), "") | S32: {=_xlfn.TEXTJOIN(", ",TRUE,_xlfn._xlws.FILTER(Tabla29[[#All],[PARTE]],ISNUMBER(SEARCH(Tabla29[[#All],[PCLAVE3]],Tabla8[[#This Row],[DESCRIPCION DE TRABAJO]])),""))} | T32: =IF(AND(Tabla8[[#This Row],[PIEZA]]="",Tabla8[[#This Row],[PARTE]]=""),"VACIO","OK") -> OK | U32: =+CONCATENATE(WEEKNUM(Tabla8[[#This Row],[FECHA]]),"-",YEAR(Tabla8[[#This Row],[FECHA]])) -> 1-2025
A33: 45659 | B33: Carlos Puma | C33: TARDE | D33: 0.60069444 | E33: 0.60763889 | F33: =+MOD(Tabla8[[#This Row],[HR. FIN]]-Tabla8[[#This Row],[HR. INICIO]],1) -> 0.0069444444 | G33: BAÑADORA DE CHOCOLATES 1 | H33: =IFERROR(VLOOKUP(G33,DATOS!$M$2:$N$219,2,FALSE),"") -> Maquinaria | I33: Limpieza | J33: =+VLOOKUP($I33,Tabla7[#All],2,FALSE) -> PROGRAMADA | K33: =IF(VLOOKUP(I33,Tabla7[#All],3,FALSE)=0,"",VLOOKUP(I33,Tabla7[#All],3,FALSE)) | L33: Se retiro filtro para limpieza | N33: {=IFERROR(IF(Tabla8[[#This Row],[P/NP]]="NO PROGRAMADA","",_xlfn.TEXTJOIN(", ",TRUE,_xlfn._xlws.FILTER(Tabla4[[#All],[PIEZA]],ISNUMBER(SEARCH(Tabla4[[#All],[PCLAVE]],Tabla8[[#This Row],[DESCRIPCION DE TRABAJO]])),""))),"")} -> Filtro | O33: {=_xlfn.TEXTJOIN(", ",TRUE,_xlfn._xlws.FILTER(Tabla28[[#All],[PARTE]],ISNUMBER(SEARCH(Tabla28[[#All],[PCLAVE2]],Tabla8[[#This Row],[DESCRIPCION DE TRABAJO]])),""))} | P33: =IFERROR(LEFT(O33, FIND(",", O33)-1), O33) | Q33: =IFERROR(IF(ISERROR(FIND(",", O33, FIND(",", O33)+1)), RIGHT(O33, LEN(O33)-FIND(",", O33)-1), MID(O33, FIND(",", O33)+2, FIND(",", O33, FIND(",", O33)+1)-FIND(",", O33)-2)), "") | R33: =IFERROR(RIGHT(O33, LEN(O33)-FIND(",", O33, FIND(",", O33)+1)-1), "") | S33: {=_xlfn.TEXTJOIN(", ",TRUE,_xlfn._xlws.FILTER(Tabla29[[#All],[PARTE]],ISNUMBER(SEARCH(Tabla29[[#All],[PCLAVE3]],Tabla8[[#This Row],[DESCRIPCION DE TRABAJO]])),""))} -> Filtracion, Sustitucion | T33: =IF(AND(Tabla8[[#This Row],[PIEZA]]="",Tabla8[[#This Row],[PARTE]]=""),"VACIO","OK") -> OK | U33: =+CONCATENATE(WEEKNUM(Tabla8[[#This Row],[FECHA]]),"-",YEAR(Tabla8[[#This Row],[FECHA]])) -> 1-2025
A34: 46027 | B34: CARLOS TAPIA | C34: MAÑANA | D34: 08:30 | E34: 09:50 | F34: =+MOD(Tabla8[[#This Row],[HR. FIN]]-Tabla8[[#This Row],[HR. INICIO]],1) -> 0.055555556 | G34: 1ER PISO | H34: =IFERROR(VLOOKUP(G34,DATOS!$M$2:$N$219,2,FALSE),"") -> Area | I34: SET UP | J34: NO PROGRAMADA | K34: MECÁNICA | L34: Bomba del tanque de retorno se encuentra obstruida. | M34: Se retiró tuberías conectadas a bomba y se retiró el trapeador que se encontraba obstruyendo el impulsor. | N34: {=IFERROR(IF(Tabla8[[#This Row],[P/NP]]="NO PROGRAMADA","",_xlfn.TEXTJOIN(", ",TRUE,_xlfn._xlws.FILTER(Tabla4[[#All],[PIEZA]],ISNUMBER(SEARCH(Tabla4[[#All],[PCLAVE]],Tabla8[[#This Row],[DESCRIPCION DE TRABAJO]])),""))),"")} | O34: {=_xlfn.TEXTJOIN(", ",TRUE,_xlfn._xlws.FILTER(Tabla28[[#All],[PARTE]],ISNUMBER(SEARCH(Tabla28[[#All],[PCLAVE2]],Tabla8[[#This Row],[DESCRIPCION DE TRABAJO]])),""))} -> Tanque | P34: =IFERROR(LEFT(O34, FIND(",", O34)-1), O34) -> Tanque | Q34: =IFERROR(IF(ISERROR(FIND(",", O34, FIND(",", O34)+1)), RIGHT(O34, LEN(O34)-FIND(",", O34)-1), MID(O34, FIND(",", O34)+2, FIND(",", O34, FIND(",", O34)+1)-FIND(",", O34)-2)), "") | R34: =IFERROR(RIGHT(O34, LEN(O34)-FIND(",", O34, FIND(",", O34)+1)-1), "") | S34: {=_xlfn.TEXTJOIN(", ",TRUE,_xlfn._xlws.FILTER(Tabla29[[#All],[PARTE]],ISNUMBER(SEARCH(Tabla29[[#All],[PCLAVE3]],Tabla8[[#This Row],[DESCRIPCION DE TRABAJO]])),""))} -> Obstruido, Ruido | T34: =IF(AND(Tabla8[[#This Row],[PIEZA]]="",Tabla8[[#This Row],[PARTE]]=""),"VACIO","OK") -> OK | U34: =+CONCATENATE(WEEKNUM(Tabla8[[#This Row],[FECHA]]),"-",YEAR(Tabla8[[#This Row],[FECHA]])) -> 2-2026
A35: 46027 | B35: CARLOS TAPIA | C35: MAÑANA | D35: 10:00 | E35: 11:00 | F35: =+MOD(Tabla8[[#This Row],[HR. FIN]]-Tabla8[[#This Row],[HR. INICIO]],1) -> 0.041666667 | G35: BARQUILLERA FRANZ HAAZ | H35: =IFERROR(VLOOKUP(G35,DATOS!$M$2:$N$219,2,FALSE),"") -> Maquinaria | I35: SET UP | J35: =+VLOOKUP($I35,Tabla7[#All],2,FALSE) -> PROGRAMADA | K35: =IF(VLOOKUP(I35,Tabla7[#All],3,FALSE)=0,"",VLOOKUP(I35,Tabla7[#All],3,FALSE)) | L35: Armar máquina para el turno tarde. | M35: Se colocó piezas en posición y se dejó habilitada para el turno tarde. | N35: {=IFERROR(IF(Tabla8[[#This Row],[P/NP]]="NO PROGRAMADA","",_xlfn.TEXTJOIN(", ",TRUE,_xlfn._xlws.FILTER(Tabla4[[#All],[PIEZA]],ISNUMBER(SEARCH(Tabla4[[#All],[PCLAVE]],Tabla8[[#This Row],[DESCRIPCION DE TRABAJO]])),""))),"")} | O35: {=_xlfn.TEXTJOIN(", ",TRUE,_xlfn._xlws.FILTER(Tabla28[[#All],[PARTE]],ISNUMBER(SEARCH(Tabla28[[#All],[PCLAVE2]],Tabla8[[#This Row],[DESCRIPCION DE TRABAJO]])),""))} | P35: =IFERROR(LEFT(O35, FIND(",", O35)-1), O35) | Q35: =IFERROR(IF(ISERROR(FIND(",", O35, FIND(",", O35)+1)), RIGHT(O35, LEN(O35)-FIND(",", O35)-1), MID(O35, FIND(",", O35)+2, FIND(",", O35, FIND(",", O35)+1)-FIND(",", O35)-2)), "") | R35: =IFERROR(RIGHT(O35, LEN(O35)-FIND(",", O35, FIND(",", O35)+1)-1), "") | S35: {=_xlfn.TEXTJOIN(", ",TRUE,_xlfn._xlws.FILTER(Tabla29[[#All],[PARTE]],ISNUMBER(SEARCH(Tabla29[[#All],[PCLAVE3]],Tabla8[[#This Row],[DESCRIPCION DE TRABAJO]])),""))} | T35: =IF(AND(Tabla8[[#This Row],[PIEZA]]="",Tabla8[[#This Row],[PARTE]]=""),"VACIO","OK") -> VACIO | U35: =+CONCATENATE(WEEKNUM(Tabla8[[#This Row],[FECHA]]),"-",YEAR(Tabla8[[#This Row],[FECHA]])) -> 2-2026
A36: 46027 | B36: CARLOS TAPIA | C36: MAÑANA | D36: 05:30 | E36: 06:20 | F36: =+MOD(Tabla8[[#This Row],[HR. FIN]]-Tabla8[[#This Row],[HR. INICIO]],1) -> 0.034722222 | G36: PLANTA INDUSTRIAL | H36: =IFERROR(VLOOKUP(G36,DATOS!$M$2:$N$219,2,FALSE),"") -> Area | I36: Encendido / Arranque de linea | J36: =+VLOOKUP($I36,Tabla7[#All],2,FALSE) -> PROGRAMADA | K36: =IF(VLOOKUP(I36,Tabla7[#All],3,FALSE)=0,"",VLOOKUP(I36,Tabla7[#All],3,FALSE)) | L36: Arranque de planta. | M36: Se encendió líneas de vapor agua y aire. Se revisó y encendió equipos. | N36: {=IFERROR(IF(Tabla8[[#This Row],[P/NP]]="NO PROGRAMADA","",_xlfn.TEXTJOIN(", ",TRUE,_xlfn._xlws.FILTER(Tabla4[[#All],[PIEZA]],ISNUMBER(SEARCH(Tabla4[[#All],[PCLAVE]],Tabla8[[#This Row],[DESCRIPCION DE TRABAJO]])),""))),"")} | O36: {=_xlfn.TEXTJOIN(", ",TRUE,_xlfn._xlws.FILTER(Tabla28[[#All],[PARTE]],ISNUMBER(SEARCH(Tabla28[[#All],[PCLAVE2]],Tabla8[[#This Row],[DESCRIPCION DE TRABAJO]])),""))} | P36: =IFERROR(LEFT(O36, FIND(",", O36)-1), O36) | Q36: =IFERROR(IF(ISERROR(FIND(",", O36, FIND(",", O36)+1)), RIGHT(O36, LEN(O36)-FIND(",", O36)-1), MID(O36, FIND(",", O36)+2, FIND(",", O36, FIND(",", O36)+1)-FIND(",", O36)-2)), "") | R36: =IFERROR(RIGHT(O36, LEN(O36)-FIND(",", O36, FIND(",", O36)+1)-1), "") | S36: {=_xlfn.TEXTJOIN(", ",TRUE,_xlfn._xlws.FILTER(Tabla29[[#All],[PARTE]],ISNUMBER(SEARCH(Tabla29[[#All],[PCLAVE3]],Tabla8[[#This Row],[DESCRIPCION DE TRABAJO]])),""))} | T36: =IF(AND(Tabla8[[#This Row],[PIEZA]]="",Tabla8[[#This Row],[PARTE]]=""),"VACIO","OK") -> VACIO | U36: =+CONCATENATE(WEEKNUM(Tabla8[[#This Row],[FECHA]]),"-",YEAR(Tabla8[[#This Row],[FECHA]])) -> 2-2026
A37: 46027 | B37: CARLOS TAPIA | C37: MAÑANA | D37: 12:40 | E37: 13:30 | F37: =+MOD(Tabla8[[#This Row],[HR. FIN]]-Tabla8[[#This Row],[HR. INICIO]],1) -> 0.034722222 | G37: COCINADORA 3 - GIANNINI | H37: =IFERROR(VLOOKUP(G37,DATOS!$M$2:$N$219,2,FALSE),"") -> Maquinaria | I37: Sustitucion | J37: =+VLOOKUP($I37,Tabla7[#All],2,FALSE) -> NO PROGRAMADA | K37: MECÁNICA | L37: Fuga de vapor por empaque (brida). | M37: Se retiró brida para el reemplazo de empaque. Se dejó operativa. | N37: {=IFERROR(IF(Tabla8[[#This Row],[P/NP]]="NO PROGRAMADA","",_xlfn.TEXTJOIN(", ",TRUE,_xlfn._xlws.FILTER(Tabla4[[#All],[PIEZA]],ISNUMBER(SEARCH(Tabla4[[#All],[PCLAVE]],Tabla8[[#This Row],[DESCRIPCION DE TRABAJO]])),""))),"")} | O37: {=_xlfn.TEXTJOIN(", ",TRUE,_xlfn._xlws.FILTER(Tabla28[[#All],[PARTE]],ISNUMBER(SEARCH(Tabla28[[#All],[PCLAVE2]],Tabla8[[#This Row],[DESCRIPCION DE TRABAJO]])),""))} | P37: =IFERROR(LEFT(O37, FIND(",", O37)-1), O37) | Q37: =IFERROR(IF(ISERROR(FIND(",", O37, FIND(",", O37)+1)), RIGHT(O37, LEN(O37)-FIND(",", O37)-1), MID(O37, FIND(",", O37)+2, FIND(",", O37, FIND(",", O37)+1)-FIND(",", O37)-2)), "") | R37: =IFERROR(RIGHT(O37, LEN(O37)-FIND(",", O37, FIND(",", O37)+1)-1), "") | S37: {=_xlfn.TEXTJOIN(", ",TRUE,_xlfn._xlws.FILTER(Tabla29[[#All],[PARTE]],ISNUMBER(SEARCH(Tabla29[[#All],[PCLAVE3]],Tabla8[[#This Row],[DESCRIPCION DE TRABAJO]])),""))} -> Fuga | T37: =IF(AND(Tabla8[[#This Row],[PIEZA]]="",Tabla8[[#This Row],[PARTE]]=""),"VACIO","OK") -> VACIO | U37: =+CONCATENATE(WEEKNUM(Tabla8[[#This Row],[FECHA]]),"-",YEAR(Tabla8[[#This Row],[FECHA]])) -> 2-2026
A38: 46027 | B38: CARLOS PUMA | C38: NOCHE | D38: 01:00 | E38: 01:45 | F38: =+MOD(Tabla8[[#This Row],[HR. FIN]]-Tabla8[[#This Row],[HR. INICIO]],1) -> 0.03125 | G38: QUEBRANTADOR DE CACAO 01 JAF INOX | H38: =IFERROR(VLOOKUP(G38,DATOS!$M$2:$N$219,2,FALSE),"") -> Maquinaria | I38: Ajuste /Calibracion | J38: =+VLOOKUP($I38,Tabla7[#All],2,FALSE) -> NO PROGRAMADA | K38: =IF(VLOOKUP(I38,Tabla7[#All],3,FALSE)=0,"",VLOOKUP(I38,Tabla7[#All],3,FALSE)) -> MECÁNICA | L38: Problemas con aspiración de ciclo jafinox , | M38: Se invirtió el giro de motor de aspiración y de motor de salida de cascarilla , se reviso circuito eléctrico y se realizó un puente ala bobina del contactor de motor de salida para habilitar el encendido con interruptor del teblero | N38: {=IFERROR(IF(Tabla8[[#This Row],[P/NP]]="NO PROGRAMADA","",_xlfn.TEXTJOIN(", ",TRUE,_xlfn._xlws.FILTER(Tabla4[[#All],[PIEZA]],ISNUMBER(SEARCH(Tabla4[[#All],[PCLAVE]],Tabla8[[#This Row],[DESCRIPCION DE TRABAJO]])),""))),"")} | O38: {=_xlfn.TEXTJOIN(", ",TRUE,_xlfn._xlws.FILTER(Tabla28[[#All],[PARTE]],ISNUMBER(SEARCH(Tabla28[[#All],[PCLAVE2]],Tabla8[[#This Row],[DESCRIPCION DE TRABAJO]])),""))} | P38: =IFERROR(LEFT(O38, FIND(",", O38)-1), O38) | Q38: =IFERROR(IF(ISERROR(FIND(",", O38, FIND(",", O38)+1)), RIGHT(O38, LEN(O38)-FIND(",", O38)-1), MID(O38, FIND(",", O38)+2, FIND(",", O38, FIND(",", O38)+1)-FIND(",", O38)-2)), "") | R38: =IFERROR(RIGHT(O38, LEN(O38)-FIND(",", O38, FIND(",", O38)+1)-1), "") | S38: {=_xlfn.TEXTJOIN(", ",TRUE,_xlfn._xlws.FILTER(Tabla29[[#All],[PARTE]],ISNUMBER(SEARCH(Tabla29[[#All],[PCLAVE3]],Tabla8[[#This Row],[DESCRIPCION DE TRABAJO]])),""))} | T38: =IF(AND(Tabla8[[#This Row],[PIEZA]]="",Tabla8[[#This Row],[PARTE]]=""),"VACIO","OK") -> VACIO | U38: =+CONCATENATE(WEEKNUM(Tabla8[[#This Row],[FECHA]]),"-",YEAR(Tabla8[[#This Row],[FECHA]])) -> 2-2026
A39: 46027 | B39: CARLOS PUMA | C39: NOCHE | D39: 21:55 | E39: 22:25 | F39: =+MOD(Tabla8[[#This Row],[HR. FIN]]-Tabla8[[#This Row],[HR. INICIO]],1) -> 0.020833333 | G39: LINEA AUTOMATICA HACOS 1 | H39: =IFERROR(VLOOKUP(G39,DATOS!$M$2:$N$219,2,FALSE),"") -> Maquinaria | I39: SET UP | J39: =+VLOOKUP($I39,Tabla7[#All],2,FALSE) -> PROGRAMADA | K39: =IF(VLOOKUP(I39,Tabla7[#All],3,FALSE)=0,"",VLOOKUP(I39,Tabla7[#All],3,FALSE)) | L39: Armado de mds para formato crema ovalada | N39: {=IFERROR(IF(Tabla8[[#This Row],[P/NP]]="NO PROGRAMADA","",_xlfn.TEXTJOIN(", ",TRUE,_xlfn._xlws.FILTER(Tabla4[[#All],[PIEZA]],ISNUMBER(SEARCH(Tabla4[[#All],[PCLAVE]],Tabla8[[#This Row],[DESCRIPCION DE TRABAJO]])),""))),"")} | O39: {=_xlfn.TEXTJOIN(", ",TRUE,_xlfn._xlws.FILTER(Tabla28[[#All],[PARTE]],ISNUMBER(SEARCH(Tabla28[[#All],[PCLAVE2]],Tabla8[[#This Row],[DESCRIPCION DE TRABAJO]])),""))} -> Mds | P39: =IFERROR(LEFT(O39, FIND(",", O39)-1), O39) -> Mds | Q39: =IFERROR(IF(ISERROR(FIND(",", O39, FIND(",", O39)+1)), RIGHT(O39, LEN(O39)-FIND(",", O39)-1), MID(O39, FIND(",", O39)+2, FIND(",", O39, FIND(",", O39)+1)-FIND(",", O39)-2)), "") | R39: =IFERROR(RIGHT(O39, LEN(O39)-FIND(",", O39, FIND(",", O39)+1)-1), "") | S39: {=_xlfn.TEXTJOIN(", ",TRUE,_xlfn._xlws.FILTER(Tabla29[[#All],[PARTE]],ISNUMBER(SEARCH(Tabla29[[#All],[PCLAVE3]],Tabla8[[#This Row],[DESCRIPCION DE TRABAJO]])),""))} -> Cambio De Formato | T39: =IF(AND(Tabla8[[#This Row],[PIEZA]]="",Tabla8[[#This Row],[PARTE]]=""),"VACIO","OK") -> OK | U39: =+CONCATENATE(WEEKNUM(Tabla8[[#This Row],[FECHA]]),"-",YEAR(Tabla8[[#This Row],[FECHA]])) -> 2-2026
A40: 46027 | B40: CARLOS TAPIA | C40: MAÑANA | D40: 06:30 | E40: 07:00 | F40: =+MOD(Tabla8[[#This Row],[HR. FIN]]-Tabla8[[#This Row],[HR. INICIO]],1) -> 0.020833333 | G40: LINEA AUTOMATICA HACOS 1 | H40: =IFERROR(VLOOKUP(G40,DATOS!$M$2:$N$219,2,FALSE),"") -> Maquinaria | I40: SET UP | J40: =+VLOOKUP($I40,Tabla7[#All],2,FALSE) -> PROGRAMADA | K40: =IF(VLOOKUP(I40,Tabla7[#All],3,FALSE)=0,"",VLOOKUP(I40,Tabla7[#All],3,FALSE)) | L40: Desarmar módulo MDS para su limpieza. | M40: Se desarmo módulo de MDS. | N40: {=IFERROR(IF(Tabla8[[#This Row],[P/NP]]="NO PROGRAMADA","",_xlfn.TEXTJOIN(", ",TRUE,_xlfn._xlws.FILTER(Tabla4[[#All],[PIEZA]],ISNUMBER(SEARCH(Tabla4[[#All],[PCLAVE]],Tabla8[[#This Row],[DESCRIPCION DE TRABAJO]])),""))),"")} | O40: {=_xlfn.TEXTJOIN(", ",TRUE,_xlfn._xlws.FILTER(Tabla28[[#All],[PARTE]],ISNUMBER(SEARCH(Tabla28[[#All],[PCLAVE2]],Tabla8[[#This Row],[DESCRIPCION DE TRABAJO]])),""))} -> Mds | P40: =IFERROR(LEFT(O40, FIND(",", O40)-1), O40) -> Mds | Q40: =IFERROR(IF(ISERROR(FIND(",", O40, FIND(",", O40)+1)), RIGHT(O40, LEN(O40)-FIND(",", O40)-1), MID(O40, FIND(",", O40)+2, FIND(",", O40, FIND(",", O40)+1)-FIND(",", O40)-2)), "") | R40: =IFERROR(RIGHT(O40, LEN(O40)-FIND(",", O40, FIND(",", O40)+1)-1), "") | S40: {=_xlfn.TEXTJOIN(", ",TRUE,_xlfn._xlws.FILTER(Tabla29[[#All],[PARTE]],ISNUMBER(SEARCH(Tabla29[[#All],[PCLAVE3]],Tabla8[[#This Row],[DESCRIPCION DE TRABAJO]])),""))} | T40: =IF(AND(Tabla8[[#This Row],[PIEZA]]="",Tabla8[[#This Row],[PARTE]]=""),"VACIO","OK") -> OK | U40: =+CONCATENATE(WEEKNUM(Tabla8[[#This Row],[FECHA]]),"-",YEAR(Tabla8[[#This Row],[FECHA]])) -> 2-2026
A41: 46027 | B41: CARLOS TAPIA | C41: MAÑANA | D41: 07:30 | E41: 08:00 | F41: =+MOD(Tabla8[[#This Row],[HR. FIN]]-Tabla8[[#This Row],[HR. INICIO]],1) -> 0.020833333 | G41: FORRADORA AUTOMATICA 02 | H41: =IFERROR(VLOOKUP(G41,DATOS!$M$2:$N$219,2,FALSE),"") -> Maquinaria | I41: Inspección | J41: =+VLOOKUP($I41,Tabla7[#All],2,FALSE) -> PROGRAMADA | K41: =IF(VLOOKUP(I41,Tabla7[#All],3,FALSE)=0,"",VLOOKUP(I41,Tabla7[#All],3,FALSE)) | L41: Inspección de máquina. | M41: Se revisó y se calibró la altura de la mesa Se realizó pruebas y se dejó máquina operativa. | N41: {=IFERROR(IF(Tabla8[[#This Row],[P/NP]]="NO PROGRAMADA","",_xlfn.TEXTJOIN(", ",TRUE,_xlfn._xlws.FILTER(Tabla4[[#All],[PIEZA]],ISNUMBER(SEARCH(Tabla4[[#All],[PCLAVE]],Tabla8[[#This Row],[DESCRIPCION DE TRABAJO]])),""))),"")} | O41: {=_xlfn.TEXTJOIN(", ",TRUE,_xlfn._xlws.FILTER(Tabla28[[#All],[PARTE]],ISNUMBER(SEARCH(Tabla28[[#All],[PCLAVE2]],Tabla8[[#This Row],[DESCRIPCION DE TRABAJO]])),""))} | P41: =IFERROR(LEFT(O41, FIND(",", O41)-1), O41) | Q41: =IFERROR(IF(ISERROR(FIND(",", O41, FIND(",", O41)+1)), RIGHT(O41, LEN(O41)-FIND(",", O41)-1), MID(O41, FIND(",", O41)+2, FIND(",", O41, FIND(",", O41)+1)-FIND(",", O41)-2)), "") | R41: =IFERROR(RIGHT(O41, LEN(O41)-FIND(",", O41, FIND(",", O41)+1)-1), "") | S41: {=_xlfn.TEXTJOIN(", ",TRUE,_xlfn._xlws.FILTER(Tabla29[[#All],[PARTE]],ISNUMBER(SEARCH(Tabla29[[#All],[PCLAVE3]],Tabla8[[#This Row],[DESCRIPCION DE TRABAJO]])),""))} | T41: =IF(AND(Tabla8[[#This Row],[PIEZA]]="",Tabla8[[#This Row],[PARTE]]=""),"VACIO","OK") -> VACIO | U41: =+CONCATENATE(WEEKNUM(Tabla8[[#This Row],[FECHA]]),"-",YEAR(Tabla8[[#This Row],[FECHA]])) -> 2-2026
A42: 46027 | B42: OMAR NINA | C42: MAÑANA | D42: 08:03 | E42: 08:30 | F42: =+MOD(Tabla8[[#This Row],[HR. FIN]]-Tabla8[[#This Row],[HR. INICIO]],1) -> 0.01875 | G42: LINEA AUTOMATICA HACOS 1 | H42: =IFERROR(VLOOKUP(G42,DATOS!$M$2:$N$219,2,FALSE),"") -> Maquinaria | I42: SET UP | J42: =+VLOOKUP($I42,Tabla7[#All],2,FALSE) -> PROGRAMADA | K42: =IF(VLOOKUP(I42,Tabla7[#All],3,FALSE)=0,"",VLOOKUP(I42,Tabla7[#All],3,FALSE)) | L42: Armado de MDS para formato frambuesa | N42: {=IFERROR(IF(Tabla8[[#This Row],[P/NP]]="NO PROGRAMADA","",_xlfn.TEXTJOIN(", ",TRUE,_xlfn._xlws.FILTER(Tabla4[[#All],[PIEZA]],ISNUMBER(SEARCH(Tabla4[[#All],[PCLAVE]],Tabla8[[#This Row],[DESCRIPCION DE TRABAJO]])),""))),"")} | O42: {=_xlfn.TEXTJOIN(", ",TRUE,_xlfn._xlws.FILTER(Tabla28[[#All],[PARTE]],ISNUMBER(SEARCH(Tabla28[[#All],[PCLAVE2]],Tabla8[[#This Row],[DESCRIPCION DE TRABAJO]])),""))} -> Mds | P42: =IFERROR(LEFT(O42, FIND(",", O42)-1), O42) -> Mds | Q42: =IFERROR(IF(ISERROR(FIND(",", O42, FIND(",", O42)+1)), RIGHT(O42, LEN(O42)-FIND(",", O42)-1), MID(O42, FIND(",", O42)+2, FIND(",", O42, FIND(",", O42)+1)-FIND(",", O42)-2)), "") | R42: =IFERROR(RIGHT(O42, LEN(O42)-FIND(",", O42, FIND(",", O42)+1)-1), "") | S42: {=_xlfn.TEXTJOIN(", ",TRUE,_xlfn._xlws.FILTER(Tabla29[[#All],[PARTE]],ISNUMBER(SEARCH(Tabla29[[#All],[PCLAVE3]],Tabla8[[#This Row],[DESCRIPCION DE TRABAJO]])),""))} -> Cambio De Formato | T42: =IF(AND(Tabla8[[#This Row],[PIEZA]]="",Tabla8[[#This Row],[PARTE]]=""),"VACIO","OK") -> OK | U42: =+CONCATENATE(WEEKNUM(Tabla8[[#This Row],[FECHA]]),"-",YEAR(Tabla8[[#This Row],[FECHA]])) -> 2-2026
A43: 46027 | B43: CARLOS PUMA | C43: NOCHE | D43: 22:35 | E43: 22:59 | F43: =+MOD(Tabla8[[#This Row],[HR. FIN]]-Tabla8[[#This Row],[HR. INICIO]],1) -> 0.016666667 | G43: CONCHA CLOVER 01 | H43: =IFERROR(VLOOKUP(G43,DATOS!$M$2:$N$219,2,FALSE),"") -> Maquinaria | I43: SET UP | J43: =+VLOOKUP($I43,Tabla7[#All],2,FALSE) -> PROGRAMADA | K43: =IF(VLOOKUP(I43,Tabla7[#All],3,FALSE)=0,"",VLOOKUP(I43,Tabla7[#All],3,FALSE)) | L43: Se retiró tapas, rejillas y guardas para limpieza | N43: {=IFERROR(IF(Tabla8[[#This Row],[P/NP]]="NO PROGRAMADA","",_xlfn.TEXTJOIN(", ",TRUE,_xlfn._xlws.FILTER(Tabla4[[#All],[PIEZA]],ISNUMBER(SEARCH(Tabla4[[#All],[PCLAVE]],Tabla8[[#This Row],[DESCRIPCION DE TRABAJO]])),""))),"")} -> Rejilla, Tapa | O43: {=_xlfn.TEXTJOIN(", ",TRUE,_xlfn._xlws.FILTER(Tabla28[[#All],[PARTE]],ISNUMBER(SEARCH(Tabla28[[#All],[PCLAVE2]],Tabla8[[#This Row],[DESCRIPCION DE TRABAJO]])),""))} | P43: =IFERROR(LEFT(O43, FIND(",", O43)-1), O43) | Q43: =IFERROR(IF(ISERROR(FIND(",", O43, FIND(",", O43)+1)), RIGHT(O43, LEN(O43)-FIND(",", O43)-1), MID(O43, FIND(",", O43)+2, FIND(",", O43, FIND(",", O43)+1)-FIND(",", O43)-2)), "") | R43: =IFERROR(RIGHT(O43, LEN(O43)-FIND(",", O43, FIND(",", O43)+1)-1), "") | S43: {=_xlfn.TEXTJOIN(", ",TRUE,_xlfn._xlws.FILTER(Tabla29[[#All],[PARTE]],ISNUMBER(SEARCH(Tabla29[[#All],[PCLAVE3]],Tabla8[[#This Row],[DESCRIPCION DE TRABAJO]])),""))} -> Sustitucion | T43: =IF(AND(Tabla8[[#This Row],[PIEZA]]="",Tabla8[[#This Row],[PARTE]]=""),"VACIO","OK") -> OK | U43: =+CONCATENATE(WEEKNUM(Tabla8[[#This Row],[FECHA]]),"-",YEAR(Tabla8[[#This Row],[FECHA]])) -> 2-2026
A44: 46027 | B44: OMAR NINA | C44: MAÑANA | D44: 13:46 | E44: 14:10 | F44: =+MOD(Tabla8[[#This Row],[HR. FIN]]-Tabla8[[#This Row],[HR. INICIO]],1) -> 0.016666667 | G44: EMP. NAPOLITANA | H44: =IFERROR(VLOOKUP(G44,DATOS!$M$2:$N$219,2,FALSE),"") -> Maquinaria | I44: SET UP | J44: =+VLOOKUP($I44,Tabla7[#All],2,FALSE) -> PROGRAMADA | K44: =IF(VLOOKUP(I44,Tabla7[#All],3,FALSE)=0,"",VLOOKUP(I44,Tabla7[#All],3,FALSE)) | L44: Llenado de aceite | N44: {=IFERROR(IF(Tabla8[[#This Row],[P/NP]]="NO PROGRAMADA","",_xlfn.TEXTJOIN(", ",TRUE,_xlfn._xlws.FILTER(Tabla4[[#All],[PIEZA]],ISNUMBER(SEARCH(Tabla4[[#All],[PCLAVE]],Tabla8[[#This Row],[DESCRIPCION DE TRABAJO]])),""))),"")} | O44: {=_xlfn.TEXTJOIN(", ",TRUE,_xlfn._xlws.FILTER(Tabla28[[#All],[PARTE]],ISNUMBER(SEARCH(Tabla28[[#All],[PCLAVE2]],Tabla8[[#This Row],[DESCRIPCION DE TRABAJO]])),""))} | P44: =IFERROR(LEFT(O44, FIND(",", O44)-1), O44) | Q44: =IFERROR(IF(ISERROR(FIND(",", O44, FIND(",", O44)+1)), RIGHT(O44, LEN(O44)-FIND(",", O44)-1), MID(O44, FIND(",", O44)+2, FIND(",", O44, FIND(",", O44)+1)-FIND(",", O44)-2)), "") | R44: =IFERROR(RIGHT(O44, LEN(O44)-FIND(",", O44, FIND(",", O44)+1)-1), "") | S44: {=_xlfn.TEXTJOIN(", ",TRUE,_xlfn._xlws.FILTER(Tabla29[[#All],[PARTE]],ISNUMBER(SEARCH(Tabla29[[#All],[PCLAVE3]],Tabla8[[#This Row],[DESCRIPCION DE TRABAJO]])),""))} | T44: =IF(AND(Tabla8[[#This Row],[PIEZA]]="",Tabla8[[#This Row],[PARTE]]=""),"VACIO","OK") -> VACIO | U44: =+CONCATENATE(WEEKNUM(Tabla8[[#This Row],[FECHA]]),"-",YEAR(Tabla8[[#This Row],[FECHA]])) -> 2-2026
A45: 46027 | B45: CARLOS PUMA | C45: NOCHE | D45: 02:50 | E45: 03:10 | F45: =+MOD(Tabla8[[#This Row],[HR. FIN]]-Tabla8[[#This Row],[HR. INICIO]],1) -> 0.013888889 | G45: BARQUILLERA FRANZ HAAZ | H45: =IFERROR(VLOOKUP(G45,DATOS!$M$2:$N$219,2,FALSE),"") -> Maquinaria | I45: Inspección | J45: =+VLOOKUP($I45,Tabla7[#All],2,FALSE) -> PROGRAMADA | K45: =IF(VLOOKUP(I45,Tabla7[#All],3,FALSE)=0,"",VLOOKUP(I45,Tabla7[#All],3,FALSE)) | L45: Inspección de parámetros de nivel de tanque de masa | N45: {=IFERROR(IF(Tabla8[[#This Row],[P/NP]]="NO PROGRAMADA","",_xlfn.TEXTJOIN(", ",TRUE,_xlfn._xlws.FILTER(Tabla4[[#All],[PIEZA]],ISNUMBER(SEARCH(Tabla4[[#All],[PCLAVE]],Tabla8[[#This Row],[DESCRIPCION DE TRABAJO]])),""))),"")} -> Producto | O45: {=_xlfn.TEXTJOIN(", ",TRUE,_xlfn._xlws.FILTER(Tabla28[[#All],[PARTE]],ISNUMBER(SEARCH(Tabla28[[#All],[PCLAVE2]],Tabla8[[#This Row],[DESCRIPCION DE TRABAJO]])),""))} -> Tanque | P45: =IFERROR(LEFT(O45, FIND(",", O45)-1), O45) -> Tanque | Q45: =IFERROR(IF(ISERROR(FIND(",", O45, FIND(",", O45)+1)), RIGHT(O45, LEN(O45)-FIND(",", O45)-1), MID(O45, FIND(",", O45)+2, FIND(",", O45, FIND(",", O45)+1)-FIND(",", O45)-2)), "") | R45: =IFERROR(RIGHT(O45, LEN(O45)-FIND(",", O45, FIND(",", O45)+1)-1), "") | S45: {=_xlfn.TEXTJOIN(", ",TRUE,_xlfn._xlws.FILTER(Tabla29[[#All],[PARTE]],ISNUMBER(SEARCH(Tabla29[[#All],[PCLAVE3]],Tabla8[[#This Row],[DESCRIPCION DE TRABAJO]])),""))} -> Nivel | T45: =IF(AND(Tabla8[[#This Row],[PIEZA]]="",Tabla8[[#This Row],[PARTE]]=""),"VACIO","OK") -> OK | U45: =+CONCATENATE(WEEKNUM(Tabla8[[#This Row],[FECHA]]),"-",YEAR(Tabla8[[#This Row],[FECHA]])) -> 2-2026
A46: 46027 | B46: CARLOS PUMA | C46: NOCHE | D46: 02:00 | E46: 02:20 | F46: =+MOD(Tabla8[[#This Row],[HR. FIN]]-Tabla8[[#This Row],[HR. INICIO]],1) -> 0.013888889 | G46: CODIFICADORA LASER MACSA 4TO PISO | H46: =IFERROR(VLOOKUP(G46,DATOS!$M$2:$N$219,2,FALSE),"") -> Maquinaria | I46: SET UP | J46: NO PROGRAMADA | K46: ELÉCTRICA | L46: No detecta señal de sensor | M46: Se configuro parámetros y tipo de sensor a usar , se aseguro conexiones y se hizo pruebas | N46: {=IFERROR(IF(Tabla8[[#This Row],[P/NP]]="NO PROGRAMADA","",_xlfn.TEXTJOIN(", ",TRUE,_xlfn._xlws.FILTER(Tabla4[[#All],[PIEZA]],ISNUMBER(SEARCH(Tabla4[[#All],[PCLAVE]],Tabla8[[#This Row],[DESCRIPCION DE TRABAJO]])),""))),"")} | O46: {=_xlfn.TEXTJOIN(", ",TRUE,_xlfn._xlws.FILTER(Tabla28[[#All],[PARTE]],ISNUMBER(SEARCH(Tabla28[[#All],[PCLAVE2]],Tabla8[[#This Row],[DESCRIPCION DE TRABAJO]])),""))} | P46: =IFERROR(LEFT(O46, FIND(",", O46)-1), O46) | Q46: =IFERROR(IF(ISERROR(FIND(",", O46, FIND(",", O46)+1)), RIGHT(O46, LEN(O46)-FIND(",", O46)-1), MID(O46, FIND(",", O46)+2, FIND(",", O46, FIND(",", O46)+1)-FIND(",", O46)-2)), "") | R46: =IFERROR(RIGHT(O46, LEN(O46)-FIND(",", O46, FIND(",", O46)+1)-1), "") | S46: {=_xlfn.TEXTJOIN(", ",TRUE,_xlfn._xlws.FILTER(Tabla29[[#All],[PARTE]],ISNUMBER(SEARCH(Tabla29[[#All],[PCLAVE3]],Tabla8[[#This Row],[DESCRIPCION DE TRABAJO]])),""))} | T46: =IF(AND(Tabla8[[#This Row],[PIEZA]]="",Tabla8[[#This Row],[PARTE]]=""),"VACIO","OK") -> VACIO | U46: =+CONCATENATE(WEEKNUM(Tabla8[[#This Row],[FECHA]]),"-",YEAR(Tabla8[[#This Row],[FECHA]])) -> 2-2026
A47: 46027 | B47: OMAR NINA | C47: MAÑANA | D47: 10:55 | E47: 11:15 | F47: =+MOD(Tabla8[[#This Row],[HR. FIN]]-Tabla8[[#This Row],[HR. INICIO]],1) -> 0.013888889 | G47: EMP. 2 - CARLE MONTANARY | H47: =IFERROR(VLOOKUP(G47,DATOS!$M$2:$N$219,2,FALSE),"") -> Maquinaria | I47: Inspección | J47: =+VLOOKUP($I47,Tabla7[#All],2,FALSE) -> PROGRAMADA | K47: =IF(VLOOKUP(I47,Tabla7[#All],3,FALSE)=0,"",VLOOKUP(I47,Tabla7[#All],3,FALSE)) | L47: Inspección funcionamiento de equipo | N47: {=IFERROR(IF(Tabla8[[#This Row],[P/NP]]="NO PROGRAMADA","",_xlfn.TEXTJOIN(", ",TRUE,_xlfn._xlws.FILTER(Tabla4[[#All],[PIEZA]],ISNUMBER(SEARCH(Tabla4[[#All],[PCLAVE]],Tabla8[[#This Row],[DESCRIPCION DE TRABAJO]])),""))),"")} | O47: {=_xlfn.TEXTJOIN(", ",TRUE,_xlfn._xlws.FILTER(Tabla28[[#All],[PARTE]],ISNUMBER(SEARCH(Tabla28[[#All],[PCLAVE2]],Tabla8[[#This Row],[DESCRIPCION DE TRABAJO]])),""))} | P47: =IFERROR(LEFT(O47, FIND(",", O47)-1), O47) | Q47: =IFERROR(IF(ISERROR(FIND(",", O47, FIND(",", O47)+1)), RIGHT(O47, LEN(O47)-FIND(",", O47)-1), MID(O47, FIND(",", O47)+2, FIND(",", O47, FIND(",", O47)+1)-FIND(",", O47)-2)), "") | R47: =IFERROR(RIGHT(O47, LEN(O47)-FIND(",", O47, FIND(",", O47)+1)-1), "") | S47: {=_xlfn.TEXTJOIN(", ",TRUE,_xlfn._xlws.FILTER(Tabla29[[#All],[PARTE]],ISNUMBER(SEARCH(Tabla29[[#All],[PCLAVE3]],Tabla8[[#This Row],[DESCRIPCION DE TRABAJO]])),""))} | T47: =IF(AND(Tabla8[[#This Row],[PIEZA]]="",Tabla8[[#This Row],[PARTE]]=""),"VACIO","OK") -> VACIO | U47: =+CONCATENATE(WEEKNUM(Tabla8[[#This Row],[FECHA]]),"-",YEAR(Tabla8[[#This Row],[FECHA]])) -> 2-2026
A48: 46027 | B48: CARLOS PUMA | C48: NOCHE | D48: 00:03 | E48: 00:20 | F48: =+MOD(Tabla8[[#This Row],[HR. FIN]]-Tabla8[[#This Row],[HR. INICIO]],1) -> 0.011805556 | G48: BARQUILLERA FRANZ HAAZ | H48: =IFERROR(VLOOKUP(G48,DATOS!$M$2:$N$219,2,FALSE),"") -> Maquinaria | I48: Ajuste /Calibracion | J48: PROGRAMADA | L48: Se apoyó en el ajuste de manguera de masa y se regulo parámetros de nivel del tanque de masa | N48: {=IFERROR(IF(Tabla8[[#This Row],[P/NP]]="NO PROGRAMADA","",_xlfn.TEXTJOIN(", ",TRUE,_xlfn._xlws.FILTER(Tabla4[[#All],[PIEZA]],ISNUMBER(SEARCH(Tabla4[[#All],[PCLAVE]],Tabla8[[#This Row],[DESCRIPCION DE TRABAJO]])),""))),"")} -> Manguera, Producto | O48: {=_xlfn.TEXTJOIN(", ",TRUE,_xlfn._xlws.FILTER(Tabla28[[#All],[PARTE]],ISNUMBER(SEARCH(Tabla28[[#All],[PCLAVE2]],Tabla8[[#This Row],[DESCRIPCION DE TRABAJO]])),""))} -> Tanque | P48: =IFERROR(LEFT(O48, FIND(",", O48)-1), O48) -> Tanque | Q48: =IFERROR(IF(ISERROR(FIND(",", O48, FIND(",", O48)+1)), RIGHT(O48, LEN(O48)-FIND(",", O48)-1), MID(O48, FIND(",", O48)+2, FIND(",", O48, FIND(",", O48)+1)-FIND(",", O48)-2)), "") | R48: =IFERROR(RIGHT(O48, LEN(O48)-FIND(",", O48, FIND(",", O48)+1)-1), "") | S48: {=_xlfn.TEXTJOIN(", ",TRUE,_xlfn._xlws.FILTER(Tabla29[[#All],[PARTE]],ISNUMBER(SEARCH(Tabla29[[#All],[PCLAVE3]],Tabla8[[#This Row],[DESCRIPCION DE TRABAJO]])),""))} -> Calibracion, Nivel | T48: =IF(AND(Tabla8[[#This Row],[PIEZA]]="",Tabla8[[#This Row],[PARTE]]=""),"VACIO","OK") -> OK | U48: =+CONCATENATE(WEEKNUM(Tabla8[[#This Row],[FECHA]]),"-",YEAR(Tabla8[[#This Row],[FECHA]])) -> 2-2026
A49: 46027 | B49: OMAR NINA | C49: MAÑANA | D49: 08:35 | E49: 08:51 | F49: =+MOD(Tabla8[[#This Row],[HR. FIN]]-Tabla8[[#This Row],[HR. INICIO]],1) -> 0.011111111 | G49: LINEA AUTOMATICA HACOS 1 | H49: =IFERROR(VLOOKUP(G49,DATOS!$M$2:$N$219,2,FALSE),"") -> Maquinaria | I49: SET UP | J49: NO PROGRAMADA | K49: MECÁNICA | L49: Temperatura de túnel de enfriamiento demorar en bajar | M49: Se agrega refrigerante a compresor | N49: {=IFERROR(IF(Tabla8[[#This Row],[P/NP]]="NO PROGRAMADA","",_xlfn.TEXTJOIN(", ",TRUE,_xlfn._xlws.FILTER(Tabla4[[#All],[PIEZA]],ISNUMBER(SEARCH(Tabla4[[#All],[PCLAVE]],Tabla8[[#This Row],[DESCRIPCION DE TRABAJO]])),""))),"")} | O49: {=_xlfn.TEXTJOIN(", ",TRUE,_xlfn._xlws.FILTER(Tabla28[[#All],[PARTE]],ISNUMBER(SEARCH(Tabla28[[#All],[PCLAVE2]],Tabla8[[#This Row],[DESCRIPCION DE TRABAJO]])),""))} | P49: =IFERROR(LEFT(O49, FIND(",", O49)-1), O49) | Q49: =IFERROR(IF(ISERROR(FIND(",", O49, FIND(",", O49)+1)), RIGHT(O49, LEN(O49)-FIND(",", O49)-1), MID(O49, FIND(",", O49)+2, FIND(",", O49, FIND(",", O49)+1)-FIND(",", O49)-2)), "") | R49: =IFERROR(RIGHT(O49, LEN(O49)-FIND(",", O49, FIND(",", O49)+1)-1), "") | S49: {=_xlfn.TEXTJOIN(", ",TRUE,_xlfn._xlws.FILTER(Tabla29[[#All],[PARTE]],ISNUMBER(SEARCH(Tabla29[[#All],[PCLAVE3]],Tabla8[[#This Row],[DESCRIPCION DE TRABAJO]])),""))} -> Demora, Temperatura | T49: =IF(AND(Tabla8[[#This Row],[PIEZA]]="",Tabla8[[#This Row],[PARTE]]=""),"VACIO","OK") -> VACIO | U49: =+CONCATENATE(WEEKNUM(Tabla8[[#This Row],[FECHA]]),"-",YEAR(Tabla8[[#This Row],[FECHA]])) -> 2-2026
A50: 46027 | B50: OMAR NINA | C50: MAÑANA | D50: 07:07 | E50: 07:22 | F50: =+MOD(Tabla8[[#This Row],[HR. FIN]]-Tabla8[[#This Row],[HR. INICIO]],1) -> 0.010416667 | G50: RAYOS X 1 | H50: =IFERROR(VLOOKUP(G50,DATOS!$M$2:$N$219,2,FALSE),"") -> Maquinaria | I50: Limpieza | J50: =+VLOOKUP($I50,Tabla7[#All],2,FALSE) -> PROGRAMADA | K50: =IF(VLOOKUP(I50,Tabla7[#All],3,FALSE)=0,"",VLOOKUP(I50,Tabla7[#All],3,FALSE)) | L50: Apoyo retirando faja central para limpieza | N50: {=IFERROR(IF(Tabla8[[#This Row],[P/NP]]="NO PROGRAMADA","",_xlfn.TEXTJOIN(", ",TRUE,_xlfn._xlws.FILTER(Tabla4[[#All],[PIEZA]],ISNUMBER(SEARCH(Tabla4[[#All],[PCLAVE]],Tabla8[[#This Row],[DESCRIPCION DE TRABAJO]])),""))),"")} -> Banda | O50: {=_xlfn.TEXTJOIN(", ",TRUE,_xlfn._xlws.FILTER(Tabla28[[#All],[PARTE]],ISNUMBER(SEARCH(Tabla28[[#All],[PCLAVE2]],Tabla8[[#This Row],[DESCRIPCION DE TRABAJO]])),""))} | P50: =IFERROR(LEFT(O50, FIND(",", O50)-1), O50) | Q50: =IFERROR(IF(ISERROR(FIND(",", O50, FIND(",", O50)+1)), RIGHT(O50, LEN(O50)-FIND(",", O50)-1), MID(O50, FIND(",", O50)+2, FIND(",", O50, FIND(",", O50)+1)-FIND(",", O50)-2)), "") | R50: =IFERROR(RIGHT(O50, LEN(O50)-FIND(",", O50, FIND(",", O50)+1)-1), "") | S50: {=_xlfn.TEXTJOIN(", ",TRUE,_xlfn._xlws.FILTER(Tabla29[[#All],[PARTE]],ISNUMBER(SEARCH(Tabla29[[#All],[PCLAVE3]],Tabla8[[#This Row],[DESCRIPCION DE TRABAJO]])),""))} -> Sustitucion | T50: =IF(AND(Tabla8[[#This Row],[PIEZA]]="",Tabla8[[#This Row],[PARTE]]=""),"VACIO","OK") -> OK | U50: =+CONCATENATE(WEEKNUM(Tabla8[[#This Row],[FECHA]]),"-",YEAR(Tabla8[[#This Row],[FECHA]])) -> 2-2026
A51: 46027 | B51: CARLOS PUMA | C51: NOCHE | D51: 00:30 | E51: 00:45 | F51: =+MOD(Tabla8[[#This Row],[HR. FIN]]-Tabla8[[#This Row],[HR. INICIO]],1) -> 0.010416667 | G51: PROCESADORA DE MASAS - NETZSCH | H51: =IFERROR(VLOOKUP(G51,DATOS!$M$2:$N$219,2,FALSE),"") -> Maquinaria | I51: SET UP | J51: =+VLOOKUP($I51,Tabla7[#All],2,FALSE) -> PROGRAMADA | K51: =IF(VLOOKUP(I51,Tabla7[#All],3,FALSE)=0,"",VLOOKUP(I51,Tabla7[#All],3,FALSE)) | L51: Desarme de equipo por limpieza | N51: {=IFERROR(IF(Tabla8[[#This Row],[P/NP]]="NO PROGRAMADA","",_xlfn.TEXTJOIN(", ",TRUE,_xlfn._xlws.FILTER(Tabla4[[#All],[PIEZA]],ISNUMBER(SEARCH(Tabla4[[#All],[PCLAVE]],Tabla8[[#This Row],[DESCRIPCION DE TRABAJO]])),""))),"")} | O51: {=_xlfn.TEXTJOIN(", ",TRUE,_xlfn._xlws.FILTER(Tabla28[[#All],[PARTE]],ISNUMBER(SEARCH(Tabla28[[#All],[PCLAVE2]],Tabla8[[#This Row],[DESCRIPCION DE TRABAJO]])),""))} | P51: =IFERROR(LEFT(O51, FIND(",", O51)-1), O51) | Q51: =IFERROR(IF(ISERROR(FIND(",", O51, FIND(",", O51)+1)), RIGHT(O51, LEN(O51)-FIND(",", O51)-1), MID(O51, FIND(",", O51)+2, FIND(",", O51, FIND(",", O51)+1)-FIND(",", O51)-2)), "") | R51: =IFERROR(RIGHT(O51, LEN(O51)-FIND(",", O51, FIND(",", O51)+1)-1), "") | S51: {=_xlfn.TEXTJOIN(", ",TRUE,_xlfn._xlws.FILTER(Tabla29[[#All],[PARTE]],ISNUMBER(SEARCH(Tabla29[[#All],[PCLAVE3]],Tabla8[[#This Row],[DESCRIPCION DE TRABAJO]])),""))} | T51: =IF(AND(Tabla8[[#This Row],[PIEZA]]="",Tabla8[[#This Row],[PARTE]]=""),"VACIO","OK") -> VACIO | U51: =+CONCATENATE(WEEKNUM(Tabla8[[#This Row],[FECHA]]),"-",YEAR(Tabla8[[#This Row],[FECHA]])) -> 2-2026
A52: 46027 | B52: CARLOS PUMA | C52: NOCHE | D52: 21:30 | E52: 21:45 | F52: =+MOD(Tabla8[[#This Row],[HR. FIN]]-Tabla8[[#This Row],[HR. INICIO]],1) -> 0.010416667 | G52: TOSTADOR CARLE MONTANARY | H52: =IFERROR(VLOOKUP(G52,DATOS!$M$2:$N$219,2,FALSE),"") -> Maquinaria | I52: Inspección | J52: =+VLOOKUP($I52,Tabla7[#All],2,FALSE) -> PROGRAMADA | K52: =IF(VLOOKUP(I52,Tabla7[#All],3,FALSE)=0,"",VLOOKUP(I52,Tabla7[#All],3,FALSE)) | L52: Reportan válvulas de gas abiertas | M52: Se reviso estado de válvulas de gas | N52: {=IFERROR(IF(Tabla8[[#This Row],[P/NP]]="NO PROGRAMADA","",_xlfn.TEXTJOIN(", ",TRUE,_xlfn._xlws.FILTER(Tabla4[[#All],[PIEZA]],ISNUMBER(SEARCH(Tabla4[[#All],[PCLAVE]],Tabla8[[#This Row],[DESCRIPCION DE TRABAJO]])),""))),"")} | O52: {=_xlfn.TEXTJOIN(", ",TRUE,_xlfn._xlws.FILTER(Tabla28[[#All],[PARTE]],ISNUMBER(SEARCH(Tabla28[[#All],[PCLAVE2]],Tabla8[[#This Row],[DESCRIPCION DE TRABAJO]])),""))} | P52: =IFERROR(LEFT(O52, FIND(",", O52)-1), O52) | Q52: =IFERROR(IF(ISERROR(FIND(",", O52, FIND(",", O52)+1)), RIGHT(O52, LEN(O52)-FIND(",", O52)-1), MID(O52, FIND(",", O52)+2, FIND(",", O52, FIND(",", O52)+1)-FIND(",", O52)-2)), "") | R52: =IFERROR(RIGHT(O52, LEN(O52)-FIND(",", O52, FIND(",", O52)+1)-1), "") | S52: {=_xlfn.TEXTJOIN(", ",TRUE,_xlfn._xlws.FILTER(Tabla29[[#All],[PARTE]],ISNUMBER(SEARCH(Tabla29[[#All],[PCLAVE3]],Tabla8[[#This Row],[DESCRIPCION DE TRABAJO]])),""))} -> Abierto | T52: =IF(AND(Tabla8[[#This Row],[PIEZA]]="",Tabla8[[#This Row],[PARTE]]=""),"VACIO","OK") -> VACIO | U52: =+CONCATENATE(WEEKNUM(Tabla8[[#This Row],[FECHA]]),"-",YEAR(Tabla8[[#This Row],[FECHA]])) -> 2-2026
A53: 46027 | B53: OMAR NINA | C53: MAÑANA | D53: 07:45 | E53: 07:58 | F53: =+MOD(Tabla8[[#This Row],[HR. FIN]]-Tabla8[[#This Row],[HR. INICIO]],1) -> 0.0090277778 | G53: RAYOS X 1 | H53: =IFERROR(VLOOKUP(G53,DATOS!$M$2:$N$219,2,FALSE),"") -> Maquinaria | I53: SET UP | J53: =+VLOOKUP($I53,Tabla7[#All],2,FALSE) -> PROGRAMADA | K53: =IF(VLOOKUP(I53,Tabla7[#All],3,FALSE)=0,"",VLOOKUP(I53,Tabla7[#All],3,FALSE)) | L53: Colocación de faja | N53: {=IFERROR(IF(Tabla8[[#This Row],[P/NP]]="NO PROGRAMADA","",_xlfn.TEXTJOIN(", ",TRUE,_xlfn._xlws.FILTER(Tabla4[[#All],[PIEZA]],ISNUMBER(SEARCH(Tabla4[[#All],[PCLAVE]],Tabla8[[#This Row],[DESCRIPCION DE TRABAJO]])),""))),"")} -> Banda | O53: {=_xlfn.TEXTJOIN(", ",TRUE,_xlfn._xlws.FILTER(Tabla28[[#All],[PARTE]],ISNUMBER(SEARCH(Tabla28[[#All],[PCLAVE2]],Tabla8[[#This Row],[DESCRIPCION DE TRABAJO]])),""))} | P53: =IFERROR(LEFT(O53, FIND(",", O53)-1), O53) | Q53: =IFERROR(IF(ISERROR(FIND(",", O53, FIND(",", O53)+1)), RIGHT(O53, LEN(O53)-FIND(",", O53)-1), MID(O53, FIND(",", O53)+2, FIND(",", O53, FIND(",", O53)+1)-FIND(",", O53)-2)), "") | R53: =IFERROR(RIGHT(O53, LEN(O53)-FIND(",", O53, FIND(",", O53)+1)-1), "") | S53: {=_xlfn.TEXTJOIN(", ",TRUE,_xlfn._xlws.FILTER(Tabla29[[#All],[PARTE]],ISNUMBER(SEARCH(Tabla29[[#All],[PCLAVE3]],Tabla8[[#This Row],[DESCRIPCION DE TRABAJO]])),""))} | T53: =IF(AND(Tabla8[[#This Row],[PIEZA]]="",Tabla8[[#This Row],[PARTE]]=""),"VACIO","OK") -> OK | U53: =+CONCATENATE(WEEKNUM(Tabla8[[#This Row],[FECHA]]),"-",YEAR(Tabla8[[#This Row],[FECHA]])) -> 2-2026
A54: 46028 | B54: JOSÉ HAÑARI | C54: TARDE | D54: 0.86944444 | E54: 0 | F54: =+MOD(Tabla8[[#This Row],[HR. FIN]]-Tabla8[[#This Row],[HR. INICIO]],1) -> 0.13055556 | G54: 1ER PISO | H54: =IFERROR(VLOOKUP(G54,DATOS!$M$2:$N$219,2,FALSE),"") -> Area | I54: SET UP | J54: =+VLOOKUP($I54,Tabla7[#All],2,FALSE) -> PROGRAMADA | K54: =IF(VLOOKUP(I54,Tabla7[#All],3,FALSE)=0,"",VLOOKUP(I54,Tabla7[#All],3,FALSE)) | L54: Habilitar extensión grageadora | M54: Se habilita extensión en grageadora | N54: {=IFERROR(IF(Tabla8[[#This Row],[P/NP]]="NO PROGRAMADA","",_xlfn.TEXTJOIN(", ",TRUE,_xlfn._xlws.FILTER(Tabla4[[#All],[PIEZA]],ISNUMBER(SEARCH(Tabla4[[#All],[PCLAVE]],Tabla8[[#This Row],[DESCRIPCION DE TRABAJO]])),""))),"")} | O54: {=_xlfn.TEXTJOIN(", ",TRUE,_xlfn._xlws.FILTER(Tabla28[[#All],[PARTE]],ISNUMBER(SEARCH(Tabla28[[#All],[PCLAVE2]],Tabla8[[#This Row],[DESCRIPCION DE TRABAJO]])),""))} -> Extension | P54: =IFERROR(LEFT(O54, FIND(",", O54)-1), O54) -> Extension | Q54: =IFERROR(IF(ISERROR(FIND(",", O54, FIND(",", O54)+1)), RIGHT(O54, LEN(O54)-FIND(",", O54)-1), MID(O54, FIND(",", O54)+2, FIND(",", O54, FIND(",", O54)+1)-FIND(",", O54)-2)), "") | R54: =IFERROR(RIGHT(O54, LEN(O54)-FIND(",", O54, FIND(",", O54)+1)-1), "") | S54: {=_xlfn.TEXTJOIN(", ",TRUE,_xlfn._xlws.FILTER(Tabla29[[#All],[PARTE]],ISNUMBER(SEARCH(Tabla29[[#All],[PCLAVE3]],Tabla8[[#This Row],[DESCRIPCION DE TRABAJO]])),""))} | T54: =IF(AND(Tabla8[[#This Row],[PIEZA]]="",Tabla8[[#This Row],[PARTE]]=""),"VACIO","OK") -> OK | U54: =+CONCATENATE(WEEKNUM(Tabla8[[#This Row],[FECHA]]),"-",YEAR(Tabla8[[#This Row],[FECHA]])) -> 2-2026
A55: 46028 | B55: CARLOS TAPIA | C55: MAÑANA | D55: 0.26388889 | E55: 0.32291667 | F55: =+MOD(Tabla8[[#This Row],[HR. FIN]]-Tabla8[[#This Row],[HR. INICIO]],1) -> 0.059027778 | G55: ENCELOFANADORA ECCOPAC | H55: =IFERROR(VLOOKUP(G55,DATOS!$M$2:$N$219,2,FALSE),"") -> Maquinaria | I55: SET UP | J55: =+VLOOKUP($I55,Tabla7[#All],2,FALSE) -> PROGRAMADA | K55: =IF(VLOOKUP(I55,Tabla7[#All],3,FALSE)=0,"",VLOOKUP(I55,Tabla7[#All],3,FALSE)) | L55: Cambio de formato. | M55: Se realizó el cambio de formato en máquina. | N55: {=IFERROR(IF(Tabla8[[#This Row],[P/NP]]="NO PROGRAMADA","",_xlfn.TEXTJOIN(", ",TRUE,_xlfn._xlws.FILTER(Tabla4[[#All],[PIEZA]],ISNUMBER(SEARCH(Tabla4[[#All],[PCLAVE]],Tabla8[[#This Row],[DESCRIPCION DE TRABAJO]])),""))),"")} | O55: {=_xlfn.TEXTJOIN(", ",TRUE,_xlfn._xlws.FILTER(Tabla28[[#All],[PARTE]],ISNUMBER(SEARCH(Tabla28[[#All],[PCLAVE2]],Tabla8[[#This Row],[DESCRIPCION DE TRABAJO]])),""))} | P55: =IFERROR(LEFT(O55, FIND(",", O55)-1), O55) | Q55: =IFERROR(IF(ISERROR(FIND(",", O55, FIND(",", O55)+1)), RIGHT(O55, LEN(O55)-FIND(",", O55)-1), MID(O55, FIND(",", O55)+2, FIND(",", O55, FIND(",", O55)+1)-FIND(",", O55)-2)), "") | R55: =IFERROR(RIGHT(O55, LEN(O55)-FIND(",", O55, FIND(",", O55)+1)-1), "") | S55: {=_xlfn.TEXTJOIN(", ",TRUE,_xlfn._xlws.FILTER(Tabla29[[#All],[PARTE]],ISNUMBER(SEARCH(Tabla29[[#All],[PCLAVE3]],Tabla8[[#This Row],[DESCRIPCION DE TRABAJO]])),""))} -> Cambio De Formato | T55: =IF(AND(Tabla8[[#This Row],[PIEZA]]="",Tabla8[[#This Row],[PARTE]]=""),"VACIO","OK") -> VACIO | U55: =+CONCATENATE(WEEKNUM(Tabla8[[#This Row],[FECHA]]),"-",YEAR(Tabla8[[#This Row],[FECHA]])) -> 2-2026
A56: 46028 | B56: OMAR NINA | C56: MAÑANA | D56: 0.54861111 | E56: 0.59027778 | F56: =+MOD(Tabla8[[#This Row],[HR. FIN]]-Tabla8[[#This Row],[HR. INICIO]],1) -> 0.041666667 | G56: BATIDORA DE HUEVOS 02 NOVA | H56: =IFERROR(VLOOKUP(G56,DATOS!$M$2:$N$219,2,FALSE),"") -> Maquinaria | I56: Reparacion | J56: =+VLOOKUP($I56,Tabla7[#All],2,FALSE) -> NO PROGRAMADA | K56: MECÁNICA | L56: Agitador tiene óxido en los pernos | M56: Se lleva a taller y se inicia con el cambio de pernos y pulido | N56: {=IFERROR(IF(Tabla8[[#This Row],[P/NP]]="NO PROGRAMADA","",_xlfn.TEXTJOIN(", ",TRUE,_xlfn._xlws.FILTER(Tabla4[[#All],[PIEZA]],ISNUMBER(SEARCH(Tabla4[[#All],[PCLAVE]],Tabla8[[#This Row],[DESCRIPCION DE TRABAJO]])),""))),"")} | O56: {=_xlfn.TEXTJOIN(", ",TRUE,_xlfn._xlws.FILTER(Tabla28[[#All],[PARTE]],ISNUMBER(SEARCH(Tabla28[[#All],[PCLAVE2]],Tabla8[[#This Row],[DESCRIPCION DE TRABAJO]])),""))} | P56: =IFERROR(LEFT(O56, FIND(",", O56)-1), O56) | Q56: =IFERROR(IF(ISERROR(FIND(",", O56, FIND(",", O56)+1)), RIGHT(O56, LEN(O56)-FIND(",", O56)-1), MID(O56, FIND(",", O56)+2, FIND(",", O56, FIND(",", O56)+1)-FIND(",", O56)-2)), "") | R56: =IFERROR(RIGHT(O56, LEN(O56)-FIND(",", O56, FIND(",", O56)+1)-1), "") | S56: {=_xlfn.TEXTJOIN(", ",TRUE,_xlfn._xlws.FILTER(Tabla29[[#All],[PARTE]],ISNUMBER(SEARCH(Tabla29[[#All],[PCLAVE3]],Tabla8[[#This Row],[DESCRIPCION DE TRABAJO]])),""))} | T56: =IF(AND(Tabla8[[#This Row],[PIEZA]]="",Tabla8[[#This Row],[PARTE]]=""),"VACIO","OK") -> VACIO | U56: =+CONCATENATE(WEEKNUM(Tabla8[[#This Row],[FECHA]]),"-",YEAR(Tabla8[[#This Row],[FECHA]])) -> 2-2026
A57: 46028 | B57: OMAR NINA | C57: MAÑANA | D57: 0.27916667 | E57: 0.31944444 | F57: =+MOD(Tabla8[[#This Row],[HR. FIN]]-Tabla8[[#This Row],[HR. INICIO]],1) -> 0.040277778 | G57: ENCELOFANADORA ECCOPAC | H57: =IFERROR(VLOOKUP(G57,DATOS!$M$2:$N$219,2,FALSE),"") -> Maquinaria | I57: SET UP | J57: =+VLOOKUP($I57,Tabla7[#All],2,FALSE) -> PROGRAMADA | K57: =IF(VLOOKUP(I57,Tabla7[#All],3,FALSE)=0,"",VLOOKUP(I57,Tabla7[#All],3,FALSE)) | L57: Cambio de formato de pisco x9 a milky | M57: Cambio de piezas y calibración de equipo | N57: {=IFERROR(IF(Tabla8[[#This Row],[P/NP]]="NO PROGRAMADA","",_xlfn.TEXTJOIN(", ",TRUE,_xlfn._xlws.FILTER(Tabla4[[#All],[PIEZA]],ISNUMBER(SEARCH(Tabla4[[#All],[PCLAVE]],Tabla8[[#This Row],[DESCRIPCION DE TRABAJO]])),""))),"")} | O57: {=_xlfn.TEXTJOIN(", ",TRUE,_xlfn._xlws.FILTER(Tabla28[[#All],[PARTE]],ISNUMBER(SEARCH(Tabla28[[#All],[PCLAVE2]],Tabla8[[#This Row],[DESCRIPCION DE TRABAJO]])),""))} | P57: =IFERROR(LEFT(O57, FIND(",", O57)-1), O57) | Q57: =IFERROR(IF(ISERROR(FIND(",", O57, FIND(",", O57)+1)), RIGHT(O57, LEN(O57)-FIND(",", O57)-1), MID(O57, FIND(",", O57)+2, FIND(",", O57, FIND(",", O57)+1)-FIND(",", O57)-2)), "") | R57: =IFERROR(RIGHT(O57, LEN(O57)-FIND(",", O57, FIND(",", O57)+1)-1), "") | S57: {=_xlfn.TEXTJOIN(", ",TRUE,_xlfn._xlws.FILTER(Tabla29[[#All],[PARTE]],ISNUMBER(SEARCH(Tabla29[[#All],[PCLAVE3]],Tabla8[[#This Row],[DESCRIPCION DE TRABAJO]])),""))} -> Cambio De Formato | T57: =IF(AND(Tabla8[[#This Row],[PIEZA]]="",Tabla8[[#This Row],[PARTE]]=""),"VACIO","OK") -> VACIO | U57: =+CONCATENATE(WEEKNUM(Tabla8[[#This Row],[FECHA]]),"-",YEAR(Tabla8[[#This Row],[FECHA]])) -> 2-2026
A58: 46028 | B58: CESAR QUIROZ | C58: TARDE | D58: 0.63611111 | E58: 0.66180556 | F58: =+MOD(Tabla8[[#This Row],[HR. FIN]]-Tabla8[[#This Row],[HR. INICIO]],1) -> 0.025694444 | G58: EMP. SAPAL | H58: =IFERROR(VLOOKUP(G58,DATOS!$M$2:$N$219,2,FALSE),"") -> Maquinaria | I58: SET UP | J58: =+VLOOKUP($I58,Tabla7[#All],2,FALSE) -> PROGRAMADA | K58: =IF(VLOOKUP(I58,Tabla7[#All],3,FALSE)=0,"",VLOOKUP(I58,Tabla7[#All],3,FALSE)) | L58: Cambio de formato para barras x50 | N58: {=IFERROR(IF(Tabla8[[#This Row],[P/NP]]="NO PROGRAMADA","",_xlfn.TEXTJOIN(", ",TRUE,_xlfn._xlws.FILTER(Tabla4[[#All],[PIEZA]],ISNUMBER(SEARCH(Tabla4[[#All],[PCLAVE]],Tabla8[[#This Row],[DESCRIPCION DE TRABAJO]])),""))),"")} | O58: {=_xlfn.TEXTJOIN(", ",TRUE,_xlfn._xlws.FILTER(Tabla28[[#All],[PARTE]],ISNUMBER(SEARCH(Tabla28[[#All],[PCLAVE2]],Tabla8[[#This Row],[DESCRIPCION DE TRABAJO]])),""))} | P58: =IFERROR(LEFT(O58, FIND(",", O58)-1), O58) | Q58: =IFERROR(IF(ISERROR(FIND(",", O58, FIND(",", O58)+1)), RIGHT(O58, LEN(O58)-FIND(",", O58)-1), MID(O58, FIND(",", O58)+2, FIND(",", O58, FIND(",", O58)+1)-FIND(",", O58)-2)), "") | R58: =IFERROR(RIGHT(O58, LEN(O58)-FIND(",", O58, FIND(",", O58)+1)-1), "") | S58: {=_xlfn.TEXTJOIN(", ",TRUE,_xlfn._xlws.FILTER(Tabla29[[#All],[PARTE]],ISNUMBER(SEARCH(Tabla29[[#All],[PCLAVE3]],Tabla8[[#This Row],[DESCRIPCION DE TRABAJO]])),""))} -> Cambio De Formato | T58: =IF(AND(Tabla8[[#This Row],[PIEZA]]="",Tabla8[[#This Row],[PARTE]]=""),"VACIO","OK") -> VACIO | U58: =+CONCATENATE(WEEKNUM(Tabla8[[#This Row],[FECHA]]),"-",YEAR(Tabla8[[#This Row],[FECHA]])) -> 2-2026
A59: 46028 | B59: OMAR NINA | C59: MAÑANA | D59: 0.39930556 | E59: 0.42361111 | F59: =+MOD(Tabla8[[#This Row],[HR. FIN]]-Tabla8[[#This Row],[HR. INICIO]],1) -> 0.024305556 | G59: LINEA AUTOMATICA HACOS 1 | H59: =IFERROR(VLOOKUP(G59,DATOS!$M$2:$N$219,2,FALSE),"") -> Maquinaria | I59: Inspección | J59: =+VLOOKUP($I59,Tabla7[#All],2,FALSE) -> PROGRAMADA | K59: =IF(VLOOKUP(I59,Tabla7[#All],3,FALSE)=0,"",VLOOKUP(I59,Tabla7[#All],3,FALSE)) | L59: Reportan que equipo se apagó. Guardamotor th9 protegido | M59: Se revisó tensión de línea principal. Se revisó ventiladores y se inicia equipo. | N59: {=IFERROR(IF(Tabla8[[#This Row],[P/NP]]="NO PROGRAMADA","",_xlfn.TEXTJOIN(", ",TRUE,_xlfn._xlws.FILTER(Tabla4[[#All],[PIEZA]],ISNUMBER(SEARCH(Tabla4[[#All],[PCLAVE]],Tabla8[[#This Row],[DESCRIPCION DE TRABAJO]])),""))),"")} -> Guardamotor, Motor | O59: {=_xlfn.TEXTJOIN(", ",TRUE,_xlfn._xlws.FILTER(Tabla28[[#All],[PARTE]],ISNUMBER(SEARCH(Tabla28[[#All],[PCLAVE2]],Tabla8[[#This Row],[DESCRIPCION DE TRABAJO]])),""))} | P59: =IFERROR(LEFT(O59, FIND(",", O59)-1), O59) | Q59: =IFERROR(IF(ISERROR(FIND(",", O59, FIND(",", O59)+1)), RIGHT(O59, LEN(O59)-FIND(",", O59)-1), MID(O59, FIND(",", O59)+2, FIND(",", O59, FIND(",", O59)+1)-FIND(",", O59)-2)), "") | R59: =IFERROR(RIGHT(O59, LEN(O59)-FIND(",", O59, FIND(",", O59)+1)-1), "") | S59: {=_xlfn.TEXTJOIN(", ",TRUE,_xlfn._xlws.FILTER(Tabla29[[#All],[PARTE]],ISNUMBER(SEARCH(Tabla29[[#All],[PCLAVE3]],Tabla8[[#This Row],[DESCRIPCION DE TRABAJO]])),""))} -> Rotura | T59: =IF(AND(Tabla8[[#This Row],[PIEZA]]="",Tabla8[[#This Row],[PARTE]]=""),"VACIO","OK") -> OK | U59: =+CONCATENATE(WEEKNUM(Tabla8[[#This Row],[FECHA]]),"-",YEAR(Tabla8[[#This Row],[FECHA]])) -> 2-2026
A60: 46028 | B60: CESAR QUIROZ | C60: TARDE | D60: 0.59097222 | E60: 0.6125 | F60: =+MOD(Tabla8[[#This Row],[HR. FIN]]-Tabla8[[#This Row],[HR. INICIO]],1) -> 0.021527778 | G60: LINEA AUTOMATICA HACOS 1 | H60: =IFERROR(VLOOKUP(G60,DATOS!$M$2:$N$219,2,FALSE),"") -> Maquinaria | I60: SET UP | J60: =+VLOOKUP($I60,Tabla7[#All],2,FALSE) -> PROGRAMADA | K60: =IF(VLOOKUP(I60,Tabla7[#All],3,FALSE)=0,"",VLOOKUP(I60,Tabla7[#All],3,FALSE)) | L60: Limpieza de módulo mds | M60: Desarmado de formato cremas de mds | N60: {=IFERROR(IF(Tabla8[[#This Row],[P/NP]]="NO PROGRAMADA","",_xlfn.TEXTJOIN(", ",TRUE,_xlfn._xlws.FILTER(Tabla4[[#All],[PIEZA]],ISNUMBER(SEARCH(Tabla4[[#All],[PCLAVE]],Tabla8[[#This Row],[DESCRIPCION DE TRABAJO]])),""))),"")} | O60: {=_xlfn.TEXTJOIN(", ",TRUE,_xlfn._xlws.FILTER(Tabla28[[#All],[PARTE]],ISNUMBER(SEARCH(Tabla28[[#All],[PCLAVE2]],Tabla8[[#This Row],[DESCRIPCION DE TRABAJO]])),""))} -> Mds | P60: =IFERROR(LEFT(O60, FIND(",", O60)-1), O60) -> Mds | Q60: =IFERROR(IF(ISERROR(FIND(",", O60, FIND(",", O60)+1)), RIGHT(O60, LEN(O60)-FIND(",", O60)-1), MID(O60, FIND(",", O60)+2, FIND(",", O60, FIND(",", O60)+1)-FIND(",", O60)-2)), "") | R60: =IFERROR(RIGHT(O60, LEN(O60)-FIND(",", O60, FIND(",", O60)+1)-1), "") | S60: {=_xlfn.TEXTJOIN(", ",TRUE,_xlfn._xlws.FILTER(Tabla29[[#All],[PARTE]],ISNUMBER(SEARCH(Tabla29[[#All],[PCLAVE3]],Tabla8[[#This Row],[DESCRIPCION DE TRABAJO]])),""))} | T60: =IF(AND(Tabla8[[#This Row],[PIEZA]]="",Tabla8[[#This Row],[PARTE]]=""),"VACIO","OK") -> OK | U60: =+CONCATENATE(WEEKNUM(Tabla8[[#This Row],[FECHA]]),"-",YEAR(Tabla8[[#This Row],[FECHA]])) -> 2-2026
A61: 46028 | B61: OMAR NINA | C61: MAÑANA | D61: 0.5 | E61: 0.52083333 | F61: =+MOD(Tabla8[[#This Row],[HR. FIN]]-Tabla8[[#This Row],[HR. INICIO]],1) -> 0.020833333 | G61: EMP. 1 - CHOCOTECH | H61: =IFERROR(VLOOKUP(G61,DATOS!$M$2:$N$219,2,FALSE),"") -> Maquinaria | I61: Inspección | J61: =+VLOOKUP($I61,Tabla7[#All],2,FALSE) -> PROGRAMADA | K61: =IF(VLOOKUP(I61,Tabla7[#All],3,FALSE)=0,"",VLOOKUP(I61,Tabla7[#All],3,FALSE)) | L61: Inspección funcionamiento de equipo | N61: {=IFERROR(IF(Tabla8[[#This Row],[P/NP]]="NO PROGRAMADA","",_xlfn.TEXTJOIN(", ",TRUE,_xlfn._xlws.FILTER(Tabla4[[#All],[PIEZA]],ISNUMBER(SEARCH(Tabla4[[#All],[PCLAVE]],Tabla8[[#This Row],[DESCRIPCION DE TRABAJO]])),""))),"")} | O61: {=_xlfn.TEXTJOIN(", ",TRUE,_xlfn._xlws.FILTER(Tabla28[[#All],[PARTE]],ISNUMBER(SEARCH(Tabla28[[#All],[PCLAVE2]],Tabla8[[#This Row],[DESCRIPCION DE TRABAJO]])),""))} | P61: =IFERROR(LEFT(O61, FIND(",", O61)-1), O61) | Q61: =IFERROR(IF(ISERROR(FIND(",", O61, FIND(",", O61)+1)), RIGHT(O61, LEN(O61)-FIND(",", O61)-1), MID(O61, FIND(",", O61)+2, FIND(",", O61, FIND(",", O61)+1)-FIND(",", O61)-2)), "") | R61: =IFERROR(RIGHT(O61, LEN(O61)-FIND(",", O61, FIND(",", O61)+1)-1), "") | S61: {=_xlfn.TEXTJOIN(", ",TRUE,_xlfn._xlws.FILTER(Tabla29[[#All],[PARTE]],ISNUMBER(SEARCH(Tabla29[[#All],[PCLAVE3]],Tabla8[[#This Row],[DESCRIPCION DE TRABAJO]])),""))} | T61: =IF(AND(Tabla8[[#This Row],[PIEZA]]="",Tabla8[[#This Row],[PARTE]]=""),"VACIO","OK") -> VACIO | U61: =+CONCATENATE(WEEKNUM(Tabla8[[#This Row],[FECHA]]),"-",YEAR(Tabla8[[#This Row],[FECHA]])) -> 2-2026
A62: 46028 | B62: OMAR NINA | C62: MAÑANA | D62: 0.35416667 | E62: 0.375 | F62: =+MOD(Tabla8[[#This Row],[HR. FIN]]-Tabla8[[#This Row],[HR. INICIO]],1) -> 0.020833333 | G62: QUEBRANTADOR DE CACAO 01 JAF INOX | H62: =IFERROR(VLOOKUP(G62,DATOS!$M$2:$N$219,2,FALSE),"") -> Maquinaria | I62: Ajuste /Calibracion | J62: PROGRAMADA | L62: Inspección funcionamiento de equipo | M62: Se regula aspiración de cascarilla | N62: {=IFERROR(IF(Tabla8[[#This Row],[P/NP]]="NO PROGRAMADA","",_xlfn.TEXTJOIN(", ",TRUE,_xlfn._xlws.FILTER(Tabla4[[#All],[PIEZA]],ISNUMBER(SEARCH(Tabla4[[#All],[PCLAVE]],Tabla8[[#This Row],[DESCRIPCION DE TRABAJO]])),""))),"")} | O62: {=_xlfn.TEXTJOIN(", ",TRUE,_xlfn._xlws.FILTER(Tabla28[[#All],[PARTE]],ISNUMBER(SEARCH(Tabla28[[#All],[PCLAVE2]],Tabla8[[#This Row],[DESCRIPCION DE TRABAJO]])),""))} | P62: =IFERROR(LEFT(O62, FIND(",", O62)-1), O62) | Q62: =IFERROR(IF(ISERROR(FIND(",", O62, FIND(",", O62)+1)), RIGHT(O62, LEN(O62)-FIND(",", O62)-1), MID(O62, FIND(",", O62)+2, FIND(",", O62, FIND(",", O62)+1)-FIND(",", O62)-2)), "") | R62: =IFERROR(RIGHT(O62, LEN(O62)-FIND(",", O62, FIND(",", O62)+1)-1), "") | S62: {=_xlfn.TEXTJOIN(", ",TRUE,_xlfn._xlws.FILTER(Tabla29[[#All],[PARTE]],ISNUMBER(SEARCH(Tabla29[[#All],[PCLAVE3]],Tabla8[[#This Row],[DESCRIPCION DE TRABAJO]])),""))} | T62: =IF(AND(Tabla8[[#This Row],[PIEZA]]="",Tabla8[[#This Row],[PARTE]]=""),"VACIO","OK") -> VACIO | U62: =+CONCATENATE(WEEKNUM(Tabla8[[#This Row],[FECHA]]),"-",YEAR(Tabla8[[#This Row],[FECHA]])) -> 2-2026
A63: 46028 | B63: JOSÉ HAÑARI | C63: TARDE | D63: 0.70833333 | E63: 0.72916667 | F63: =+MOD(Tabla8[[#This Row],[HR. FIN]]-Tabla8[[#This Row],[HR. INICIO]],1) -> 0.020833333 | G63: EMP. 2 - CARLE MONTANARY | H63: =IFERROR(VLOOKUP(G63,DATOS!$M$2:$N$219,2,FALSE),"") -> Maquinaria | I63: Ajuste /Calibracion | J63: =+VLOOKUP($I63,Tabla7[#All],2,FALSE) -> NO PROGRAMADA | K63: =IF(VLOOKUP(I63,Tabla7[#All],3,FALSE)=0,"",VLOOKUP(I63,Tabla7[#All],3,FALSE)) -> MECÁNICA | L63: Contra elevador doblado y rajado | M63: Se corrige dobaduras y se refuersa con soldadura | N63: {=IFERROR(IF(Tabla8[[#This Row],[P/NP]]="NO PROGRAMADA","",_xlfn.TEXTJOIN(", ",TRUE,_xlfn._xlws.FILTER(Tabla4[[#All],[PIEZA]],ISNUMBER(SEARCH(Tabla4[[#All],[PCLAVE]],Tabla8[[#This Row],[DESCRIPCION DE TRABAJO]])),""))),"")} | O63: {=_xlfn.TEXTJOIN(", ",TRUE,_xlfn._xlws.FILTER(Tabla28[[#All],[PARTE]],ISNUMBER(SEARCH(Tabla28[[#All],[PCLAVE2]],Tabla8[[#This Row],[DESCRIPCION DE TRABAJO]])),""))} | P63: =IFERROR(LEFT(O63, FIND(",", O63)-1), O63) | Q63: =IFERROR(IF(ISERROR(FIND(",", O63, FIND(",", O63)+1)), RIGHT(O63, LEN(O63)-FIND(",", O63)-1), MID(O63, FIND(",", O63)+2, FIND(",", O63, FIND(",", O63)+1)-FIND(",", O63)-2)), "") | R63: =IFERROR(RIGHT(O63, LEN(O63)-FIND(",", O63, FIND(",", O63)+1)-1), "") | S63: {=_xlfn.TEXTJOIN(", ",TRUE,_xlfn._xlws.FILTER(Tabla29[[#All],[PARTE]],ISNUMBER(SEARCH(Tabla29[[#All],[PCLAVE3]],Tabla8[[#This Row],[DESCRIPCION DE TRABAJO]])),""))} -> Doblada, Rajadura | T63: =IF(AND(Tabla8[[#This Row],[PIEZA]]="",Tabla8[[#This Row],[PARTE]]=""),"VACIO","OK") -> VACIO | U63: =+CONCATENATE(WEEKNUM(Tabla8[[#This Row],[FECHA]]),"-",YEAR(Tabla8[[#This Row],[FECHA]])) -> 2-2026
A64: 46028 | B64: CESAR QUIROZ | C64: TARDE | D64: 0.56458333 | E64: 0.58263889 | F64: =+MOD(Tabla8[[#This Row],[HR. FIN]]-Tabla8[[#This Row],[HR. INICIO]],1) -> 0.018055556 | G64: MOLINO BILLAS | H64: =IFERROR(VLOOKUP(G64,DATOS!$M$2:$N$219,2,FALSE),"") -> Maquinaria | I64: SET UP | J64: NO PROGRAMADA | K64: ELÉCTRICA | L64: No inicia, tablero de tanque de pasta gruesa desactivado | M64: Se habilitó tablero de tanque de pasta gruesa, se verifico calentamiento de chaqueta, se encendio molino de villas, se dejó trabajando | N64: {=IFERROR(IF(Tabla8[[#This Row],[P/NP]]="NO PROGRAMADA","",_xlfn.TEXTJOIN(", ",TRUE,_xlfn._xlws.FILTER(Tabla4[[#All],[PIEZA]],ISNUMBER(SEARCH(Tabla4[[#All],[PCLAVE]],Tabla8[[#This Row],[DESCRIPCION DE TRABAJO]])),""))),"")} | O64: {=_xlfn.TEXTJOIN(", ",TRUE,_xlfn._xlws.FILTER(Tabla28[[#All],[PARTE]],ISNUMBER(SEARCH(Tabla28[[#All],[PCLAVE2]],Tabla8[[#This Row],[DESCRIPCION DE TRABAJO]])),""))} -> Tanque | P64: =IFERROR(LEFT(O64, FIND(",", O64)-1), O64) -> Tanque | Q64: =IFERROR(IF(ISERROR(FIND(",", O64, FIND(",", O64)+1)), RIGHT(O64, LEN(O64)-FIND(",", O64)-1), MID(O64, FIND(",", O64)+2, FIND(",", O64, FIND(",", O64)+1)-FIND(",", O64)-2)), "") | R64: =IFERROR(RIGHT(O64, LEN(O64)-FIND(",", O64, FIND(",", O64)+1)-1), "") | S64: {=_xlfn.TEXTJOIN(", ",TRUE,_xlfn._xlws.FILTER(Tabla29[[#All],[PARTE]],ISNUMBER(SEARCH(Tabla29[[#All],[PCLAVE3]],Tabla8[[#This Row],[DESCRIPCION DE TRABAJO]])),""))} -> No Inicia | T64: =IF(AND(Tabla8[[#This Row],[PIEZA]]="",Tabla8[[#This Row],[PARTE]]=""),"VACIO","OK") -> OK | U64: =+CONCATENATE(WEEKNUM(Tabla8[[#This Row],[FECHA]]),"-",YEAR(Tabla8[[#This Row],[FECHA]])) -> 2-2026
A65: 46028 | B65: CESAR QUIROZ | C65: TARDE | D65: 0.61458333 | E65: 0.63263889 | F65: =+MOD(Tabla8[[#This Row],[HR. FIN]]-Tabla8[[#This Row],[HR. INICIO]],1) -> 0.018055556 | G65: CODIFICADORA MARKEM IMAJE 9450 4TO PISO | H65: =IFERROR(VLOOKUP(G65,DATOS!$M$2:$N$219,2,FALSE),"") -> Maquinaria | I65: Limpieza | J65: =+VLOOKUP($I65,Tabla7[#All],2,FALSE) -> PROGRAMADA | K65: =IF(VLOOKUP(I65,Tabla7[#All],3,FALSE)=0,"",VLOOKUP(I65,Tabla7[#All],3,FALSE)) | L65: No imprime bien | M65: Se realizó limpieza de cabezal y se realizó pruebas de funcionamiento | N65: {=IFERROR(IF(Tabla8[[#This Row],[P/NP]]="NO PROGRAMADA","",_xlfn.TEXTJOIN(", ",TRUE,_xlfn._xlws.FILTER(Tabla4[[#All],[PIEZA]],ISNUMBER(SEARCH(Tabla4[[#All],[PCLAVE]],Tabla8[[#This Row],[DESCRIPCION DE TRABAJO]])),""))),"")} | O65: {=_xlfn.TEXTJOIN(", ",TRUE,_xlfn._xlws.FILTER(Tabla28[[#All],[PARTE]],ISNUMBER(SEARCH(Tabla28[[#All],[PCLAVE2]],Tabla8[[#This Row],[DESCRIPCION DE TRABAJO]])),""))} | P65: =IFERROR(LEFT(O65, FIND(",", O65)-1), O65) | Q65: =IFERROR(IF(ISERROR(FIND(",", O65, FIND(",", O65)+1)), RIGHT(O65, LEN(O65)-FIND(",", O65)-1), MID(O65, FIND(",", O65)+2, FIND(",", O65, FIND(",", O65)+1)-FIND(",", O65)-2)), "") | R65: =IFERROR(RIGHT(O65, LEN(O65)-FIND(",", O65, FIND(",", O65)+1)-1), "") | S65: {=_xlfn.TEXTJOIN(", ",TRUE,_xlfn._xlws.FILTER(Tabla29[[#All],[PARTE]],ISNUMBER(SEARCH(Tabla29[[#All],[PCLAVE3]],Tabla8[[#This Row],[DESCRIPCION DE TRABAJO]])),""))} -> No Imprime | T65: =IF(AND(Tabla8[[#This Row],[PIEZA]]="",Tabla8[[#This Row],[PARTE]]=""),"VACIO","OK") -> VACIO | U65: =+CONCATENATE(WEEKNUM(Tabla8[[#This Row],[FECHA]]),"-",YEAR(Tabla8[[#This Row],[FECHA]])) -> 2-2026
A66: 46028 | B66: OMAR NINA | C66: MAÑANA | D66: 0.32986111 | E66: 0.34722222 | F66: =+MOD(Tabla8[[#This Row],[HR. FIN]]-Tabla8[[#This Row],[HR. INICIO]],1) -> 0.017361111 | G66: DESINFECCION DE CASTAÑA | H66: =IFERROR(VLOOKUP(G66,DATOS!$M$2:$N$219,2,FALSE),"") -> Maquinaria | I66: Ajuste /Calibracion | J66: PROGRAMADA | L66: Revisión de equipo, operador necesita hacer hervir agua | M66: Se revisó válvulas y se hizo hervir. | N66: {=IFERROR(IF(Tabla8[[#This Row],[P/NP]]="NO PROGRAMADA","",_xlfn.TEXTJOIN(", ",TRUE,_xlfn._xlws.FILTER(Tabla4[[#All],[PIEZA]],ISNUMBER(SEARCH(Tabla4[[#All],[PCLAVE]],Tabla8[[#This Row],[DESCRIPCION DE TRABAJO]])),""))),"")} | O66: {=_xlfn.TEXTJOIN(", ",TRUE,_xlfn._xlws.FILTER(Tabla28[[#All],[PARTE]],ISNUMBER(SEARCH(Tabla28[[#All],[PCLAVE2]],Tabla8[[#This Row],[DESCRIPCION DE TRABAJO]])),""))} | P66: =IFERROR(LEFT(O66, FIND(",", O66)-1), O66) | Q66: =IFERROR(IF(ISERROR(FIND(",", O66, FIND(",", O66)+1)), RIGHT(O66, LEN(O66)-FIND(",", O66)-1), MID(O66, FIND(",", O66)+2, FIND(",", O66, FIND(",", O66)+1)-FIND(",", O66)-2)), "") | R66: =IFERROR(RIGHT(O66, LEN(O66)-FIND(",", O66, FIND(",", O66)+1)-1), "") | S66: {=_xlfn.TEXTJOIN(", ",TRUE,_xlfn._xlws.FILTER(Tabla29[[#All],[PARTE]],ISNUMBER(SEARCH(Tabla29[[#All],[PCLAVE3]],Tabla8[[#This Row],[DESCRIPCION DE TRABAJO]])),""))} | T66: =IF(AND(Tabla8[[#This Row],[PIEZA]]="",Tabla8[[#This Row],[PARTE]]=""),"VACIO","OK") -> VACIO | U66: =+CONCATENATE(WEEKNUM(Tabla8[[#This Row],[FECHA]]),"-",YEAR(Tabla8[[#This Row],[FECHA]])) -> 2-2026
A67: 46028 | B67: OMAR NINA | C67: MAÑANA | D67: 0.4375 | E67: 0.45138889 | F67: =+MOD(Tabla8[[#This Row],[HR. FIN]]-Tabla8[[#This Row],[HR. INICIO]],1) -> 0.013888889 | G67: CONCHA CLOVER 02 | H67: =IFERROR(VLOOKUP(G67,DATOS!$M$2:$N$219,2,FALSE),"") -> Maquinaria | I67: Inspección | J67: =+VLOOKUP($I67,Tabla7[#All],2,FALSE) -> PROGRAMADA | K67: =IF(VLOOKUP(I67,Tabla7[#All],3,FALSE)=0,"",VLOOKUP(I67,Tabla7[#All],3,FALSE)) | L67: Inspección visual de equipo | M67: Se informa de fisura en chaqueta de agua. | N67: {=IFERROR(IF(Tabla8[[#This Row],[P/NP]]="NO PROGRAMADA","",_xlfn.TEXTJOIN(", ",TRUE,_xlfn._xlws.FILTER(Tabla4[[#All],[PIEZA]],ISNUMBER(SEARCH(Tabla4[[#All],[PCLAVE]],Tabla8[[#This Row],[DESCRIPCION DE TRABAJO]])),""))),"")} | O67: {=_xlfn.TEXTJOIN(", ",TRUE,_xlfn._xlws.FILTER(Tabla28[[#All],[PARTE]],ISNUMBER(SEARCH(Tabla28[[#All],[PCLAVE2]],Tabla8[[#This Row],[DESCRIPCION DE TRABAJO]])),""))} | P67: =IFERROR(LEFT(O67, FIND(",", O67)-1), O67) | Q67: =IFERROR(IF(ISERROR(FIND(",", O67, FIND(",", O67)+1)), RIGHT(O67, LEN(O67)-FIND(",", O67)-1), MID(O67, FIND(",", O67)+2, FIND(",", O67, FIND(",", O67)+1)-FIND(",", O67)-2)), "") | R67: =IFERROR(RIGHT(O67, LEN(O67)-FIND(",", O67, FIND(",", O67)+1)-1), "") | S67: {=_xlfn.TEXTJOIN(", ",TRUE,_xlfn._xlws.FILTER(Tabla29[[#All],[PARTE]],ISNUMBER(SEARCH(Tabla29[[#All],[PCLAVE3]],Tabla8[[#This Row],[DESCRIPCION DE TRABAJO]])),""))} | T67: =IF(AND(Tabla8[[#This Row],[PIEZA]]="",Tabla8[[#This Row],[PARTE]]=""),"VACIO","OK") -> VACIO | U67: =+CONCATENATE(WEEKNUM(Tabla8[[#This Row],[FECHA]]),"-",YEAR(Tabla8[[#This Row],[FECHA]])) -> 2-2026
A68: 46028 | B68: CARLOS TAPIA | C68: MAÑANA | D68: 0.52777778 | E68: 0.54166667 | F68: =+MOD(Tabla8[[#This Row],[HR. FIN]]-Tabla8[[#This Row],[HR. INICIO]],1) -> 0.013888889 | G68: LINEA AUTOMATICA HACOS 1 | H68: =IFERROR(VLOOKUP(G68,DATOS!$M$2:$N$219,2,FALSE),"") -> Maquinaria | I68: Inspección | J68: =+VLOOKUP($I68,Tabla7[#All],2,FALSE) -> PROGRAMADA | K68: =IF(VLOOKUP(I68,Tabla7[#All],3,FALSE)=0,"",VLOOKUP(I68,Tabla7[#All],3,FALSE)) | L68: Inspección de máquina. | M68: Se dió seguimiento al funcionamiento de máquina | N68: {=IFERROR(IF(Tabla8[[#This Row],[P/NP]]="NO PROGRAMADA","",_xlfn.TEXTJOIN(", ",TRUE,_xlfn._xlws.FILTER(Tabla4[[#All],[PIEZA]],ISNUMBER(SEARCH(Tabla4[[#All],[PCLAVE]],Tabla8[[#This Row],[DESCRIPCION DE TRABAJO]])),""))),"")} | O68: {=_xlfn.TEXTJOIN(", ",TRUE,_xlfn._xlws.FILTER(Tabla28[[#All],[PARTE]],ISNUMBER(SEARCH(Tabla28[[#All],[PCLAVE2]],Tabla8[[#This Row],[DESCRIPCION DE TRABAJO]])),""))} | P68: =IFERROR(LEFT(O68, FIND(",", O68)-1), O68) | Q68: =IFERROR(IF(ISERROR(FIND(",", O68, FIND(",", O68)+1)), RIGHT(O68, LEN(O68)-FIND(",", O68)-1), MID(O68, FIND(",", O68)+2, FIND(",", O68, FIND(",", O68)+1)-FIND(",", O68)-2)), "") | R68: =IFERROR(RIGHT(O68, LEN(O68)-FIND(",", O68, FIND(",", O68)+1)-1), "") | S68: {=_xlfn.TEXTJOIN(", ",TRUE,_xlfn._xlws.FILTER(Tabla29[[#All],[PARTE]],ISNUMBER(SEARCH(Tabla29[[#All],[PCLAVE3]],Tabla8[[#This Row],[DESCRIPCION DE TRABAJO]])),""))} | T68: =IF(AND(Tabla8[[#This Row],[PIEZA]]="",Tabla8[[#This Row],[PARTE]]=""),"VACIO","OK") -> VACIO | U68: =+CONCATENATE(WEEKNUM(Tabla8[[#This Row],[FECHA]]),"-",YEAR(Tabla8[[#This Row],[FECHA]])) -> 2-2026
A69: 46028 | B69: CESAR QUIROZ | C69: TARDE | D69: 0.52569444 | E69: 0.53888889 | F69: =+MOD(Tabla8[[#This Row],[HR. FIN]]-Tabla8[[#This Row],[HR. INICIO]],1) -> 0.013194444 | G69: CALDERO, CHRILLER Y COMPRESOR | H69: =IFERROR(VLOOKUP(G69,DATOS!$M$2:$N$219,2,FALSE),"") -> Equipos auxiliares | I69: Inspección | J69: =+VLOOKUP($I69,Tabla7[#All],2,FALSE) -> PROGRAMADA | K69: =IF(VLOOKUP(I69,Tabla7[#All],3,FALSE)=0,"",VLOOKUP(I69,Tabla7[#All],3,FALSE)) | L69: Revisión de funcionamiento y parámetros de trabajo de equipos | N69: {=IFERROR(IF(Tabla8[[#This Row],[P/NP]]="NO PROGRAMADA","",_xlfn.TEXTJOIN(", ",TRUE,_xlfn._xlws.FILTER(Tabla4[[#All],[PIEZA]],ISNUMBER(SEARCH(Tabla4[[#All],[PCLAVE]],Tabla8[[#This Row],[DESCRIPCION DE TRABAJO]])),""))),"")} | O69: {=_xlfn.TEXTJOIN(", ",TRUE,_xlfn._xlws.FILTER(Tabla28[[#All],[PARTE]],ISNUMBER(SEARCH(Tabla28[[#All],[PCLAVE2]],Tabla8[[#This Row],[DESCRIPCION DE TRABAJO]])),""))} | P69: =IFERROR(LEFT(O69, FIND(",", O69)-1), O69) | Q69: =IFERROR(IF(ISERROR(FIND(",", O69, FIND(",", O69)+1)), RIGHT(O69, LEN(O69)-FIND(",", O69)-1), MID(O69, FIND(",", O69)+2, FIND(",", O69, FIND(",", O69)+1)-FIND(",", O69)-2)), "") | R69: =IFERROR(RIGHT(O69, LEN(O69)-FIND(",", O69, FIND(",", O69)+1)-1), "") | S69: {=_xlfn.TEXTJOIN(", ",TRUE,_xlfn._xlws.FILTER(Tabla29[[#All],[PARTE]],ISNUMBER(SEARCH(Tabla29[[#All],[PCLAVE3]],Tabla8[[#This Row],[DESCRIPCION DE TRABAJO]])),""))} | T69: =IF(AND(Tabla8[[#This Row],[PIEZA]]="",Tabla8[[#This Row],[PARTE]]=""),"VACIO","OK") -> VACIO | U69: =+CONCATENATE(WEEKNUM(Tabla8[[#This Row],[FECHA]]),"-",YEAR(Tabla8[[#This Row],[FECHA]])) -> 2-2026
A70: 46028 | B70: CESAR QUIROZ | C70: TARDE | D70: 0.54791667 | E70: 0.56111111 | F70: =+MOD(Tabla8[[#This Row],[HR. FIN]]-Tabla8[[#This Row],[HR. INICIO]],1) -> 0.013194444 | G70: BATIDORA DE HUEVOS 01 SUPERMAP | H70: =IFERROR(VLOOKUP(G70,DATOS!$M$2:$N$219,2,FALSE),"") -> Maquinaria | I70: Sustitucion | J70: =+VLOOKUP($I70,Tabla7[#All],2,FALSE) -> NO PROGRAMADA | K70: MECÁNICA | L70: Accesorio con presencia de oxido en pernos | M70: Se apoyo en el cambio de pernos y limpieza de oxido | N70: {=IFERROR(IF(Tabla8[[#This Row],[P/NP]]="NO PROGRAMADA","",_xlfn.TEXTJOIN(", ",TRUE,_xlfn._xlws.FILTER(Tabla4[[#All],[PIEZA]],ISNUMBER(SEARCH(Tabla4[[#All],[PCLAVE]],Tabla8[[#This Row],[DESCRIPCION DE TRABAJO]])),""))),"")} | O70: {=_xlfn.TEXTJOIN(", ",TRUE,_xlfn._xlws.FILTER(Tabla28[[#All],[PARTE]],ISNUMBER(SEARCH(Tabla28[[#All],[PCLAVE2]],Tabla8[[#This Row],[DESCRIPCION DE TRABAJO]])),""))} | P70: =IFERROR(LEFT(O70, FIND(",", O70)-1), O70) | Q70: =IFERROR(IF(ISERROR(FIND(",", O70, FIND(",", O70)+1)), RIGHT(O70, LEN(O70)-FIND(",", O70)-1), MID(O70, FIND(",", O70)+2, FIND(",", O70, FIND(",", O70)+1)-FIND(",", O70)-2)), "") | R70: =IFERROR(RIGHT(O70, LEN(O70)-FIND(",", O70, FIND(",", O70)+1)-1), "") | S70: {=_xlfn.TEXTJOIN(", ",TRUE,_xlfn._xlws.FILTER(Tabla29[[#All],[PARTE]],ISNUMBER(SEARCH(Tabla29[[#All],[PCLAVE3]],Tabla8[[#This Row],[DESCRIPCION DE TRABAJO]])),""))} -> Con Oxido | T70: =IF(AND(Tabla8[[#This Row],[PIEZA]]="",Tabla8[[#This Row],[PARTE]]=""),"VACIO","OK") -> VACIO | U70: =+CONCATENATE(WEEKNUM(Tabla8[[#This Row],[FECHA]]),"-",YEAR(Tabla8[[#This Row],[FECHA]])) -> 2-2026
A71: 46028 | B71: OMAR NINA | C71: MAÑANA | D71: 0.26041667 | E71: 0.27083333 | F71: =+MOD(Tabla8[[#This Row],[HR. FIN]]-Tabla8[[#This Row],[HR. INICIO]],1) -> 0.010416667 | G71: LINEA AUTOMATICA HACOS 1 | H71: =IFERROR(VLOOKUP(G71,DATOS!$M$2:$N$219,2,FALSE),"") -> Maquinaria | I71: SET UP | J71: NO PROGRAMADA | K71: ELÉCTRICA | L71: Temperadora bloqueada, no hay chocolate en tanque | M71: Se restablece guardamotor y se deja en modo calentamiento | N71: {=IFERROR(IF(Tabla8[[#This Row],[P/NP]]="NO PROGRAMADA","",_xlfn.TEXTJOIN(", ",TRUE,_xlfn._xlws.FILTER(Tabla4[[#All],[PIEZA]],ISNUMBER(SEARCH(Tabla4[[#All],[PCLAVE]],Tabla8[[#This Row],[DESCRIPCION DE TRABAJO]])),""))),"")} | O71: {=_xlfn.TEXTJOIN(", ",TRUE,_xlfn._xlws.FILTER(Tabla28[[#All],[PARTE]],ISNUMBER(SEARCH(Tabla28[[#All],[PCLAVE2]],Tabla8[[#This Row],[DESCRIPCION DE TRABAJO]])),""))} -> Tanque, Temperadora | P71: =IFERROR(LEFT(O71, FIND(",", O71)-1), O71) -> Tanque | Q71: =IFERROR(IF(ISERROR(FIND(",", O71, FIND(",", O71)+1)), RIGHT(O71, LEN(O71)-FIND(",", O71)-1), MID(O71, FIND(",", O71)+2, FIND(",", O71, FIND(",", O71)+1)-FIND(",", O71)-2)), "") -> Temperadora | R71: =IFERROR(RIGHT(O71, LEN(O71)-FIND(",", O71, FIND(",", O71)+1)-1), "") | S71: {=_xlfn.TEXTJOIN(", ",TRUE,_xlfn._xlws.FILTER(Tabla29[[#All],[PARTE]],ISNUMBER(SEARCH(Tabla29[[#All],[PCLAVE3]],Tabla8[[#This Row],[DESCRIPCION DE TRABAJO]])),""))} -> Bloqueado | T71: =IF(AND(Tabla8[[#This Row],[PIEZA]]="",Tabla8[[#This Row],[PARTE]]=""),"VACIO","OK") -> OK | U71: =+CONCATENATE(WEEKNUM(Tabla8[[#This Row],[FECHA]]),"-",YEAR(Tabla8[[#This Row],[FECHA]])) -> 2-2026
A72: 46029 | B72: CARLOS TAPIA | C72: MAÑANA | D72: 0.39583333 | E72: 0.4375 | F72: =+MOD(Tabla8[[#This Row],[HR. FIN]]-Tabla8[[#This Row],[HR. INICIO]],1) -> 0.041666667 | G72: RAYOS X 2 | H72: =IFERROR(VLOOKUP(G72,DATOS!$M$2:$N$219,2,FALSE),"") -> Maquinaria | I72: Ajuste /Calibracion | J72: =+VLOOKUP($I72,Tabla7[#All],2,FALSE) -> NO PROGRAMADA | K72: =IF(VLOOKUP(I72,Tabla7[#All],3,FALSE)=0,"",VLOOKUP(I72,Tabla7[#All],3,FALSE)) -> MECÁNICA | L72: Equipo presenta error E8 y E9. | M72: Se revisó equipo y se restableció enfriador. | N72: {=IFERROR(IF(Tabla8[[#This Row],[P/NP]]="NO PROGRAMADA","",_xlfn.TEXTJOIN(", ",TRUE,_xlfn._xlws.FILTER(Tabla4[[#All],[PIEZA]],ISNUMBER(SEARCH(Tabla4[[#All],[PCLAVE]],Tabla8[[#This Row],[DESCRIPCION DE TRABAJO]])),""))),"")} | O72: {=_xlfn.TEXTJOIN(", ",TRUE,_xlfn._xlws.FILTER(Tabla28[[#All],[PARTE]],ISNUMBER(SEARCH(Tabla28[[#All],[PCLAVE2]],Tabla8[[#This Row],[DESCRIPCION DE TRABAJO]])),""))} | P72: =IFERROR(LEFT(O72, FIND(",", O72)-1), O72) | Q72: =IFERROR(IF(ISERROR(FIND(",", O72, FIND(",", O72)+1)), RIGHT(O72, LEN(O72)-FIND(",", O72)-1), MID(O72, FIND(",", O72)+2, FIND(",", O72, FIND(",", O72)+1)-FIND(",", O72)-2)), "") | R72: =IFERROR(RIGHT(O72, LEN(O72)-FIND(",", O72, FIND(",", O72)+1)-1), "") | S72: {=_xlfn.TEXTJOIN(", ",TRUE,_xlfn._xlws.FILTER(Tabla29[[#All],[PARTE]],ISNUMBER(SEARCH(Tabla29[[#All],[PCLAVE3]],Tabla8[[#This Row],[DESCRIPCION DE TRABAJO]])),""))} -> Error | T72: =IF(AND(Tabla8[[#This Row],[PIEZA]]="",Tabla8[[#This Row],[PARTE]]=""),"VACIO","OK") -> VACIO | U72: =+CONCATENATE(WEEKNUM(Tabla8[[#This Row],[FECHA]]),"-",YEAR(Tabla8[[#This Row],[FECHA]])) -> 2-2026
A73: 46029 | B73: OMAR NINA | C73: MAÑANA | D73: 0.53472222 | E73: 0.56597222 | F73: =+MOD(Tabla8[[#This Row],[HR. FIN]]-Tabla8[[#This Row],[HR. INICIO]],1) -> 0.03125 | G73: EMP. SAPAL | H73: =IFERROR(VLOOKUP(G73,DATOS!$M$2:$N$219,2,FALSE),"") -> Maquinaria | I73: SET UP | J73: =+VLOOKUP($I73,Tabla7[#All],2,FALSE) -> PROGRAMADA | K73: =IF(VLOOKUP(I73,Tabla7[#All],3,FALSE)=0,"",VLOOKUP(I73,Tabla7[#All],3,FALSE)) | L73: Inspección de equipo | M73: Ajuste de medida 4 y apoyo en configuración de formato de fecha | N73: {=IFERROR(IF(Tabla8[[#This Row],[P/NP]]="NO PROGRAMADA","",_xlfn.TEXTJOIN(", ",TRUE,_xlfn._xlws.FILTER(Tabla4[[#All],[PIEZA]],ISNUMBER(SEARCH(Tabla4[[#All],[PCLAVE]],Tabla8[[#This Row],[DESCRIPCION DE TRABAJO]])),""))),"")} | O73: {=_xlfn.TEXTJOIN(", ",TRUE,_xlfn._xlws.FILTER(Tabla28[[#All],[PARTE]],ISNUMBER(SEARCH(Tabla28[[#All],[PCLAVE2]],Tabla8[[#This Row],[DESCRIPCION DE TRABAJO]])),""))} | P73: =IFERROR(LEFT(O73, FIND(",", O73)-1), O73) | Q73: =IFERROR(IF(ISERROR(FIND(",", O73, FIND(",", O73)+1)), RIGHT(O73, LEN(O73)-FIND(",", O73)-1), MID(O73, FIND(",", O73)+2, FIND(",", O73, FIND(",", O73)+1)-FIND(",", O73)-2)), "") | R73: =IFERROR(RIGHT(O73, LEN(O73)-FIND(",", O73, FIND(",", O73)+1)-1), "") | S73: {=_xlfn.TEXTJOIN(", ",TRUE,_xlfn._xlws.FILTER(Tabla29[[#All],[PARTE]],ISNUMBER(SEARCH(Tabla29[[#All],[PCLAVE3]],Tabla8[[#This Row],[DESCRIPCION DE TRABAJO]])),""))} | T73: =IF(AND(Tabla8[[#This Row],[PIEZA]]="",Tabla8[[#This Row],[PARTE]]=""),"VACIO","OK") -> VACIO | U73: =+CONCATENATE(WEEKNUM(Tabla8[[#This Row],[FECHA]]),"-",YEAR(Tabla8[[#This Row],[FECHA]])) -> 2-2026
A74: 46029 | B74: OMAR NINA | C74: MAÑANA | D74: 0.34027778 | E74: 0.36666667 | F74: =+MOD(Tabla8[[#This Row],[HR. FIN]]-Tabla8[[#This Row],[HR. INICIO]],1) -> 0.026388889 | G74: RAYOS X 1 | H74: =IFERROR(VLOOKUP(G74,DATOS!$M$2:$N$219,2,FALSE),"") -> Maquinaria | I74: Inspección | J74: NO PROGRAMADA | K74: ELÉCTRICA | L74: No enciende la mesa de vibración con el pulsador de reset. | M74: Se revisa conección eléctrica. Estado de relés. | N74: {=IFERROR(IF(Tabla8[[#This Row],[P/NP]]="NO PROGRAMADA","",_xlfn.TEXTJOIN(", ",TRUE,_xlfn._xlws.FILTER(Tabla4[[#All],[PIEZA]],ISNUMBER(SEARCH(Tabla4[[#All],[PCLAVE]],Tabla8[[#This Row],[DESCRIPCION DE TRABAJO]])),""))),"")} | O74: {=_xlfn.TEXTJOIN(", ",TRUE,_xlfn._xlws.FILTER(Tabla28[[#All],[PARTE]],ISNUMBER(SEARCH(Tabla28[[#All],[PCLAVE2]],Tabla8[[#This Row],[DESCRIPCION DE TRABAJO]])),""))} | P74: =IFERROR(LEFT(O74, FIND(",", O74)-1), O74) | Q74: =IFERROR(IF(ISERROR(FIND(",", O74, FIND(",", O74)+1)), RIGHT(O74, LEN(O74)-FIND(",", O74)-1), MID(O74, FIND(",", O74)+2, FIND(",", O74, FIND(",", O74)+1)-FIND(",", O74)-2)), "") | R74: =IFERROR(RIGHT(O74, LEN(O74)-FIND(",", O74, FIND(",", O74)+1)-1), "") | S74: {=_xlfn.TEXTJOIN(", ",TRUE,_xlfn._xlws.FILTER(Tabla29[[#All],[PARTE]],ISNUMBER(SEARCH(Tabla29[[#All],[PCLAVE3]],Tabla8[[#This Row],[DESCRIPCION DE TRABAJO]])),""))} -> No Enciende, Reset, Vibracion | T74: =IF(AND(Tabla8[[#This Row],[PIEZA]]="",Tabla8[[#This Row],[PARTE]]=""),"VACIO","OK") -> VACIO | U74: =+CONCATENATE(WEEKNUM(Tabla8[[#This Row],[FECHA]]),"-",YEAR(Tabla8[[#This Row],[FECHA]])) -> 2-2026
A75: 46029 | B75: OMAR NINA | C75: MAÑANA | D75: 0.29166667 | E75: 0.31597222 | F75: =+MOD(Tabla8[[#This Row],[HR. FIN]]-Tabla8[[#This Row],[HR. INICIO]],1) -> 0.024305556 | G75: ENCELOFANADORA ECCOPAC | H75: =IFERROR(VLOOKUP(G75,DATOS!$M$2:$N$219,2,FALSE),"") -> Maquinaria | I75: Ajuste /Calibracion | J75: =+VLOOKUP($I75,Tabla7[#All],2,FALSE) -> NO PROGRAMADA | K75: =IF(VLOOKUP(I75,Tabla7[#All],3,FALSE)=0,"",VLOOKUP(I75,Tabla7[#All],3,FALSE)) -> MECÁNICA | L75: Aplasta cajas, y no sella | M75: Se calibra presión inicial de cajas. Altura de cuchilla y plegadores | N75: {=IFERROR(IF(Tabla8[[#This Row],[P/NP]]="NO PROGRAMADA","",_xlfn.TEXTJOIN(", ",TRUE,_xlfn._xlws.FILTER(Tabla4[[#All],[PIEZA]],ISNUMBER(SEARCH(Tabla4[[#All],[PCLAVE]],Tabla8[[#This Row],[DESCRIPCION DE TRABAJO]])),""))),"")} | O75: {=_xlfn.TEXTJOIN(", ",TRUE,_xlfn._xlws.FILTER(Tabla28[[#All],[PARTE]],ISNUMBER(SEARCH(Tabla28[[#All],[PCLAVE2]],Tabla8[[#This Row],[DESCRIPCION DE TRABAJO]])),""))} | P75: =IFERROR(LEFT(O75, FIND(",", O75)-1), O75) | Q75: =IFERROR(IF(ISERROR(FIND(",", O75, FIND(",", O75)+1)), RIGHT(O75, LEN(O75)-FIND(",", O75)-1), MID(O75, FIND(",", O75)+2, FIND(",", O75, FIND(",", O75)+1)-FIND(",", O75)-2)), "") | R75: =IFERROR(RIGHT(O75, LEN(O75)-FIND(",", O75, FIND(",", O75)+1)-1), "") | S75: {=_xlfn.TEXTJOIN(", ",TRUE,_xlfn._xlws.FILTER(Tabla29[[#All],[PARTE]],ISNUMBER(SEARCH(Tabla29[[#All],[PCLAVE3]],Tabla8[[#This Row],[DESCRIPCION DE TRABAJO]])),""))} -> No Sella | T75: =IF(AND(Tabla8[[#This Row],[PIEZA]]="",Tabla8[[#This Row],[PARTE]]=""),"VACIO","OK") -> VACIO | U75: =+CONCATENATE(WEEKNUM(Tabla8[[#This Row],[FECHA]]),"-",YEAR(Tabla8[[#This Row],[FECHA]])) -> 2-2026
A76: 46029 | B76: OMAR NINA | C76: MAÑANA | D76: 0.38541667 | E76: 0.40972222 | F76: =+MOD(Tabla8[[#This Row],[HR. FIN]]-Tabla8[[#This Row],[HR. INICIO]],1) -> 0.024305556 | G76: RAYOS X 2 | H76: =IFERROR(VLOOKUP(G76,DATOS!$M$2:$N$219,2,FALSE),"") -> Maquinaria | I76: Limpieza | J76: NO PROGRAMADA | K76: MECÁNICA | L76: Alarma de temperatura no deja iniciar equipo | M76: Se realiza limpieza de condensador y se realiza pruebas de funcionamiento | N76: {=IFERROR(IF(Tabla8[[#This Row],[P/NP]]="NO PROGRAMADA","",_xlfn.TEXTJOIN(", ",TRUE,_xlfn._xlws.FILTER(Tabla4[[#All],[PIEZA]],ISNUMBER(SEARCH(Tabla4[[#All],[PCLAVE]],Tabla8[[#This Row],[DESCRIPCION DE TRABAJO]])),""))),"")} | O76: {=_xlfn.TEXTJOIN(", ",TRUE,_xlfn._xlws.FILTER(Tabla28[[#All],[PARTE]],ISNUMBER(SEARCH(Tabla28[[#All],[PCLAVE2]],Tabla8[[#This Row],[DESCRIPCION DE TRABAJO]])),""))} | P76: =IFERROR(LEFT(O76, FIND(",", O76)-1), O76) | Q76: =IFERROR(IF(ISERROR(FIND(",", O76, FIND(",", O76)+1)), RIGHT(O76, LEN(O76)-FIND(",", O76)-1), MID(O76, FIND(",", O76)+2, FIND(",", O76, FIND(",", O76)+1)-FIND(",", O76)-2)), "") | R76: =IFERROR(RIGHT(O76, LEN(O76)-FIND(",", O76, FIND(",", O76)+1)-1), "") | S76: {=_xlfn.TEXTJOIN(", ",TRUE,_xlfn._xlws.FILTER(Tabla29[[#All],[PARTE]],ISNUMBER(SEARCH(Tabla29[[#All],[PCLAVE3]],Tabla8[[#This Row],[DESCRIPCION DE TRABAJO]])),""))} -> Alarma | T76: =IF(AND(Tabla8[[#This Row],[PIEZA]]="",Tabla8[[#This Row],[PARTE]]=""),"VACIO","OK") -> VACIO | U76: =+CONCATENATE(WEEKNUM(Tabla8[[#This Row],[FECHA]]),"-",YEAR(Tabla8[[#This Row],[FECHA]])) -> 2-2026
A77: 46029 | B77: CESAR QUIROZ | C77: TARDE | D77: 0.55138889 | E77: 0.57430556 | F77: =+MOD(Tabla8[[#This Row],[HR. FIN]]-Tabla8[[#This Row],[HR. INICIO]],1) -> 0.022916667 | G77: LINEA AUTOMATICA HACOS 1 | H77: =IFERROR(VLOOKUP(G77,DATOS!$M$2:$N$219,2,FALSE),"") -> Maquinaria | I77: SET UP | J77: =+VLOOKUP($I77,Tabla7[#All],2,FALSE) -> PROGRAMADA | K77: =IF(VLOOKUP(I77,Tabla7[#All],3,FALSE)=0,"",VLOOKUP(I77,Tabla7[#All],3,FALSE)) | L77: Armado de formato agregados x100 en mds | N77: {=IFERROR(IF(Tabla8[[#This Row],[P/NP]]="NO PROGRAMADA","",_xlfn.TEXTJOIN(", ",TRUE,_xlfn._xlws.FILTER(Tabla4[[#All],[PIEZA]],ISNUMBER(SEARCH(Tabla4[[#All],[PCLAVE]],Tabla8[[#This Row],[DESCRIPCION DE TRABAJO]])),""))),"")} | O77: {=_xlfn.TEXTJOIN(", ",TRUE,_xlfn._xlws.FILTER(Tabla28[[#All],[PARTE]],ISNUMBER(SEARCH(Tabla28[[#All],[PCLAVE2]],Tabla8[[#This Row],[DESCRIPCION DE TRABAJO]])),""))} -> Mds | P77: =IFERROR(LEFT(O77, FIND(",", O77)-1), O77) -> Mds | Q77: =IFERROR(IF(ISERROR(FIND(",", O77, FIND(",", O77)+1)), RIGHT(O77, LEN(O77)-FIND(",", O77)-1), MID(O77, FIND(",", O77)+2, FIND(",", O77, FIND(",", O77)+1)-FIND(",", O77)-2)), "") | R77: =IFERROR(RIGHT(O77, LEN(O77)-FIND(",", O77, FIND(",", O77)+1)-1), "") | S77: {=_xlfn.TEXTJOIN(", ",TRUE,_xlfn._xlws.FILTER(Tabla29[[#All],[PARTE]],ISNUMBER(SEARCH(Tabla29[[#All],[PCLAVE3]],Tabla8[[#This Row],[DESCRIPCION DE TRABAJO]])),""))} -> Cambio De Formato | T77: =IF(AND(Tabla8[[#This Row],[PIEZA]]="",Tabla8[[#This Row],[PARTE]]=""),"VACIO","OK") -> OK | U77: =+CONCATENATE(WEEKNUM(Tabla8[[#This Row],[FECHA]]),"-",YEAR(Tabla8[[#This Row],[FECHA]])) -> 2-2026
A78: 46029 | B78: CARLOS PUMA | C78: NOCHE | D78: 0.12152778 | E78: 0.13888889 | F78: =+MOD(Tabla8[[#This Row],[HR. FIN]]-Tabla8[[#This Row],[HR. INICIO]],1) -> 0.017361111 | G78: ENCELOFANADORA ECCOPAC | H78: =IFERROR(VLOOKUP(G78,DATOS!$M$2:$N$219,2,FALSE),"") -> Maquinaria | I78: Ajuste /Calibracion | J78: =+VLOOKUP($I78,Tabla7[#All],2,FALSE) -> NO PROGRAMADA | K78: =IF(VLOOKUP(I78,Tabla7[#All],3,FALSE)=0,"",VLOOKUP(I78,Tabla7[#All],3,FALSE)) -> MECÁNICA | L78: Equipo aplasta las cajas | M78: Se calibro sellador principal, laminado y apertura de mesa, se hizo pruebas y apoyó en la operación | N78: {=IFERROR(IF(Tabla8[[#This Row],[P/NP]]="NO PROGRAMADA","",_xlfn.TEXTJOIN(", ",TRUE,_xlfn._xlws.FILTER(Tabla4[[#All],[PIEZA]],ISNUMBER(SEARCH(Tabla4[[#All],[PCLAVE]],Tabla8[[#This Row],[DESCRIPCION DE TRABAJO]])),""))),"")} | O78: {=_xlfn.TEXTJOIN(", ",TRUE,_xlfn._xlws.FILTER(Tabla28[[#All],[PARTE]],ISNUMBER(SEARCH(Tabla28[[#All],[PCLAVE2]],Tabla8[[#This Row],[DESCRIPCION DE TRABAJO]])),""))} | P78: =IFERROR(LEFT(O78, FIND(",", O78)-1), O78) | Q78: =IFERROR(IF(ISERROR(FIND(",", O78, FIND(",", O78)+1)), RIGHT(O78, LEN(O78)-FIND(",", O78)-1), MID(O78, FIND(",", O78)+2, FIND(",", O78, FIND(",", O78)+1)-FIND(",", O78)-2)), "") | R78: =IFERROR(RIGHT(O78, LEN(O78)-FIND(",", O78, FIND(",", O78)+1)-1), "") | S78: {=_xlfn.TEXTJOIN(", ",TRUE,_xlfn._xlws.FILTER(Tabla29[[#All],[PARTE]],ISNUMBER(SEARCH(Tabla29[[#All],[PCLAVE3]],Tabla8[[#This Row],[DESCRIPCION DE TRABAJO]])),""))} | T78: =IF(AND(Tabla8[[#This Row],[PIEZA]]="",Tabla8[[#This Row],[PARTE]]=""),"VACIO","OK") -> VACIO | U78: =+CONCATENATE(WEEKNUM(Tabla8[[#This Row],[FECHA]]),"-",YEAR(Tabla8[[#This Row],[FECHA]])) -> 2-2026
A79: 46029 | B79: OMAR NINA | C79: MAÑANA | D79: 0.44097222 | E79: 0.45555556 | F79: =+MOD(Tabla8[[#This Row],[HR. FIN]]-Tabla8[[#This Row],[HR. INICIO]],1) -> 0.014583333 | G79: POZOS | H79: =IFERROR(VLOOKUP(G79,DATOS!$M$2:$N$219,2,FALSE),"") -> Sistema | I79: Inspección | J79: =+VLOOKUP($I79,Tabla7[#All],2,FALSE) -> PROGRAMADA | K79: =IF(VLOOKUP(I79,Tabla7[#All],3,FALSE)=0,"",VLOOKUP(I79,Tabla7[#All],3,FALSE)) | L79: Inspección de nivel de agua | N79: {=IFERROR(IF(Tabla8[[#This Row],[P/NP]]="NO PROGRAMADA","",_xlfn.TEXTJOIN(", ",TRUE,_xlfn._xlws.FILTER(Tabla4[[#All],[PIEZA]],ISNUMBER(SEARCH(Tabla4[[#All],[PCLAVE]],Tabla8[[#This Row],[DESCRIPCION DE TRABAJO]])),""))),"")} | O79: {=_xlfn.TEXTJOIN(", ",TRUE,_xlfn._xlws.FILTER(Tabla28[[#All],[PARTE]],ISNUMBER(SEARCH(Tabla28[[#All],[PCLAVE2]],Tabla8[[#This Row],[DESCRIPCION DE TRABAJO]])),""))} | P79: =IFERROR(LEFT(O79, FIND(",", O79)-1), O79) | Q79: =IFERROR(IF(ISERROR(FIND(",", O79, FIND(",", O79)+1)), RIGHT(O79, LEN(O79)-FIND(",", O79)-1), MID(O79, FIND(",", O79)+2, FIND(",", O79, FIND(",", O79)+1)-FIND(",", O79)-2)), "") | R79: =IFERROR(RIGHT(O79, LEN(O79)-FIND(",", O79, FIND(",", O79)+1)-1), "") | S79: {=_xlfn.TEXTJOIN(", ",TRUE,_xlfn._xlws.FILTER(Tabla29[[#All],[PARTE]],ISNUMBER(SEARCH(Tabla29[[#All],[PCLAVE3]],Tabla8[[#This Row],[DESCRIPCION DE TRABAJO]])),""))} -> Nivel | T79: =IF(AND(Tabla8[[#This Row],[PIEZA]]="",Tabla8[[#This Row],[PARTE]]=""),"VACIO","OK") -> VACIO | U79: =+CONCATENATE(WEEKNUM(Tabla8[[#This Row],[FECHA]]),"-",YEAR(Tabla8[[#This Row],[FECHA]])) -> 2-2026
A80: 46029 | B80: CARLOS TAPIA | C80: MAÑANA | D80: 0.31944444 | E80: 0.33333333 | F80: =+MOD(Tabla8[[#This Row],[HR. FIN]]-Tabla8[[#This Row],[HR. INICIO]],1) -> 0.013888889 | G80: CYCLOP 80 / F.HUECAS | H80: =IFERROR(VLOOKUP(G80,DATOS!$M$2:$N$219,2,FALSE),"") -> Maquinaria | I80: Inspección | J80: =+VLOOKUP($I80,Tabla7[#All],2,FALSE) -> PROGRAMADA | K80: =IF(VLOOKUP(I80,Tabla7[#All],3,FALSE)=0,"",VLOOKUP(I80,Tabla7[#All],3,FALSE)) | L80: Inspección de máquina. | M80: Se revisó y habilitó máquina. | N80: {=IFERROR(IF(Tabla8[[#This Row],[P/NP]]="NO PROGRAMADA","",_xlfn.TEXTJOIN(", ",TRUE,_xlfn._xlws.FILTER(Tabla4[[#All],[PIEZA]],ISNUMBER(SEARCH(Tabla4[[#All],[PCLAVE]],Tabla8[[#This Row],[DESCRIPCION DE TRABAJO]])),""))),"")} | O80: {=_xlfn.TEXTJOIN(", ",TRUE,_xlfn._xlws.FILTER(Tabla28[[#All],[PARTE]],ISNUMBER(SEARCH(Tabla28[[#All],[PCLAVE2]],Tabla8[[#This Row],[DESCRIPCION DE TRABAJO]])),""))} | P80: =IFERROR(LEFT(O80, FIND(",", O80)-1), O80) | Q80: =IFERROR(IF(ISERROR(FIND(",", O80, FIND(",", O80)+1)), RIGHT(O80, LEN(O80)-FIND(",", O80)-1), MID(O80, FIND(",", O80)+2, FIND(",", O80, FIND(",", O80)+1)-FIND(",", O80)-2)), "") | R80: =IFERROR(RIGHT(O80, LEN(O80)-FIND(",", O80, FIND(",", O80)+1)-1), "") | S80: {=_xlfn.TEXTJOIN(", ",TRUE,_xlfn._xlws.FILTER(Tabla29[[#All],[PARTE]],ISNUMBER(SEARCH(Tabla29[[#All],[PCLAVE3]],Tabla8[[#This Row],[DESCRIPCION DE TRABAJO]])),""))} | T80: =IF(AND(Tabla8[[#This Row],[PIEZA]]="",Tabla8[[#This Row],[PARTE]]=""),"VACIO","OK") -> VACIO | U80: =+CONCATENATE(WEEKNUM(Tabla8[[#This Row],[FECHA]]),"-",YEAR(Tabla8[[#This Row],[FECHA]])) -> 2-2026
A81: 46029 | B81: OMAR NINA | C81: MAÑANA | D81: 0.46527778 | E81: 0.47916667 | F81: =+MOD(Tabla8[[#This Row],[HR. FIN]]-Tabla8[[#This Row],[HR. INICIO]],1) -> 0.013888889 | G81: EMP. 2 - CARLE MONTANARY | H81: =IFERROR(VLOOKUP(G81,DATOS!$M$2:$N$219,2,FALSE),"") -> Maquinaria | I81: Inspección | J81: =+VLOOKUP($I81,Tabla7[#All],2,FALSE) -> PROGRAMADA | K81: =IF(VLOOKUP(I81,Tabla7[#All],3,FALSE)=0,"",VLOOKUP(I81,Tabla7[#All],3,FALSE)) | L81: Inspección de funcionamiento de equipo | N81: {=IFERROR(IF(Tabla8[[#This Row],[P/NP]]="NO PROGRAMADA","",_xlfn.TEXTJOIN(", ",TRUE,_xlfn._xlws.FILTER(Tabla4[[#All],[PIEZA]],ISNUMBER(SEARCH(Tabla4[[#All],[PCLAVE]],Tabla8[[#This Row],[DESCRIPCION DE TRABAJO]])),""))),"")} | O81: {=_xlfn.TEXTJOIN(", ",TRUE,_xlfn._xlws.FILTER(Tabla28[[#All],[PARTE]],ISNUMBER(SEARCH(Tabla28[[#All],[PCLAVE2]],Tabla8[[#This Row],[DESCRIPCION DE TRABAJO]])),""))} | P81: =IFERROR(LEFT(O81, FIND(",", O81)-1), O81) | Q81: =IFERROR(IF(ISERROR(FIND(",", O81, FIND(",", O81)+1)), RIGHT(O81, LEN(O81)-FIND(",", O81)-1), MID(O81, FIND(",", O81)+2, FIND(",", O81, FIND(",", O81)+1)-FIND(",", O81)-2)), "") | R81: =IFERROR(RIGHT(O81, LEN(O81)-FIND(",", O81, FIND(",", O81)+1)-1), "") | S81: {=_xlfn.TEXTJOIN(", ",TRUE,_xlfn._xlws.FILTER(Tabla29[[#All],[PARTE]],ISNUMBER(SEARCH(Tabla29[[#All],[PCLAVE3]],Tabla8[[#This Row],[DESCRIPCION DE TRABAJO]])),""))} | T81: =IF(AND(Tabla8[[#This Row],[PIEZA]]="",Tabla8[[#This Row],[PARTE]]=""),"VACIO","OK") -> VACIO | U81: =+CONCATENATE(WEEKNUM(Tabla8[[#This Row],[FECHA]]),"-",YEAR(Tabla8[[#This Row],[FECHA]])) -> 2-2026
A82: 46029 | B82: OMAR NINA | C82: MAÑANA | D82: 0.27083333 | E82: 0.28472222 | F82: =+MOD(Tabla8[[#This Row],[HR. FIN]]-Tabla8[[#This Row],[HR. INICIO]],1) -> 0.013888889 | G82: TOSTADOR PETRONCINI | H82: =IFERROR(VLOOKUP(G82,DATOS!$M$2:$N$219,2,FALSE),"") -> Maquinaria | I82: Ajuste /Calibracion | J82: =+VLOOKUP($I82,Tabla7[#All],2,FALSE) -> NO PROGRAMADA | K82: =IF(VLOOKUP(I82,Tabla7[#All],3,FALSE)=0,"",VLOOKUP(I82,Tabla7[#All],3,FALSE)) -> MECÁNICA | L82: No permite llenar la tolva, el tablero tiene activo el indicador de tolva llena. | M82: Se calibra posición de sensor. | N82: {=IFERROR(IF(Tabla8[[#This Row],[P/NP]]="NO PROGRAMADA","",_xlfn.TEXTJOIN(", ",TRUE,_xlfn._xlws.FILTER(Tabla4[[#All],[PIEZA]],ISNUMBER(SEARCH(Tabla4[[#All],[PCLAVE]],Tabla8[[#This Row],[DESCRIPCION DE TRABAJO]])),""))),"")} | O82: {=_xlfn.TEXTJOIN(", ",TRUE,_xlfn._xlws.FILTER(Tabla28[[#All],[PARTE]],ISNUMBER(SEARCH(Tabla28[[#All],[PCLAVE2]],Tabla8[[#This Row],[DESCRIPCION DE TRABAJO]])),""))} | P82: =IFERROR(LEFT(O82, FIND(",", O82)-1), O82) | Q82: =IFERROR(IF(ISERROR(FIND(",", O82, FIND(",", O82)+1)), RIGHT(O82, LEN(O82)-FIND(",", O82)-1), MID(O82, FIND(",", O82)+2, FIND(",", O82, FIND(",", O82)+1)-FIND(",", O82)-2)), "") | R82: =IFERROR(RIGHT(O82, LEN(O82)-FIND(",", O82, FIND(",", O82)+1)-1), "") | S82: {=_xlfn.TEXTJOIN(", ",TRUE,_xlfn._xlws.FILTER(Tabla29[[#All],[PARTE]],ISNUMBER(SEARCH(Tabla29[[#All],[PCLAVE3]],Tabla8[[#This Row],[DESCRIPCION DE TRABAJO]])),""))} | T82: =IF(AND(Tabla8[[#This Row],[PIEZA]]="",Tabla8[[#This Row],[PARTE]]=""),"VACIO","OK") -> VACIO | U82: =+CONCATENATE(WEEKNUM(Tabla8[[#This Row],[FECHA]]),"-",YEAR(Tabla8[[#This Row],[FECHA]])) -> 2-2026
A83: 46029 | B83: CESAR QUIROZ | C83: TARDE | D83: 0.58125 | E83: 0.59444444 | F83: =+MOD(Tabla8[[#This Row],[HR. FIN]]-Tabla8[[#This Row],[HR. INICIO]],1) -> 0.013194444 | G83: MEZCLADORA DE DOBLE EJE SSHS40 | H83: =IFERROR(VLOOKUP(G83,DATOS!$M$2:$N$219,2,FALSE),"") -> Maquinaria | I83: Lubricación | J83: =+VLOOKUP($I83,Tabla7[#All],2,FALSE) -> PROGRAMADA | K83: =IF(VLOOKUP(I83,Tabla7[#All],3,FALSE)=0,"",VLOOKUP(I83,Tabla7[#All],3,FALSE)) | L83: Máquina sin presencia de grasa | M83: Se lubrico equipo por puntos de engrase | N83: {=IFERROR(IF(Tabla8[[#This Row],[P/NP]]="NO PROGRAMADA","",_xlfn.TEXTJOIN(", ",TRUE,_xlfn._xlws.FILTER(Tabla4[[#All],[PIEZA]],ISNUMBER(SEARCH(Tabla4[[#All],[PCLAVE]],Tabla8[[#This Row],[DESCRIPCION DE TRABAJO]])),""))),"")} | O83: {=_xlfn.TEXTJOIN(", ",TRUE,_xlfn._xlws.FILTER(Tabla28[[#All],[PARTE]],ISNUMBER(SEARCH(Tabla28[[#All],[PCLAVE2]],Tabla8[[#This Row],[DESCRIPCION DE TRABAJO]])),""))} | P83: =IFERROR(LEFT(O83, FIND(",", O83)-1), O83) | Q83: =IFERROR(IF(ISERROR(FIND(",", O83, FIND(",", O83)+1)), RIGHT(O83, LEN(O83)-FIND(",", O83)-1), MID(O83, FIND(",", O83)+2, FIND(",", O83, FIND(",", O83)+1)-FIND(",", O83)-2)), "") | R83: =IFERROR(RIGHT(O83, LEN(O83)-FIND(",", O83, FIND(",", O83)+1)-1), "") | S83: {=_xlfn.TEXTJOIN(", ",TRUE,_xlfn._xlws.FILTER(Tabla29[[#All],[PARTE]],ISNUMBER(SEARCH(Tabla29[[#All],[PCLAVE3]],Tabla8[[#This Row],[DESCRIPCION DE TRABAJO]])),""))} -> Presencia De Grasa | T83: =IF(AND(Tabla8[[#This Row],[PIEZA]]="",Tabla8[[#This Row],[PARTE]]=""),"VACIO","OK") -> VACIO | U83: =+CONCATENATE(WEEKNUM(Tabla8[[#This Row],[FECHA]]),"-",YEAR(Tabla8[[#This Row],[FECHA]])) -> 2-2026
A84: 46029 | B84: CESAR QUIROZ | C84: TARDE | D84: 0.52708333 | E84: 0.53819444 | F84: =+MOD(Tabla8[[#This Row],[HR. FIN]]-Tabla8[[#This Row],[HR. INICIO]],1) -> 0.011111111 | G84: CALDERO, CHRILLER Y COMPRESOR | H84: =IFERROR(VLOOKUP(G84,DATOS!$M$2:$N$219,2,FALSE),"") -> Equipos auxiliares | I84: Inspección | J84: =+VLOOKUP($I84,Tabla7[#All],2,FALSE) -> PROGRAMADA | K84: =IF(VLOOKUP(I84,Tabla7[#All],3,FALSE)=0,"",VLOOKUP(I84,Tabla7[#All],3,FALSE)) | L84: Revisión de funcionamiento y parámetros de trabajo | N84: {=IFERROR(IF(Tabla8[[#This Row],[P/NP]]="NO PROGRAMADA","",_xlfn.TEXTJOIN(", ",TRUE,_xlfn._xlws.FILTER(Tabla4[[#All],[PIEZA]],ISNUMBER(SEARCH(Tabla4[[#All],[PCLAVE]],Tabla8[[#This Row],[DESCRIPCION DE TRABAJO]])),""))),"")} | O84: {=_xlfn.TEXTJOIN(", ",TRUE,_xlfn._xlws.FILTER(Tabla28[[#All],[PARTE]],ISNUMBER(SEARCH(Tabla28[[#All],[PCLAVE2]],Tabla8[[#This Row],[DESCRIPCION DE TRABAJO]])),""))} | P84: =IFERROR(LEFT(O84, FIND(",", O84)-1), O84) | Q84: =IFERROR(IF(ISERROR(FIND(",", O84, FIND(",", O84)+1)), RIGHT(O84, LEN(O84)-FIND(",", O84)-1), MID(O84, FIND(",", O84)+2, FIND(",", O84, FIND(",", O84)+1)-FIND(",", O84)-2)), "") | R84: =IFERROR(RIGHT(O84, LEN(O84)-FIND(",", O84, FIND(",", O84)+1)-1), "") | S84: {=_xlfn.TEXTJOIN(", ",TRUE,_xlfn._xlws.FILTER(Tabla29[[#All],[PARTE]],ISNUMBER(SEARCH(Tabla29[[#All],[PCLAVE3]],Tabla8[[#This Row],[DESCRIPCION DE TRABAJO]])),""))} | T84: =IF(AND(Tabla8[[#This Row],[PIEZA]]="",Tabla8[[#This Row],[PARTE]]=""),"VACIO","OK") -> VACIO | U84: =+CONCATENATE(WEEKNUM(Tabla8[[#This Row],[FECHA]]),"-",YEAR(Tabla8[[#This Row],[FECHA]])) -> 2-2026
A85: 46029 | B85: OMAR NINA | C85: MAÑANA | D85: 0.42013889 | E85: 0.43055556 | F85: =+MOD(Tabla8[[#This Row],[HR. FIN]]-Tabla8[[#This Row],[HR. INICIO]],1) -> 0.010416667 | G85: EMP. SAPAL | H85: =IFERROR(VLOOKUP(G85,DATOS!$M$2:$N$219,2,FALSE),"") -> Maquinaria | I85: SET UP | J85: =+VLOOKUP($I85,Tabla7[#All],2,FALSE) -> PROGRAMADA | K85: =IF(VLOOKUP(I85,Tabla7[#All],3,FALSE)=0,"",VLOOKUP(I85,Tabla7[#All],3,FALSE)) | L85: Apoyo en calibración de puntos de goma | N85: {=IFERROR(IF(Tabla8[[#This Row],[P/NP]]="NO PROGRAMADA","",_xlfn.TEXTJOIN(", ",TRUE,_xlfn._xlws.FILTER(Tabla4[[#All],[PIEZA]],ISNUMBER(SEARCH(Tabla4[[#All],[PCLAVE]],Tabla8[[#This Row],[DESCRIPCION DE TRABAJO]])),""))),"")} -> Gomas | O85: {=_xlfn.TEXTJOIN(", ",TRUE,_xlfn._xlws.FILTER(Tabla28[[#All],[PARTE]],ISNUMBER(SEARCH(Tabla28[[#All],[PCLAVE2]],Tabla8[[#This Row],[DESCRIPCION DE TRABAJO]])),""))} | P85: =IFERROR(LEFT(O85, FIND(",", O85)-1), O85) | Q85: =IFERROR(IF(ISERROR(FIND(",", O85, FIND(",", O85)+1)), RIGHT(O85, LEN(O85)-FIND(",", O85)-1), MID(O85, FIND(",", O85)+2, FIND(",", O85, FIND(",", O85)+1)-FIND(",", O85)-2)), "") | R85: =IFERROR(RIGHT(O85, LEN(O85)-FIND(",", O85, FIND(",", O85)+1)-1), "") | S85: {=_xlfn.TEXTJOIN(", ",TRUE,_xlfn._xlws.FILTER(Tabla29[[#All],[PARTE]],ISNUMBER(SEARCH(Tabla29[[#All],[PCLAVE3]],Tabla8[[#This Row],[DESCRIPCION DE TRABAJO]])),""))} -> Calibracion | T85: =IF(AND(Tabla8[[#This Row],[PIEZA]]="",Tabla8[[#This Row],[PARTE]]=""),"VACIO","OK") -> OK | U85: =+CONCATENATE(WEEKNUM(Tabla8[[#This Row],[FECHA]]),"-",YEAR(Tabla8[[#This Row],[FECHA]])) -> 2-2026
A86: 46029 | B86: CARLOS PUMA | C86: NOCHE | D86: 0.10416667 | E86: 0.11458333 | F86: =+MOD(Tabla8[[#This Row],[HR. FIN]]-Tabla8[[#This Row],[HR. INICIO]],1) -> 0.010416667 | G86: TUNEL DE ENFRIAMIENTO WHESTONE | H86: =IFERROR(VLOOKUP(G86,DATOS!$M$2:$N$219,2,FALSE),"") -> Maquinaria | I86: Ajuste /Calibracion | J86: =+VLOOKUP($I86,Tabla7[#All],2,FALSE) -> NO PROGRAMADA | K86: =IF(VLOOKUP(I86,Tabla7[#All],3,FALSE)=0,"",VLOOKUP(I86,Tabla7[#All],3,FALSE)) -> MECÁNICA | L86: Reportan que moldes se atoran en el interior del tunel | M86: Se reviso que no exista obtruccions , se realizó una limpieza parcial de guías y se tenso guias | N86: {=IFERROR(IF(Tabla8[[#This Row],[P/NP]]="NO PROGRAMADA","",_xlfn.TEXTJOIN(", ",TRUE,_xlfn._xlws.FILTER(Tabla4[[#All],[PIEZA]],ISNUMBER(SEARCH(Tabla4[[#All],[PCLAVE]],Tabla8[[#This Row],[DESCRIPCION DE TRABAJO]])),""))),"")} | O86: {=_xlfn.TEXTJOIN(", ",TRUE,_xlfn._xlws.FILTER(Tabla28[[#All],[PARTE]],ISNUMBER(SEARCH(Tabla28[[#All],[PCLAVE2]],Tabla8[[#This Row],[DESCRIPCION DE TRABAJO]])),""))} -> Tunel De Enfriamiento | P86: =IFERROR(LEFT(O86, FIND(",", O86)-1), O86) -> Tunel De Enfriamiento | Q86: =IFERROR(IF(ISERROR(FIND(",", O86, FIND(",", O86)+1)), RIGHT(O86, LEN(O86)-FIND(",", O86)-1), MID(O86, FIND(",", O86)+2, FIND(",", O86, FIND(",", O86)+1)-FIND(",", O86)-2)), "") | R86: =IFERROR(RIGHT(O86, LEN(O86)-FIND(",", O86, FIND(",", O86)+1)-1), "") | S86: {=_xlfn.TEXTJOIN(", ",TRUE,_xlfn._xlws.FILTER(Tabla29[[#All],[PARTE]],ISNUMBER(SEARCH(Tabla29[[#All],[PCLAVE3]],Tabla8[[#This Row],[DESCRIPCION DE TRABAJO]])),""))} | T86: =IF(AND(Tabla8[[#This Row],[PIEZA]]="",Tabla8[[#This Row],[PARTE]]=""),"VACIO","OK") -> OK | U86: =+CONCATENATE(WEEKNUM(Tabla8[[#This Row],[FECHA]]),"-",YEAR(Tabla8[[#This Row],[FECHA]])) -> 2-2026
A87: 46029 | B87: CARLOS PUMA | C87: NOCHE | D87: 0.061111111 | E87: 0.070833333 | F87: =+MOD(Tabla8[[#This Row],[HR. FIN]]-Tabla8[[#This Row],[HR. INICIO]],1) -> 0.0097222222 | G87: EMP. SAPAL | H87: =IFERROR(VLOOKUP(G87,DATOS!$M$2:$N$219,2,FALSE),"") -> Maquinaria | I87: Ajuste /Calibracion | J87: =+VLOOKUP($I87,Tabla7[#All],2,FALSE) -> NO PROGRAMADA | K87: =IF(VLOOKUP(I87,Tabla7[#All],3,FALSE)=0,"",VLOOKUP(I87,Tabla7[#All],3,FALSE)) -> MECÁNICA | L87: Pieza de empujador suelta fuera de pocision | M87: Se reconecto pieza a su respectiva base y se regulo embrague , se hizo pruebas en vacio | N87: {=IFERROR(IF(Tabla8[[#This Row],[P/NP]]="NO PROGRAMADA","",_xlfn.TEXTJOIN(", ",TRUE,_xlfn._xlws.FILTER(Tabla4[[#All],[PIEZA]],ISNUMBER(SEARCH(Tabla4[[#All],[PCLAVE]],Tabla8[[#This Row],[DESCRIPCION DE TRABAJO]])),""))),"")} | O87: {=_xlfn.TEXTJOIN(", ",TRUE,_xlfn._xlws.FILTER(Tabla28[[#All],[PARTE]],ISNUMBER(SEARCH(Tabla28[[#All],[PCLAVE2]],Tabla8[[#This Row],[DESCRIPCION DE TRABAJO]])),""))} | P87: =IFERROR(LEFT(O87, FIND(",", O87)-1), O87) | Q87: =IFERROR(IF(ISERROR(FIND(",", O87, FIND(",", O87)+1)), RIGHT(O87, LEN(O87)-FIND(",", O87)-1), MID(O87, FIND(",", O87)+2, FIND(",", O87, FIND(",", O87)+1)-FIND(",", O87)-2)), "") | R87: =IFERROR(RIGHT(O87, LEN(O87)-FIND(",", O87, FIND(",", O87)+1)-1), "") | S87: {=_xlfn.TEXTJOIN(", ",TRUE,_xlfn._xlws.FILTER(Tabla29[[#All],[PARTE]],ISNUMBER(SEARCH(Tabla29[[#All],[PCLAVE3]],Tabla8[[#This Row],[DESCRIPCION DE TRABAJO]])),""))} -> Fuera De Posicion, Soltura | T87: =IF(AND(Tabla8[[#This Row],[PIEZA]]="",Tabla8[[#This Row],[PARTE]]=""),"VACIO","OK") -> VACIO | U87: =+CONCATENATE(WEEKNUM(Tabla8[[#This Row],[FECHA]]),"-",YEAR(Tabla8[[#This Row],[FECHA]])) -> 2-2026
A88: 46029 | B88: CARLOS PUMA | C88: NOCHE | D88: 0.05 | E88: 0.056944444 | F88: =+MOD(Tabla8[[#This Row],[HR. FIN]]-Tabla8[[#This Row],[HR. INICIO]],1) -> 0.0069444444 | G88: CONCHA CLOVER 01 | H88: =IFERROR(VLOOKUP(G88,DATOS!$M$2:$N$219,2,FALSE),"") -> Maquinaria | I88: SET UP | J88: =+VLOOKUP($I88,Tabla7[#All],2,FALSE) -> PROGRAMADA | K88: =IF(VLOOKUP(I88,Tabla7[#All],3,FALSE)=0,"",VLOOKUP(I88,Tabla7[#All],3,FALSE)) | L88: Reconexión habilitación de motor de faja de ingreso a clovers | N88: {=IFERROR(IF(Tabla8[[#This Row],[P/NP]]="NO PROGRAMADA","",_xlfn.TEXTJOIN(", ",TRUE,_xlfn._xlws.FILTER(Tabla4[[#All],[PIEZA]],ISNUMBER(SEARCH(Tabla4[[#All],[PCLAVE]],Tabla8[[#This Row],[DESCRIPCION DE TRABAJO]])),""))),"")} -> Banda, Motor | O88: {=_xlfn.TEXTJOIN(", ",TRUE,_xlfn._xlws.FILTER(Tabla28[[#All],[PARTE]],ISNUMBER(SEARCH(Tabla28[[#All],[PCLAVE2]],Tabla8[[#This Row],[DESCRIPCION DE TRABAJO]])),""))} | P88: =IFERROR(LEFT(O88, FIND(",", O88)-1), O88) | Q88: =IFERROR(IF(ISERROR(FIND(",", O88, FIND(",", O88)+1)), RIGHT(O88, LEN(O88)-FIND(",", O88)-1), MID(O88, FIND(",", O88)+2, FIND(",", O88, FIND(",", O88)+1)-FIND(",", O88)-2)), "") | R88: =IFERROR(RIGHT(O88, LEN(O88)-FIND(",", O88, FIND(",", O88)+1)-1), "") | S88: {=_xlfn.TEXTJOIN(", ",TRUE,_xlfn._xlws.FILTER(Tabla29[[#All],[PARTE]],ISNUMBER(SEARCH(Tabla29[[#All],[PCLAVE3]],Tabla8[[#This Row],[DESCRIPCION DE TRABAJO]])),""))} | T88: =IF(AND(Tabla8[[#This Row],[PIEZA]]="",Tabla8[[#This Row],[PARTE]]=""),"VACIO","OK") -> OK | U88: =+CONCATENATE(WEEKNUM(Tabla8[[#This Row],[FECHA]]),"-",YEAR(Tabla8[[#This Row],[FECHA]])) -> 2-2026
A89: 46029 | B89: CARLOS PUMA | C89: NOCHE | D89: 0.076388889 | E89: 0.083333333 | F89: =+MOD(Tabla8[[#This Row],[HR. FIN]]-Tabla8[[#This Row],[HR. INICIO]],1) -> 0.0069444444 | G89: LINEA DE COCCION HANSEL | H89: =IFERROR(VLOOKUP(G89,DATOS!$M$2:$N$219,2,FALSE),"") -> Maquinaria | I89: Ajuste /Calibracion | J89: PROGRAMADA | L89: Apoyo en máquina | M89: Se ajusto uniones sms de tuberías de descarga | N89: {=IFERROR(IF(Tabla8[[#This Row],[P/NP]]="NO PROGRAMADA","",_xlfn.TEXTJOIN(", ",TRUE,_xlfn._xlws.FILTER(Tabla4[[#All],[PIEZA]],ISNUMBER(SEARCH(Tabla4[[#All],[PCLAVE]],Tabla8[[#This Row],[DESCRIPCION DE TRABAJO]])),""))),"")} | O89: {=_xlfn.TEXTJOIN(", ",TRUE,_xlfn._xlws.FILTER(Tabla28[[#All],[PARTE]],ISNUMBER(SEARCH(Tabla28[[#All],[PCLAVE2]],Tabla8[[#This Row],[DESCRIPCION DE TRABAJO]])),""))} | P89: =IFERROR(LEFT(O89, FIND(",", O89)-1), O89) | Q89: =IFERROR(IF(ISERROR(FIND(",", O89, FIND(",", O89)+1)), RIGHT(O89, LEN(O89)-FIND(",", O89)-1), MID(O89, FIND(",", O89)+2, FIND(",", O89, FIND(",", O89)+1)-FIND(",", O89)-2)), "") | R89: =IFERROR(RIGHT(O89, LEN(O89)-FIND(",", O89, FIND(",", O89)+1)-1), "") | S89: {=_xlfn.TEXTJOIN(", ",TRUE,_xlfn._xlws.FILTER(Tabla29[[#All],[PARTE]],ISNUMBER(SEARCH(Tabla29[[#All],[PCLAVE3]],Tabla8[[#This Row],[DESCRIPCION DE TRABAJO]])),""))} | T89: =IF(AND(Tabla8[[#This Row],[PIEZA]]="",Tabla8[[#This Row],[PARTE]]=""),"VACIO","OK") -> VACIO | U89: =+CONCATENATE(WEEKNUM(Tabla8[[#This Row],[FECHA]]),"-",YEAR(Tabla8[[#This Row],[FECHA]])) -> 2-2026
A90: 46030 | B90: CARLOS PUMA | C90: NOCHE | D90: 01:00 | E90: 02:00 | F90: =+MOD(Tabla8[[#This Row],[HR. FIN]]-Tabla8[[#This Row],[HR. INICIO]],1) -> 0.041666667 | G90: PLANTA INDUSTRIAL | H90: =IFERROR(VLOOKUP(G90,DATOS!$M$2:$N$219,2,FALSE),"") -> Area | I90: Inspección | J90: =+VLOOKUP($I90,Tabla7[#All],2,FALSE) -> PROGRAMADA | K90: =IF(VLOOKUP(I90,Tabla7[#All],3,FALSE)=0,"",VLOOKUP(I90,Tabla7[#All],3,FALSE)) | L90: Inspección de equipos en uso durante el turno | N90: {=IFERROR(IF(Tabla8[[#This Row],[P/NP]]="NO PROGRAMADA","",_xlfn.TEXTJOIN(", ",TRUE,_xlfn._xlws.FILTER(Tabla4[[#All],[PIEZA]],ISNUMBER(SEARCH(Tabla4[[#All],[PCLAVE]],Tabla8[[#This Row],[DESCRIPCION DE TRABAJO]])),""))),"")} | O90: {=_xlfn.TEXTJOIN(", ",TRUE,_xlfn._xlws.FILTER(Tabla28[[#All],[PARTE]],ISNUMBER(SEARCH(Tabla28[[#All],[PCLAVE2]],Tabla8[[#This Row],[DESCRIPCION DE TRABAJO]])),""))} | P90: =IFERROR(LEFT(O90, FIND(",", O90)-1), O90) | Q90: =IFERROR(IF(ISERROR(FIND(",", O90, FIND(",", O90)+1)), RIGHT(O90, LEN(O90)-FIND(",", O90)-1), MID(O90, FIND(",", O90)+2, FIND(",", O90, FIND(",", O90)+1)-FIND(",", O90)-2)), "") | R90: =IFERROR(RIGHT(O90, LEN(O90)-FIND(",", O90, FIND(",", O90)+1)-1), "") | S90: {=_xlfn.TEXTJOIN(", ",TRUE,_xlfn._xlws.FILTER(Tabla29[[#All],[PARTE]],ISNUMBER(SEARCH(Tabla29[[#All],[PCLAVE3]],Tabla8[[#This Row],[DESCRIPCION DE TRABAJO]])),""))} | T90: =IF(AND(Tabla8[[#This Row],[PIEZA]]="",Tabla8[[#This Row],[PARTE]]=""),"VACIO","OK") -> VACIO | U90: =+CONCATENATE(WEEKNUM(Tabla8[[#This Row],[FECHA]]),"-",YEAR(Tabla8[[#This Row],[FECHA]])) -> 2-2026
A91: 46030 | B91: CESAR QUIROZ | C91: TARDE | D91: 13:08 | E91: 14:03 | F91: =+MOD(Tabla8[[#This Row],[HR. FIN]]-Tabla8[[#This Row],[HR. INICIO]],1) -> 0.038194444 | G91: 1ER PISO | H91: =IFERROR(VLOOKUP(G91,DATOS!$M$2:$N$219,2,FALSE),"") -> Area | I91: Inspección | J91: =+VLOOKUP($I91,Tabla7[#All],2,FALSE) -> PROGRAMADA | K91: =IF(VLOOKUP(I91,Tabla7[#All],3,FALSE)=0,"",VLOOKUP(I91,Tabla7[#All],3,FALSE)) | L91: Revisión de circuitos y tableros eléctricos | N91: {=IFERROR(IF(Tabla8[[#This Row],[P/NP]]="NO PROGRAMADA","",_xlfn.TEXTJOIN(", ",TRUE,_xlfn._xlws.FILTER(Tabla4[[#All],[PIEZA]],ISNUMBER(SEARCH(Tabla4[[#All],[PCLAVE]],Tabla8[[#This Row],[DESCRIPCION DE TRABAJO]])),""))),"")} | O91: {=_xlfn.TEXTJOIN(", ",TRUE,_xlfn._xlws.FILTER(Tabla28[[#All],[PARTE]],ISNUMBER(SEARCH(Tabla28[[#All],[PCLAVE2]],Tabla8[[#This Row],[DESCRIPCION DE TRABAJO]])),""))} | P91: =IFERROR(LEFT(O91, FIND(",", O91)-1), O91) | Q91: =IFERROR(IF(ISERROR(FIND(",", O91, FIND(",", O91)+1)), RIGHT(O91, LEN(O91)-FIND(",", O91)-1), MID(O91, FIND(",", O91)+2, FIND(",", O91, FIND(",", O91)+1)-FIND(",", O91)-2)), "") | R91: =IFERROR(RIGHT(O91, LEN(O91)-FIND(",", O91, FIND(",", O91)+1)-1), "") | S91: {=_xlfn.TEXTJOIN(", ",TRUE,_xlfn._xlws.FILTER(Tabla29[[#All],[PARTE]],ISNUMBER(SEARCH(Tabla29[[#All],[PCLAVE3]],Tabla8[[#This Row],[DESCRIPCION DE TRABAJO]])),""))} | T91: =IF(AND(Tabla8[[#This Row],[PIEZA]]="",Tabla8[[#This Row],[PARTE]]=""),"VACIO","OK") -> VACIO | U91: =+CONCATENATE(WEEKNUM(Tabla8[[#This Row],[FECHA]]),"-",YEAR(Tabla8[[#This Row],[FECHA]])) -> 2-2026
A92: 46030 | B92: JOSÉ HAÑARI | C92: TARDE | D92: 12:40 | E92: 13:30 | F92: =+MOD(Tabla8[[#This Row],[HR. FIN]]-Tabla8[[#This Row],[HR. INICIO]],1) -> 0.034722222 | G92: 1ER PISO | H92: =IFERROR(VLOOKUP(G92,DATOS!$M$2:$N$219,2,FALSE),"") -> Area | I92: Inspección | J92: =+VLOOKUP($I92,Tabla7[#All],2,FALSE) -> PROGRAMADA | K92: =IF(VLOOKUP(I92,Tabla7[#All],3,FALSE)=0,"",VLOOKUP(I92,Tabla7[#All],3,FALSE)) | L92: Se hace inspección de circuitos eléctricos del primer piso | N92: {=IFERROR(IF(Tabla8[[#This Row],[P/NP]]="NO PROGRAMADA","",_xlfn.TEXTJOIN(", ",TRUE,_xlfn._xlws.FILTER(Tabla4[[#All],[PIEZA]],ISNUMBER(SEARCH(Tabla4[[#All],[PCLAVE]],Tabla8[[#This Row],[DESCRIPCION DE TRABAJO]])),""))),"")} | O92: {=_xlfn.TEXTJOIN(", ",TRUE,_xlfn._xlws.FILTER(Tabla28[[#All],[PARTE]],ISNUMBER(SEARCH(Tabla28[[#All],[PCLAVE2]],Tabla8[[#This Row],[DESCRIPCION DE TRABAJO]])),""))} | P92: =IFERROR(LEFT(O92, FIND(",", O92)-1), O92) | Q92: =IFERROR(IF(ISERROR(FIND(",", O92, FIND(",", O92)+1)), RIGHT(O92, LEN(O92)-FIND(",", O92)-1), MID(O92, FIND(",", O92)+2, FIND(",", O92, FIND(",", O92)+1)-FIND(",", O92)-2)), "") | R92: =IFERROR(RIGHT(O92, LEN(O92)-FIND(",", O92, FIND(",", O92)+1)-1), "") | S92: {=_xlfn.TEXTJOIN(", ",TRUE,_xlfn._xlws.FILTER(Tabla29[[#All],[PARTE]],ISNUMBER(SEARCH(Tabla29[[#All],[PCLAVE3]],Tabla8[[#This Row],[DESCRIPCION DE TRABAJO]])),""))} | T92: =IF(AND(Tabla8[[#This Row],[PIEZA]]="",Tabla8[[#This Row],[PARTE]]=""),"VACIO","OK") -> VACIO | U92: =+CONCATENATE(WEEKNUM(Tabla8[[#This Row],[FECHA]]),"-",YEAR(Tabla8[[#This Row],[FECHA]])) -> 2-2026
A93: 46030 | B93: JOSÉ HAÑARI | C93: TARDE | D93: 16:00 | E93: 16:40 | F93: =+MOD(Tabla8[[#This Row],[HR. FIN]]-Tabla8[[#This Row],[HR. INICIO]],1) -> 0.027777778 | G93: BAÑADORA DE CHOCOLATE 2 | H93: =IFERROR(VLOOKUP(G93,DATOS!$M$2:$N$219,2,FALSE),"") -> Maquinaria | I93: Ajuste /Calibracion | J93: =+VLOOKUP($I93,Tabla7[#All],2,FALSE) -> NO PROGRAMADA | K93: =IF(VLOOKUP(I93,Tabla7[#All],3,FALSE)=0,"",VLOOKUP(I93,Tabla7[#All],3,FALSE)) -> MECÁNICA | L93: Se habilita la faja de tranporte de producto y se regula temperatura de cabina | N93: {=IFERROR(IF(Tabla8[[#This Row],[P/NP]]="NO PROGRAMADA","",_xlfn.TEXTJOIN(", ",TRUE,_xlfn._xlws.FILTER(Tabla4[[#All],[PIEZA]],ISNUMBER(SEARCH(Tabla4[[#All],[PCLAVE]],Tabla8[[#This Row],[DESCRIPCION DE TRABAJO]])),""))),"")} | O93: {=_xlfn.TEXTJOIN(", ",TRUE,_xlfn._xlws.FILTER(Tabla28[[#All],[PARTE]],ISNUMBER(SEARCH(Tabla28[[#All],[PCLAVE2]],Tabla8[[#This Row],[DESCRIPCION DE TRABAJO]])),""))} | P93: =IFERROR(LEFT(O93, FIND(",", O93)-1), O93) | Q93: =IFERROR(IF(ISERROR(FIND(",", O93, FIND(",", O93)+1)), RIGHT(O93, LEN(O93)-FIND(",", O93)-1), MID(O93, FIND(",", O93)+2, FIND(",", O93, FIND(",", O93)+1)-FIND(",", O93)-2)), "") | R93: =IFERROR(RIGHT(O93, LEN(O93)-FIND(",", O93, FIND(",", O93)+1)-1), "") | S93: {=_xlfn.TEXTJOIN(", ",TRUE,_xlfn._xlws.FILTER(Tabla29[[#All],[PARTE]],ISNUMBER(SEARCH(Tabla29[[#All],[PCLAVE3]],Tabla8[[#This Row],[DESCRIPCION DE TRABAJO]])),""))} | T93: =IF(AND(Tabla8[[#This Row],[PIEZA]]="",Tabla8[[#This Row],[PARTE]]=""),"VACIO","OK") -> VACIO | U93: =+CONCATENATE(WEEKNUM(Tabla8[[#This Row],[FECHA]]),"-",YEAR(Tabla8[[#This Row],[FECHA]])) -> 2-2026
A94: 46030 | B94: JOSÉ HAÑARI | C94: TARDE | D94: 19:00 | E94: 19:40 | F94: =+MOD(Tabla8[[#This Row],[HR. FIN]]-Tabla8[[#This Row],[HR. INICIO]],1) -> 0.027777778 | G94: LINEA AUTOMATICA HACOS 2 | H94: =IFERROR(VLOOKUP(G94,DATOS!$M$2:$N$219,2,FALSE),"") -> Maquinaria | I94: SET UP | J94: NO PROGRAMADA | K94: MECÁNICA | L94: Sobre torque de línea | M94: Se realiza punto cero a la linea u se verifica los moldes con apoyo de cesar | N94: {=IFERROR(IF(Tabla8[[#This Row],[P/NP]]="NO PROGRAMADA","",_xlfn.TEXTJOIN(", ",TRUE,_xlfn._xlws.FILTER(Tabla4[[#All],[PIEZA]],ISNUMBER(SEARCH(Tabla4[[#All],[PCLAVE]],Tabla8[[#This Row],[DESCRIPCION DE TRABAJO]])),""))),"")} | O94: {=_xlfn.TEXTJOIN(", ",TRUE,_xlfn._xlws.FILTER(Tabla28[[#All],[PARTE]],ISNUMBER(SEARCH(Tabla28[[#All],[PCLAVE2]],Tabla8[[#This Row],[DESCRIPCION DE TRABAJO]])),""))} | P94: =IFERROR(LEFT(O94, FIND(",", O94)-1), O94) | Q94: =IFERROR(IF(ISERROR(FIND(",", O94, FIND(",", O94)+1)), RIGHT(O94, LEN(O94)-FIND(",", O94)-1), MID(O94, FIND(",", O94)+2, FIND(",", O94, FIND(",", O94)+1)-FIND(",", O94)-2)), "") | R94: =IFERROR(RIGHT(O94, LEN(O94)-FIND(",", O94, FIND(",", O94)+1)-1), "") | S94: {=_xlfn.TEXTJOIN(", ",TRUE,_xlfn._xlws.FILTER(Tabla29[[#All],[PARTE]],ISNUMBER(SEARCH(Tabla29[[#All],[PCLAVE3]],Tabla8[[#This Row],[DESCRIPCION DE TRABAJO]])),""))} | T94: =IF(AND(Tabla8[[#This Row],[PIEZA]]="",Tabla8[[#This Row],[PARTE]]=""),"VACIO","OK") -> VACIO | U94: =+CONCATENATE(WEEKNUM(Tabla8[[#This Row],[FECHA]]),"-",YEAR(Tabla8[[#This Row],[FECHA]])) -> 2-2026
A95: 46030 | B95: CESAR QUIROZ | C95: TARDE | D95: 14:38 | E95: 15:15 | F95: =+MOD(Tabla8[[#This Row],[HR. FIN]]-Tabla8[[#This Row],[HR. INICIO]],1) -> 0.025694444 | G95: EMP. 2 - CARLE MONTANARY | H95: =IFERROR(VLOOKUP(G95,DATOS!$M$2:$N$219,2,FALSE),"") -> Maquinaria | I95: Limpieza | J95: NO PROGRAMADA | K95: MECÁNICA | L95: Problemas con el rodillo de arrastre, papel se arruga constantemente | M95: Se desarmo y se realizó limpieza y correcta instalación, se lubrico y se realizó pruebas | N95: {=IFERROR(IF(Tabla8[[#This Row],[P/NP]]="NO PROGRAMADA","",_xlfn.TEXTJOIN(", ",TRUE,_xlfn._xlws.FILTER(Tabla4[[#All],[PIEZA]],ISNUMBER(SEARCH(Tabla4[[#All],[PCLAVE]],Tabla8[[#This Row],[DESCRIPCION DE TRABAJO]])),""))),"")} | O95: {=_xlfn.TEXTJOIN(", ",TRUE,_xlfn._xlws.FILTER(Tabla28[[#All],[PARTE]],ISNUMBER(SEARCH(Tabla28[[#All],[PCLAVE2]],Tabla8[[#This Row],[DESCRIPCION DE TRABAJO]])),""))} | P95: =IFERROR(LEFT(O95, FIND(",", O95)-1), O95) | Q95: =IFERROR(IF(ISERROR(FIND(",", O95, FIND(",", O95)+1)), RIGHT(O95, LEN(O95)-FIND(",", O95)-1), MID(O95, FIND(",", O95)+2, FIND(",", O95, FIND(",", O95)+1)-FIND(",", O95)-2)), "") | R95: =IFERROR(RIGHT(O95, LEN(O95)-FIND(",", O95, FIND(",", O95)+1)-1), "") | S95: {=_xlfn.TEXTJOIN(", ",TRUE,_xlfn._xlws.FILTER(Tabla29[[#All],[PARTE]],ISNUMBER(SEARCH(Tabla29[[#All],[PCLAVE3]],Tabla8[[#This Row],[DESCRIPCION DE TRABAJO]])),""))} | T95: =IF(AND(Tabla8[[#This Row],[PIEZA]]="",Tabla8[[#This Row],[PARTE]]=""),"VACIO","OK") -> VACIO | U95: =+CONCATENATE(WEEKNUM(Tabla8[[#This Row],[FECHA]]),"-",YEAR(Tabla8[[#This Row],[FECHA]])) -> 2-2026
A96: 46030 | B96: JOSÉ HAÑARI | C96: TARDE | D96: 18:15 | E96: 18:50 | F96: =+MOD(Tabla8[[#This Row],[HR. FIN]]-Tabla8[[#This Row],[HR. INICIO]],1) -> 0.024305556 | G96: EMP. 2 - CARLE MONTANARY | H96: =IFERROR(VLOOKUP(G96,DATOS!$M$2:$N$219,2,FALSE),"") -> Maquinaria | I96: Limpieza | J96: NO PROGRAMADA | K96: MECÁNICA | L96: Rodillo de arrastre de la vpack arruga el papel aluminio | M96: Se realiza limpieza de eje y rodamientos y se verifica los gomas con cesar | N96: {=IFERROR(IF(Tabla8[[#This Row],[P/NP]]="NO PROGRAMADA","",_xlfn.TEXTJOIN(", ",TRUE,_xlfn._xlws.FILTER(Tabla4[[#All],[PIEZA]],ISNUMBER(SEARCH(Tabla4[[#All],[PCLAVE]],Tabla8[[#This Row],[DESCRIPCION DE TRABAJO]])),""))),"")} | O96: {=_xlfn.TEXTJOIN(", ",TRUE,_xlfn._xlws.FILTER(Tabla28[[#All],[PARTE]],ISNUMBER(SEARCH(Tabla28[[#All],[PCLAVE2]],Tabla8[[#This Row],[DESCRIPCION DE TRABAJO]])),""))} | P96: =IFERROR(LEFT(O96, FIND(",", O96)-1), O96) | Q96: =IFERROR(IF(ISERROR(FIND(",", O96, FIND(",", O96)+1)), RIGHT(O96, LEN(O96)-FIND(",", O96)-1), MID(O96, FIND(",", O96)+2, FIND(",", O96, FIND(",", O96)+1)-FIND(",", O96)-2)), "") | R96: =IFERROR(RIGHT(O96, LEN(O96)-FIND(",", O96, FIND(",", O96)+1)-1), "") | S96: {=_xlfn.TEXTJOIN(", ",TRUE,_xlfn._xlws.FILTER(Tabla29[[#All],[PARTE]],ISNUMBER(SEARCH(Tabla29[[#All],[PCLAVE3]],Tabla8[[#This Row],[DESCRIPCION DE TRABAJO]])),""))} | T96: =IF(AND(Tabla8[[#This Row],[PIEZA]]="",Tabla8[[#This Row],[PARTE]]=""),"VACIO","OK") -> VACIO | U96: =+CONCATENATE(WEEKNUM(Tabla8[[#This Row],[FECHA]]),"-",YEAR(Tabla8[[#This Row],[FECHA]])) -> 2-2026
A97: 46030 | B97: JOSÉ HAÑARI | C97: TARDE | D97: 14:00 | E97: 14:30 | F97: =+MOD(Tabla8[[#This Row],[HR. FIN]]-Tabla8[[#This Row],[HR. INICIO]],1) -> 0.020833333 | G97: HACOS 1 | H97: =IFERROR(VLOOKUP(G97,DATOS!$M$2:$N$219,2,FALSE),"") -> Maquinaria | I97: SET UP | J97: =+VLOOKUP($I97,Tabla7[#All],2,FALSE) -> PROGRAMADA | K97: =IF(VLOOKUP(I97,Tabla7[#All],3,FALSE)=0,"",VLOOKUP(I97,Tabla7[#All],3,FALSE)) | L97: Se desarma MDS para limpieza | N97: {=IFERROR(IF(Tabla8[[#This Row],[P/NP]]="NO PROGRAMADA","",_xlfn.TEXTJOIN(", ",TRUE,_xlfn._xlws.FILTER(Tabla4[[#All],[PIEZA]],ISNUMBER(SEARCH(Tabla4[[#All],[PCLAVE]],Tabla8[[#This Row],[DESCRIPCION DE TRABAJO]])),""))),"")} | O97: {=_xlfn.TEXTJOIN(", ",TRUE,_xlfn._xlws.FILTER(Tabla28[[#All],[PARTE]],ISNUMBER(SEARCH(Tabla28[[#All],[PCLAVE2]],Tabla8[[#This Row],[DESCRIPCION DE TRABAJO]])),""))} -> Mds | P97: =IFERROR(LEFT(O97, FIND(",", O97)-1), O97) -> Mds | Q97: =IFERROR(IF(ISERROR(FIND(",", O97, FIND(",", O97)+1)), RIGHT(O97, LEN(O97)-FIND(",", O97)-1), MID(O97, FIND(",", O97)+2, FIND(",", O97, FIND(",", O97)+1)-FIND(",", O97)-2)), "") | R97: =IFERROR(RIGHT(O97, LEN(O97)-FIND(",", O97, FIND(",", O97)+1)-1), "") | S97: {=_xlfn.TEXTJOIN(", ",TRUE,_xlfn._xlws.FILTER(Tabla29[[#All],[PARTE]],ISNUMBER(SEARCH(Tabla29[[#All],[PCLAVE3]],Tabla8[[#This Row],[DESCRIPCION DE TRABAJO]])),""))} | T97: =IF(AND(Tabla8[[#This Row],[PIEZA]]="",Tabla8[[#This Row],[PARTE]]=""),"VACIO","OK") -> OK | U97: =+CONCATENATE(WEEKNUM(Tabla8[[#This Row],[FECHA]]),"-",YEAR(Tabla8[[#This Row],[FECHA]])) -> 2-2026
A98: 46030 | B98: CESAR QUIROZ | C98: TARDE | D98: 15:29 | E98: 15:54 | F98: =+MOD(Tabla8[[#This Row],[HR. FIN]]-Tabla8[[#This Row],[HR. INICIO]],1) -> 0.017361111 | G98: CAMARA DE FRIO | H98: =IFERROR(VLOOKUP(G98,DATOS!$M$2:$N$219,2,FALSE),"") -> Maquinaria | I98: SET UP | J98: =+VLOOKUP($I98,Tabla7[#All],2,FALSE) -> PROGRAMADA | K98: =IF(VLOOKUP(I98,Tabla7[#All],3,FALSE)=0,"",VLOOKUP(I98,Tabla7[#All],3,FALSE)) | L98: Camara de frío sale agua de condensado, acumulación de hielo | M98: Se retiro bandeja y se realizó limpieza y descongelacion | N98: {=IFERROR(IF(Tabla8[[#This Row],[P/NP]]="NO PROGRAMADA","",_xlfn.TEXTJOIN(", ",TRUE,_xlfn._xlws.FILTER(Tabla4[[#All],[PIEZA]],ISNUMBER(SEARCH(Tabla4[[#All],[PCLAVE]],Tabla8[[#This Row],[DESCRIPCION DE TRABAJO]])),""))),"")} | O98: {=_xlfn.TEXTJOIN(", ",TRUE,_xlfn._xlws.FILTER(Tabla28[[#All],[PARTE]],ISNUMBER(SEARCH(Tabla28[[#All],[PCLAVE2]],Tabla8[[#This Row],[DESCRIPCION DE TRABAJO]])),""))} -> Camara De Temperado | P98: =IFERROR(LEFT(O98, FIND(",", O98)-1), O98) -> Camara De Temperado | Q98: =IFERROR(IF(ISERROR(FIND(",", O98, FIND(",", O98)+1)), RIGHT(O98, LEN(O98)-FIND(",", O98)-1), MID(O98, FIND(",", O98)+2, FIND(",", O98, FIND(",", O98)+1)-FIND(",", O98)-2)), "") | R98: =IFERROR(RIGHT(O98, LEN(O98)-FIND(",", O98, FIND(",", O98)+1)-1), "") | S98: {=_xlfn.TEXTJOIN(", ",TRUE,_xlfn._xlws.FILTER(Tabla29[[#All],[PARTE]],ISNUMBER(SEARCH(Tabla29[[#All],[PCLAVE3]],Tabla8[[#This Row],[DESCRIPCION DE TRABAJO]])),""))} -> Acumulacion De Producto | T98: =IF(AND(Tabla8[[#This Row],[PIEZA]]="",Tabla8[[#This Row],[PARTE]]=""),"VACIO","OK") -> OK | U98: =+CONCATENATE(WEEKNUM(Tabla8[[#This Row],[FECHA]]),"-",YEAR(Tabla8[[#This Row],[FECHA]])) -> 2-2026
A99: 46030 | B99: CESAR QUIROZ | C99: TARDE | D99: 15:54 | E99: 16:18 | F99: =+MOD(Tabla8[[#This Row],[HR. FIN]]-Tabla8[[#This Row],[HR. INICIO]],1) -> 0.016666667 | G99: LINEA AUTOMATICA HACOS 2 | H99: =IFERROR(VLOOKUP(G99,DATOS!$M$2:$N$219,2,FALSE),"") -> Maquinaria | I99: Ajuste /Calibracion | J99: =+VLOOKUP($I99,Tabla7[#All],2,FALSE) -> NO PROGRAMADA | K99: =IF(VLOOKUP(I99,Tabla7[#All],3,FALSE)=0,"",VLOOKUP(I99,Tabla7[#All],3,FALSE)) -> MECÁNICA | L99: Moldes de juntan en salida de torre | M99: Se regulo presión de rascadores, se realizó pruebas | N99: {=IFERROR(IF(Tabla8[[#This Row],[P/NP]]="NO PROGRAMADA","",_xlfn.TEXTJOIN(", ",TRUE,_xlfn._xlws.FILTER(Tabla4[[#All],[PIEZA]],ISNUMBER(SEARCH(Tabla4[[#All],[PCLAVE]],Tabla8[[#This Row],[DESCRIPCION DE TRABAJO]])),""))),"")} | O99: {=_xlfn.TEXTJOIN(", ",TRUE,_xlfn._xlws.FILTER(Tabla28[[#All],[PARTE]],ISNUMBER(SEARCH(Tabla28[[#All],[PCLAVE2]],Tabla8[[#This Row],[DESCRIPCION DE TRABAJO]])),""))} -> Columna | P99: =IFERROR(LEFT(O99, FIND(",", O99)-1), O99) -> Columna | Q99: =IFERROR(IF(ISERROR(FIND(",", O99, FIND(",", O99)+1)), RIGHT(O99, LEN(O99)-FIND(",", O99)-1), MID(O99, FIND(",", O99)+2, FIND(",", O99, FIND(",", O99)+1)-FIND(",", O99)-2)), "") | R99: =IFERROR(RIGHT(O99, LEN(O99)-FIND(",", O99, FIND(",", O99)+1)-1), "") | S99: {=_xlfn.TEXTJOIN(", ",TRUE,_xlfn._xlws.FILTER(Tabla29[[#All],[PARTE]],ISNUMBER(SEARCH(Tabla29[[#All],[PCLAVE3]],Tabla8[[#This Row],[DESCRIPCION DE TRABAJO]])),""))} -> Juntos | T99: =IF(AND(Tabla8[[#This Row],[PIEZA]]="",Tabla8[[#This Row],[PARTE]]=""),"VACIO","OK") -> OK | U99: =+CONCATENATE(WEEKNUM(Tabla8[[#This Row],[FECHA]]),"-",YEAR(Tabla8[[#This Row],[FECHA]])) -> 2-2026
A100: 46030 | B100: CARLOS PUMA | C100: NOCHE | D100: 02:30 | E100: 02:50 | F100: =+MOD(Tabla8[[#This Row],[HR. FIN]]-Tabla8[[#This Row],[HR. INICIO]],1) -> 0.013888889 | G100: CALDERO 100 BHP | H100: =IFERROR(VLOOKUP(G100,DATOS!$M$2:$N$219,2,FALSE),"") -> Equipos auxiliares | I100: SET UP | J100: NO PROGRAMADA | K100: ELÉCTRICA | L100: Alarma falla de llama | M100: Se confirmo alarma se reseteo programa , se hizo las purgas de nivel y fondo y se dió seguimiento | N100: {=IFERROR(IF(Tabla8[[#This Row],[P/NP]]="NO PROGRAMADA","",_xlfn.TEXTJOIN(", ",TRUE,_xlfn._xlws.FILTER(Tabla4[[#All],[PIEZA]],ISNUMBER(SEARCH(Tabla4[[#All],[PCLAVE]],Tabla8[[#This Row],[DESCRIPCION DE TRABAJO]])),""))),"")} | O100: {=_xlfn.TEXTJOIN(", ",TRUE,_xlfn._xlws.FILTER(Tabla28[[#All],[PARTE]],ISNUMBER(SEARCH(Tabla28[[#All],[PCLAVE2]],Tabla8[[#This Row],[DESCRIPCION DE TRABAJO]])),""))} | P100: =IFERROR(LEFT(O100, FIND(",", O100)-1), O100) | Q100: =IFERROR(IF(ISERROR(FIND(",", O100, FIND(",", O100)+1)), RIGHT(O100, LEN(O100)-FIND(",", O100)-1), MID(O100, FIND(",", O100)+2, FIND(",", O100, FIND(",", O100)+1)-FIND(",", O100)-2)), "") | R100: =IFERROR(RIGHT(O100, LEN(O100)-FIND(",", O100, FIND(",", O100)+1)-1), "") | S100: {=_xlfn.TEXTJOIN(", ",TRUE,_xlfn._xlws.FILTER(Tabla29[[#All],[PARTE]],ISNUMBER(SEARCH(Tabla29[[#All],[PCLAVE3]],Tabla8[[#This Row],[DESCRIPCION DE TRABAJO]])),""))} -> Alarma | T100: =IF(AND(Tabla8[[#This Row],[PIEZA]]="",Tabla8[[#This Row],[PARTE]]=""),"VACIO","OK") -> VACIO | U100: =+CONCATENATE(WEEKNUM(Tabla8[[#This Row],[FECHA]]),"-",YEAR(Tabla8[[#This Row],[FECHA]])) -> 2-2026
A101: 46030 | B101: JOSÉ HAÑARI | C101: TARDE | D101: 17:50 | E101: 18:10 | F101: =+MOD(Tabla8[[#This Row],[HR. FIN]]-Tabla8[[#This Row],[HR. INICIO]],1) -> 0.013888889 | G101: GARITA | H101: =IFERROR(VLOOKUP(G101,DATOS!$M$2:$N$219,2,FALSE),"") -> Area | I101: Inspección | J101: =+VLOOKUP($I101,Tabla7[#All],2,FALSE) -> PROGRAMADA | K101: =IF(VLOOKUP(I101,Tabla7[#All],3,FALSE)=0,"",VLOOKUP(I101,Tabla7[#All],3,FALSE)) | L101: Se hace inspección de luminaria de garita y se saca medidas | N101: {=IFERROR(IF(Tabla8[[#This Row],[P/NP]]="NO PROGRAMADA","",_xlfn.TEXTJOIN(", ",TRUE,_xlfn._xlws.FILTER(Tabla4[[#All],[PIEZA]],ISNUMBER(SEARCH(Tabla4[[#All],[PCLAVE]],Tabla8[[#This Row],[DESCRIPCION DE TRABAJO]])),""))),"")} | O101: {=_xlfn.TEXTJOIN(", ",TRUE,_xlfn._xlws.FILTER(Tabla28[[#All],[PARTE]],ISNUMBER(SEARCH(Tabla28[[#All],[PCLAVE2]],Tabla8[[#This Row],[DESCRIPCION DE TRABAJO]])),""))} | P101: =IFERROR(LEFT(O101, FIND(",", O101)-1), O101) | Q101: =IFERROR(IF(ISERROR(FIND(",", O101, FIND(",", O101)+1)), RIGHT(O101, LEN(O101)-FIND(",", O101)-1), MID(O101, FIND(",", O101)+2, FIND(",", O101, FIND(",", O101)+1)-FIND(",", O101)-2)), "") | R101: =IFERROR(RIGHT(O101, LEN(O101)-FIND(",", O101, FIND(",", O101)+1)-1), "") | S101: {=_xlfn.TEXTJOIN(", ",TRUE,_xlfn._xlws.FILTER(Tabla29[[#All],[PARTE]],ISNUMBER(SEARCH(Tabla29[[#All],[PCLAVE3]],Tabla8[[#This Row],[DESCRIPCION DE TRABAJO]])),""))} | T101: =IF(AND(Tabla8[[#This Row],[PIEZA]]="",Tabla8[[#This Row],[PARTE]]=""),"VACIO","OK") -> VACIO | U101: =+CONCATENATE(WEEKNUM(Tabla8[[#This Row],[FECHA]]),"-",YEAR(Tabla8[[#This Row],[FECHA]])) -> 2-2026
A102: 46030 | B102: CESAR QUIROZ | C102: TARDE | D102: 12:39 | E102: 12:58 | F102: =+MOD(Tabla8[[#This Row],[HR. FIN]]-Tabla8[[#This Row],[HR. INICIO]],1) -> 0.013194444 | G102: CALDERO, CHRILLER Y COMPRESOR | H102: =IFERROR(VLOOKUP(G102,DATOS!$M$2:$N$219,2,FALSE),"") -> Equipos auxiliares | I102: Inspección | J102: =+VLOOKUP($I102,Tabla7[#All],2,FALSE) -> PROGRAMADA | K102: =IF(VLOOKUP(I102,Tabla7[#All],3,FALSE)=0,"",VLOOKUP(I102,Tabla7[#All],3,FALSE)) | L102: Revisión de funcionamiento y parámetros dé trabajo | N102: {=IFERROR(IF(Tabla8[[#This Row],[P/NP]]="NO PROGRAMADA","",_xlfn.TEXTJOIN(", ",TRUE,_xlfn._xlws.FILTER(Tabla4[[#All],[PIEZA]],ISNUMBER(SEARCH(Tabla4[[#All],[PCLAVE]],Tabla8[[#This Row],[DESCRIPCION DE TRABAJO]])),""))),"")} | O102: {=_xlfn.TEXTJOIN(", ",TRUE,_xlfn._xlws.FILTER(Tabla28[[#All],[PARTE]],ISNUMBER(SEARCH(Tabla28[[#All],[PCLAVE2]],Tabla8[[#This Row],[DESCRIPCION DE TRABAJO]])),""))} | P102: =IFERROR(LEFT(O102, FIND(",", O102)-1), O102) | Q102: =IFERROR(IF(ISERROR(FIND(",", O102, FIND(",", O102)+1)), RIGHT(O102, LEN(O102)-FIND(",", O102)-1), MID(O102, FIND(",", O102)+2, FIND(",", O102, FIND(",", O102)+1)-FIND(",", O102)-2)), "") | R102: =IFERROR(RIGHT(O102, LEN(O102)-FIND(",", O102, FIND(",", O102)+1)-1), "") | S102: {=_xlfn.TEXTJOIN(", ",TRUE,_xlfn._xlws.FILTER(Tabla29[[#All],[PARTE]],ISNUMBER(SEARCH(Tabla29[[#All],[PCLAVE3]],Tabla8[[#This Row],[DESCRIPCION DE TRABAJO]])),""))} | T102: =IF(AND(Tabla8[[#This Row],[PIEZA]]="",Tabla8[[#This Row],[PARTE]]=""),"VACIO","OK") -> VACIO | U102: =+CONCATENATE(WEEKNUM(Tabla8[[#This Row],[FECHA]]),"-",YEAR(Tabla8[[#This Row],[FECHA]])) -> 2-2026
...

Sheet TABLA-DIA
H1: =+SUM(Tabla107[T.TOTAL]) -> 0.78194444
B2: CONTEO-NOMBRE | C2: FECHA | D2: TECNICO | E2: TURNO | F2: INICIO | G2: FIN | H2: T.TOTAL | I2: MAQUINA / EQUIPO | J2: CLASIFICACION | K2: TIPO | L2: P/NP | M2: M/E | N2: OBSERVACION | O2: ACT. CORRECTIVA | P2: CONTEO | Q2: Maq.
B3: =IF(I3="","",CONCATENATE(I3,"-",P3)) -> EMP. NAPOLITANA-1 | C3: 46205 | D3: JOSÉ HAÑARI | E3: TARDE | F3: 0.54861111 | G3: 0.5625 | H3: 0.013888889 | I3: EMP. NAPOLITANA | J3: Maquinaria | K3: SET UP | L3: PROGRAMADA | N3: Se arma napolitana para uso | P3: =COUNTIF($I$3:I3,I3) -> 1 | Q3: =IF(Tabla107[[#This Row],[MAQUINA / EQUIPO]]="","",Tabla107[[#This Row],[MAQUINA / EQUIPO]]) -> EMP. NAPOLITANA | BK3: MAQUINARIA
B4: =IF(I4="","",CONCATENATE(I4,"-",P4)) -> 3ER PISO-1 | C4: 46205 | D4: JOSÉ HAÑARI | E4: TARDE | F4: 0.56944444 | G4: 0.59027778 | H4: 0.020833333 | I4: 3ER PISO | J4: Area | K4: Reparacion | L4: NO PROGRAMADA | M4: MECÁNICA | N4: Jujecion de cortadora lineal no sujeta | O4: Se fabrica accesorio y se deja en el tercer piso | P4: =COUNTIF($I$3:I4,I4) -> 1 | Q4: =IF(Tabla107[[#This Row],[MAQUINA / EQUIPO]]="","",Tabla107[[#This Row],[MAQUINA / EQUIPO]]) -> 3ER PISO | BK4: BAÑADORA 1
B5: =IF(I5="","",CONCATENATE(I5,"-",P5)) -> EMP. SAPAL-1 | C5: 46205 | D5: JOSÉ HAÑARI | E5: TARDE | F5: 0.59722222 | G5: 0.625 | H5: 0.027777778 | I5: EMP. SAPAL | J5: Maquinaria | K5: Reparacion | L5: NO PROGRAMADA | M5: MECÁNICA | N5: Espuma de contra elevador dañado | O5: Se realiza el pegado de espuma y limpieza de bujes | P5: =COUNTIF($I$3:I5,I5) -> 1 | Q5: =IF(Tabla107[[#This Row],[MAQUINA / EQUIPO]]="","",Tabla107[[#This Row],[MAQUINA / EQUIPO]]) -> EMP. SAPAL | BK5: BAÑADORA 2
B6: =IF(I6="","",CONCATENATE(I6,"-",P6)) -> ENCELOFANADORA ECCOPAC-1 | C6: 46205 | D6: JOSÉ HAÑARI | E6: TARDE | F6: 0.63194444 | G6: 0.65625 | H6: 0.024305556 | I6: ENCELOFANADORA ECCOPAC | J6: Maquinaria | K6: Ajuste /Calibracion | L6: NO PROGRAMADA | M6: MECÁNICA | N6: Se pega cajas | O6: Se realiza la calibración correspondiente | P6: =COUNTIF($I$3:I6,I6) -> 1 | Q6: =IF(Tabla107[[#This Row],[MAQUINA / EQUIPO]]="","",Tabla107[[#This Row],[MAQUINA / EQUIPO]]) -> ENCELOFANADORA ECCOPAC | BK6: BARQUILLERA
B7: =IF(I7="","",CONCATENATE(I7,"-",P7)) -> EMP. SAPAL-2 | C7: 46205 | D7: JOSÉ HAÑARI | E7: TARDE | F7: 0.65972222 | G7: 0.75 | H7: 0.090277778 | I7: EMP. SAPAL | J7: Maquinaria | K7: Ajuste /Calibracion | L7: NO PROGRAMADA | M7: MECÁNICA | N7: No pega goma en etiqueta | O7: Se realiza la calibración y limpieza de boquilla en dosicacion de goma en equipo | P7: =COUNTIF($I$3:I7,I7) -> 2 | Q7: =IF(Tabla107[[#This Row],[MAQUINA / EQUIPO]]="","",Tabla107[[#This Row],[MAQUINA / EQUIPO]]) -> EMP. SAPAL | BK7: BATIDORA DE FONDANT
B8: =IF(I8="","",CONCATENATE(I8,"-",P8)) -> MOLINO REBOTE - IMPACTO-1 | C8: 46205 | D8: JOSÉ HAÑARI | E8: TARDE | F8: 0.75694444 | G8: 0.77430556 | H8: 0.017361111 | I8: MOLINO REBOTE - IMPACTO | J8: Maquinaria | K8: Limpieza | L8: NO PROGRAMADA | M8: ELÉCTRICA | N8: No enciende | O8: Se realiza ala limpieza correspondiente del sensor | P8: =COUNTIF($I$3:I8,I8) -> 1 | Q8: =IF(Tabla107[[#This Row],[MAQUINA / EQUIPO]]="","",Tabla107[[#This Row],[MAQUINA / EQUIPO]]) -> MOLINO REBOTE - IMPACTO | BK8: CAMARA DE FRIO
B9: =IF(I9="","",CONCATENATE(I9,"-",P9)) -> FORRADORA MINIFLEX-1 | C9: 46205 | D9: JOSÉ HAÑARI | E9: TARDE | F9: 0.82291667 | G9: 0.85416667 | H9: 0.03125 | I9: FORRADORA MINIFLEX | J9: Maquinaria | K9: Ajuste /Calibracion | L9: NO PROGRAMADA | M9: MECÁNICA | N9: No desbobina laminado y cuchilla no corta | O9: Se realiza la calibración correspondiente | P9: =COUNTIF($I$3:I9,I9) -> 1 | Q9: =IF(Tabla107[[#This Row],[MAQUINA / EQUIPO]]="","",Tabla107[[#This Row],[MAQUINA / EQUIPO]]) -> FORRADORA MINIFLEX | BK9: CLOVER
B10: =IF(I10="","",CONCATENATE(I10,"-",P10)) -> LINEA AUTOMATICA HACOS 1-1 | C10: 46205 | D10: OMAR NINA | E10: NOCHE | F10: 00:10 | G10: 00:35 | H10: 0.017361111 | I10: LINEA AUTOMATICA HACOS 1 | J10: Maquinaria | K10: SET UP | L10: PROGRAMADA | N10: Desarmado de MDS, formato dubai | P10: =COUNTIF($I$3:I10,I10) -> 1 | Q10: =IF(Tabla107[[#This Row],[MAQUINA / EQUIPO]]="","",Tabla107[[#This Row],[MAQUINA / EQUIPO]]) -> LINEA AUTOMATICA HACOS 1 | BK10: COCINA DE TOFFEE
B11: =IF(I11="","",CONCATENATE(I11,"-",P11)) -> EMP. SAPAL-3 | C11: 46205 | D11: OMAR NINA | E11: NOCHE | F11: 00:40 | G11: 01:00 | H11: 0.013888889 | I11: EMP. SAPAL | J11: Maquinaria | K11: Inspección | L11: PROGRAMADA | N11: Inspección de equipo | O11: Apoyo en calibración de puntos de goma | P11: =COUNTIF($I$3:I11,I11) -> 3 | Q11: =IF(Tabla107[[#This Row],[MAQUINA / EQUIPO]]="","",Tabla107[[#This Row],[MAQUINA / EQUIPO]]) -> EMP. SAPAL | BK11: COD. MACSA
B12: =IF(I12="","",CONCATENATE(I12,"-",P12)) -> LINEA AUTOMATICA HACOS 1-2 | C12: 46205 | D12: OMAR NINA | E12: NOCHE | F12: 01:10 | G12: 01:45 | H12: 0.024305556 | I12: LINEA AUTOMATICA HACOS 1 | J12: Maquinaria | K12: SET UP | L12: PROGRAMADA | N12: Armado de mds para formato agregados x100 | P12: =COUNTIF($I$3:I12,I12) -> 2 | Q12: =IF(Tabla107[[#This Row],[MAQUINA / EQUIPO]]="","",Tabla107[[#This Row],[MAQUINA / EQUIPO]]) -> LINEA AUTOMATICA HACOS 1 | BK12: CODIF. 4TO PISO
B13: =IF(I13="","",CONCATENATE(I13,"-",P13)) -> TOSTADOR PETRONCINI NUEVO-1 | C13: 46205 | D13: OMAR NINA | E13: NOCHE | F13: 02:05 | G13: 02:26 | H13: 0.014583333 | I13: TOSTADOR PETRONCINI NUEVO | J13: Maquinaria | K13: Inspección | L13: PROGRAMADA | N13: Inspección funcionamiento de equipo | P13: =COUNTIF($I$3:I13,I13) -> 1 | Q13: =IF(Tabla107[[#This Row],[MAQUINA / EQUIPO]]="","",Tabla107[[#This Row],[MAQUINA / EQUIPO]]) -> TOSTADOR PETRONCINI NUEVO | BK13: CODIF. 5TO PISO
B14: =IF(I14="","",CONCATENATE(I14,"-",P14)) -> LINEA AUTOMATICA HACOS 1-3 | C14: 46205 | D14: OMAR NINA | E14: NOCHE | F14: 03:40 | G14: 04:10 | H14: 0.020833333 | I14: LINEA AUTOMATICA HACOS 1 | J14: Maquinaria | K14: Inspección | L14: PROGRAMADA | N14: Inspección de equipo | P14: =COUNTIF($I$3:I14,I14) -> 3 | Q14: =IF(Tabla107[[#This Row],[MAQUINA / EQUIPO]]="","",Tabla107[[#This Row],[MAQUINA / EQUIPO]]) -> LINEA AUTOMATICA HACOS 1 | BK14: CONCHA ASPAS
B15: =IF(I15="","",CONCATENATE(I15,"-",P15)) -> TOSTADOR PETRONCINI NUEVO-2 | C15: 46205 | D15: CARLOS TAPIA | E15: MAÑANA | F15: 06:00 | G15: 06:15 | H15: 0.010416667 | I15: TOSTADOR PETRONCINI NUEVO | J15: Maquinaria | K15: Limpieza | L15: PROGRAMADA | N15: Apoyo en máquina. | O15: Se retiró guarda para la limpieza de polines. En zona de carga. | P15: =COUNTIF($I$3:I15,I15) -> 2 | Q15: =IF(Tabla107[[#This Row],[MAQUINA / EQUIPO]]="","",Tabla107[[#This Row],[MAQUINA / EQUIPO]]) -> TOSTADOR PETRONCINI NUEVO | BK15: CONCHA BAWERMEISTER
B16: =IF(I16="","",CONCATENATE(I16,"-",P16)) -> LINEA AUTOMATICA HACOS 1-4 | C16: 46205 | D16: CARLOS TAPIA | E16: MAÑANA | F16: 07:15 | G16: 07:45 | H16: 0.020833333 | I16: LINEA AUTOMATICA HACOS 1 | J16: Maquinaria | K16: Inspección | L16: PROGRAMADA | N16: Inspección de máquina en funcionamiento | O16: Se dió seguimiento al funcionamiento de máquina con carga | P16: =COUNTIF($I$3:I16,I16) -> 4 | Q16: =IF(Tabla107[[#This Row],[MAQUINA / EQUIPO]]="","",Tabla107[[#This Row],[MAQUINA / EQUIPO]]) -> LINEA AUTOMATICA HACOS 1 | BK16: CONCHA ELK
B17: =IF(I17="","",CONCATENATE(I17,"-",P17)) -> ENVASADORA TEPACK-1 | C17: 46205 | D17: CARLOS TAPIA | E17: MAÑANA | F17: 08:00 | G17: 09:00 | H17: 0.041666667 | I17: ENVASADORA TEPACK | J17: Maquinaria | K17: Reparacion | L17: NO PROGRAMADA | M17: MECÁNICA | N17: Cuchilla no corta el laminado. | O17: Se encontró cuchilla suelta y sucia. Se retiró cuchilla para su limpieza y se colocó en posición correcta. | P17: =COUNTIF($I$3:I17,I17) -> 1 | Q17: =IF(Tabla107[[#This Row],[MAQUINA / EQUIPO]]="","",Tabla107[[#This Row],[MAQUINA / EQUIPO]]) -> ENVASADORA TEPACK | BK17: CORTADORA DE CASTAÑA
B18: =IF(I18="","",CONCATENATE(I18,"-",P18)) -> ENVASADORA TEPACK-2 | C18: 46205 | D18: CARLOS TAPIA | E18: MAÑANA | F18: 11:00 | G18: 13:00 | H18: 0.083333333 | I18: ENVASADORA TEPACK | J18: Maquinaria | K18: Ajuste /Calibracion | L18: PROGRAMADA | N18: No logran calibrar el sellado, el plegado se abre y se mueve. | O18: Se revisó y se ajusto banda de arrastre. Se alineó sellador y plegadores. Se realizó pruebas y se dejó máquina operativa | P18: =COUNTIF($I$3:I18,I18) -> 2 | Q18: =IF(Tabla107[[#This Row],[MAQUINA / EQUIPO]]="","",Tabla107[[#This Row],[MAQUINA / EQUIPO]]) -> ENVASADORA TEPACK | BK18: CORTADORA DE CENTROS
B19: =IF(I19="","",CONCATENATE(I19,"-",P19)) -> CALDERO, CHRILLER Y COMPRESOR-1 | C19: 46205 | D19: JOSÉ HAÑARI | E19: TARDE | F19: 12:40 | G19: 13:00 | H19: 0.013888889 | I19: CALDERO, CHRILLER Y COMPRESOR | J19: Equipos auxiliares | K19: Inspección | L19: PROGRAMADA | N19: Se realiza inspección de equipos y parámetros | P19: =COUNTIF($I$3:I19,I19) -> 1 | Q19: =IF(Tabla107[[#This Row],[MAQUINA / EQUIPO]]="","",Tabla107[[#This Row],[MAQUINA / EQUIPO]]) -> CALDERO, CHRILLER Y COMPRESOR | BK19: CORTADORA DE MASA
B20: =IF(I20="","",CONCATENATE(I20,"-",P20)) -> PLANTA INDUSTRIAL-1 | C20: 46205 | D20: CARLOS PUMA | E20: TARDE | F20: 13:10 | G20: 14:00 | H20: 0.034722222 | I20: PLANTA INDUSTRIAL | J20: Area | K20: Inspección | L20: PROGRAMADA | N20: Inspección de equipos en uso | P20: =COUNTIF($I$3:I20,I20) -> 1 | Q20: =IF(Tabla107[[#This Row],[MAQUINA / EQUIPO]]="","",Tabla107[[#This Row],[MAQUINA / EQUIPO]]) -> PLANTA INDUSTRIAL | BK20: CORTADORA DE TURRON
B21: =IF(I21="","",CONCATENATE(I21,"-",P21)) -> LINEA AUTOMATICA HACOS 1-5 | C21: 46205 | D21: CARLOS TAPIA | E21: MAÑANA | F21: 13:45 | G21: 14:00 | H21: 0.010416667 | I21: LINEA AUTOMATICA HACOS 1 | J21: Maquinaria | K21: Inspección | L21: PROGRAMADA | N21: Apoyo en tanque de chocolate. | O21: Se revisó tanque de chocolate, se coordino la limpieza del mismo | P21: =COUNTIF($I$3:I21,I21) -> 5 | Q21: =IF(Tabla107[[#This Row],[MAQUINA / EQUIPO]]="","",Tabla107[[#This Row],[MAQUINA / EQUIPO]]) -> LINEA AUTOMATICA HACOS 1 | BK21: DESINFECCION DE CASTAÑA
B22: =IF(I22="","",CONCATENATE(I22,"-",P22)) -> LINEA AUTOMATICA HACOS 1-6 | C22: 46205 | D22: CARLOS PUMA | E22: TARDE | F22: 14:05 | G22: 14:20 | H22: 0.010416667 | I22: LINEA AUTOMATICA HACOS 1 | J22: Maquinaria | K22: Limpieza | L22: PROGRAMADA | N22: Limpieza de tablero eléctrico de tanque de almacenamiento | P22: =COUNTIF($I$3:I22,I22) -> 6 | Q22: =IF(Tabla107[[#This Row],[MAQUINA / EQUIPO]]="","",Tabla107[[#This Row],[MAQUINA / EQUIPO]]) -> LINEA AUTOMATICA HACOS 1 | BK22: DETECTOR DE METALES
B23: =IF(I23="","",CONCATENATE(I23,"-",P23)) -> FORRADORA MINIFLEX-2 | C23: 46205 | D23: CARLOS PUMA | E23: TARDE | F23: 14:25 | G23: 14:50 | H23: 0.017361111 | I23: FORRADORA MINIFLEX | J23: Maquinaria | K23: Ajuste /Calibracion | L23: NO PROGRAMADA | M23: ELÉCTRICA | N23: No desbobina laminado | O23: Se regulo sensores de pedal y se realizó pruebas | P23: =COUNTIF($I$3:I23,I23) -> 2 | Q23: =IF(Tabla107[[#This Row],[MAQUINA / EQUIPO]]="","",Tabla107[[#This Row],[MAQUINA / EQUIPO]]) -> FORRADORA MINIFLEX | BK23: ELEVADOR DE CACAO
B24: =IF(I24="","",CONCATENATE(I24,"-",P24)) -> LINEA AUTOMATICA HACOS 1-7 | C24: 46205 | D24: CARLOS PUMA | E24: TARDE | F24: 14:55 | G24: 15:15 | H24: 0.013888889 | I24: LINEA AUTOMATICA HACOS 1 | J24: Maquinaria | K24: Limpieza | L24: PROGRAMADA | N24: Desarme de samfill para limpieza | P24: =COUNTIF($I$3:I24,I24) -> 7 | Q24: =IF(Tabla107[[#This Row],[MAQUINA / EQUIPO]]="","",Tabla107[[#This Row],[MAQUINA / EQUIPO]]) -> LINEA AUTOMATICA HACOS 1 | BK24: EMP. CHOCOTECH
B25: =IF(I25="","",CONCATENATE(I25,"-",P25)) -> EMP. SAPAL-4 | C25: 46205 | D25: CARLOS PUMA | E25: TARDE | F25: 16:30 | G25: 18:00 | H25: 0.0625 | I25: EMP. SAPAL | J25: Maquinaria | K25: Ajuste /Calibracion | L25: NO PROGRAMADA | M25: MECÁNICA | N25: Goma no dosifica correctamente | O25: Se limpio boquilla, se purgó goma , se retiró parte de impurezas , se regulo pocision de dosificador y sensor , se apoyó regulando puntos de goma | P25: =COUNTIF($I$3:I25,I25) -> 4 | Q25: =IF(Tabla107[[#This Row],[MAQUINA / EQUIPO]]="","",Tabla107[[#This Row],[MAQUINA / EQUIPO]]) -> EMP. SAPAL | BK25: EMPAQUETADORA 2
B26: =IF(I26="","",CONCATENATE(I26,"-",P26)) -> LINEA AUTOMATICA HACOS 1-8 | C26: 46205 | D26: CARLOS PUMA | E26: TARDE | F26: 18:20 | G26: 18:40 | H26: 0.013888889 | I26: LINEA AUTOMATICA HACOS 1 | J26: Maquinaria | K26: SET UP | L26: PROGRAMADA | N26: Armado de samfill | P26: =COUNTIF($I$3:I26,I26) -> 8 | Q26: =IF(Tabla107[[#This Row],[MAQUINA / EQUIPO]]="","",Tabla107[[#This Row],[MAQUINA / EQUIPO]]) -> LINEA AUTOMATICA HACOS 1 | BK26: EMPAQUETADORA AMP ROSE
B27: =IF(I27="","",CONCATENATE(I27,"-",P27)) -> EMP. FLOWPACK 2-1 | C27: 46205 | D27: CARLOS PUMA | E27: TARDE | F27: 19:00 | G27: 20:00 | H27: 0.041666667 | I27: EMP. FLOWPACK 2 | J27: Maquinaria | K27: SET UP | L27: PROGRAMADA | N27: Cambio de formato flowpack 2 | O27: Se cambió formato de milky a bite size | P27: =COUNTIF($I$3:I27,I27) -> 1 | Q27: =IF(Tabla107[[#This Row],[MAQUINA / EQUIPO]]="","",Tabla107[[#This Row],[MAQUINA / EQUIPO]]) -> EMP. FLOWPACK 2 | BK27: EMPAQUETADORA GD
B28: =IF(I28="","",CONCATENATE(I28,"-",P28)) -> GRAGEADORA CRG-100X-1 | C28: 46205 | D28: CARLOS PUMA | E28: TARDE | F28: 20:30 | G28: 20:45 | H28: 0.010416667 | I28: GRAGEADORA CRG-100X | J28: Maquinaria | K28: Inspección | L28: PROGRAMADA | N28: Inspección de equipo de aire acondicionado | P28: =COUNTIF($I$3:I28,I28) -> 1 | Q28: =IF(Tabla107[[#This Row],[MAQUINA / EQUIPO]]="","",Tabla107[[#This Row],[MAQUINA / EQUIPO]]) -> GRAGEADORA CRG-100X | BK28: ENCEFALONADORA
B29: =IF(I29="","",CONCATENATE(I29,"-",P29)) -> TOSTADOR PETRONCINI NUEVO-3 | C29: 46205 | D29: OMAR NINA | E29: NOCHE | F29: 21:31 | G29: 21:42 | H29: 0.0076388889 | I29: TOSTADOR PETRONCINI NUEVO | J29: Maquinaria | K29: Inspección | L29: NO PROGRAMADA | M29: ELÉCTRICA | N29: No permite iniciar máquina | O29: Verificación de sensores. | P29: =COUNTIF($I$3:I29,I29) -> 3 | Q29: =IF(Tabla107[[#This Row],[MAQUINA / EQUIPO]]="","",Tabla107[[#This Row],[MAQUINA / EQUIPO]]) -> TOSTADOR PETRONCINI NUEVO | BK29: FAMAIC
B30: =IF(I30="","",CONCATENATE(I30,"-",P30)) -> MEZCLADORA DE DOBLE EJE SSHS40-1 | C30: 46205 | D30: OMAR NINA | E30: NOCHE | F30: 21:51 | G30: 22:12 | H30: 0.014583333 | I30: MEZCLADORA DE DOBLE EJE SSHS40 | J30: Maquinaria | K30: Lubricación | L30: PROGRAMADA | N30: Lubricación | P30: =COUNTIF($I$3:I30,I30) -> 1 | Q30: =IF(Tabla107[[#This Row],[MAQUINA / EQUIPO]]="","",Tabla107[[#This Row],[MAQUINA / EQUIPO]]) -> MEZCLADORA DE DOBLE EJE SSHS40 | BK30: FAMAIC
B31: =IF(I31="","",CONCATENATE(I31,"-",P31)) -> EMP. 2 - CARLE MONTANARY-1 | C31: 46205 | D31: OMAR NINA | E31: NOCHE | F31: 22:16 | G31: 22:25 | H31: 0.00625 | I31: EMP. 2 - CARLE MONTANARY | J31: Maquinaria | K31: Ajuste /Calibracion | L31: PROGRAMADA | N31: Calibración de tirante de cuchilla para formato mazapán | P31: =COUNTIF($I$3:I31,I31) -> 1 | Q31: =IF(Tabla107[[#This Row],[MAQUINA / EQUIPO]]="","",Tabla107[[#This Row],[MAQUINA / EQUIPO]]) -> EMP. 2 - CARLE MONTANARY | BK31: FLOWPACK 1
B32: =IF(I32="","",CONCATENATE(I32,"-",P32)) -> EMP. NAPOLITANA-2 | C32: 46205 | D32: OMAR NINA | E32: NOCHE | F32: 22:30 | G32: 23:10 | H32: 0.027777778 | I32: EMP. NAPOLITANA | J32: Maquinaria | K32: Ajuste /Calibracion | L32: NO PROGRAMADA | M32: MECÁNICA | N32: Sonido extraño, papel aluminio sale demasiado largo, solo sale un punto de goma y etiquetas desalineadas | O32: Lubricación y calibración de equipo | P32: =COUNTIF($I$3:I32,I32) -> 2 | Q32: =IF(Tabla107[[#This Row],[MAQUINA / EQUIPO]]="","",Tabla107[[#This Row],[MAQUINA / EQUIPO]]) -> EMP. NAPOLITANA | BK32: FLOWPACK 2
B33: =IF(I33="","",CONCATENATE(I33,"-",P33)) -> EMP. SAPAL-5 | C33: 46205 | D33: OMAR NINA | E33: NOCHE | F33: 23:25 | G33: 23:59 | H33: 0.023611111 | I33: EMP. SAPAL | J33: Maquinaria | K33: Ajuste /Calibracion | L33: NO PROGRAMADA | M33: MECÁNICA | N33: Producto se rompe en los selladores | O33: Calibración de selladores y medida 4 | P33: =COUNTIF($I$3:I33,I33) -> 5 | Q33: =IF(Tabla107[[#This Row],[MAQUINA / EQUIPO]]="","",Tabla107[[#This Row],[MAQUINA / EQUIPO]]) -> EMP. SAPAL | BK33: FORMADOR DE BOLAS
B34: =IF(I34="","",CONCATENATE(I34,"-",P34)) | P34: =COUNTIF($I$3:I34,I34) -> 0 | Q34: =IF(Tabla107[[#This Row],[MAQUINA / EQUIPO]]="","",Tabla107[[#This Row],[MAQUINA / EQUIPO]]) | BK34: FORMADORA DE CORDONES
B35: =IF(I35="","",CONCATENATE(I35,"-",P35)) | P35: =COUNTIF($I$3:I35,I35) -> 0 | Q35: =IF(Tabla107[[#This Row],[MAQUINA / EQUIPO]]="","",Tabla107[[#This Row],[MAQUINA / EQUIPO]]) | BK35: FORRADORA
B36: =IF(I36="","",CONCATENATE(I36,"-",P36)) | P36: =COUNTIF($I$3:I36,I36) -> 0 | Q36: =IF(Tabla107[[#This Row],[MAQUINA / EQUIPO]]="","",Tabla107[[#This Row],[MAQUINA / EQUIPO]]) | BK36: GIANINNI 1
B37: =IF(I37="","",CONCATENATE(I37,"-",P37)) | P37: =COUNTIF($I$3:I37,I37) -> 0 | Q37: =IF(Tabla107[[#This Row],[MAQUINA / EQUIPO]]="","",Tabla107[[#This Row],[MAQUINA / EQUIPO]]) | BK37: GIANNINI 3
B38: =IF(I38="","",CONCATENATE(I38,"-",P38)) | P38: =COUNTIF($I$3:I38,I38) -> 0 | Q38: =IF(Tabla107[[#This Row],[MAQUINA / EQUIPO]]="","",Tabla107[[#This Row],[MAQUINA / EQUIPO]]) | BK38: GIRADORA CABRELLON
B39: =IF(I39="","",CONCATENATE(I39,"-",P39)) | P39: =COUNTIF($I$3:I39,I39) -> 0 | Q39: =IF(Tabla107[[#This Row],[MAQUINA / EQUIPO]]="","",Tabla107[[#This Row],[MAQUINA / EQUIPO]]) | BK39: GIRADORA COLLMAN
B40: =IF(I40="","",CONCATENATE(I40,"-",P40)) | P40: =COUNTIF($I$3:I40,I40) -> 0 | Q40: =IF(Tabla107[[#This Row],[MAQUINA / EQUIPO]]="","",Tabla107[[#This Row],[MAQUINA / EQUIPO]]) | BK40: GRAGEADORA
B41: =IF(I41="","",CONCATENATE(I41,"-",P41)) | P41: =COUNTIF($I$3:I41,I41) -> 0 | Q41: =IF(Tabla107[[#This Row],[MAQUINA / EQUIPO]]="","",Tabla107[[#This Row],[MAQUINA / EQUIPO]]) | BK41: HACOS 1
B42: =IF(I42="","",CONCATENATE(I42,"-",P42)) | P42: =COUNTIF($I$3:I42,I42) -> 0 | Q42: =IF(Tabla107[[#This Row],[MAQUINA / EQUIPO]]="","",Tabla107[[#This Row],[MAQUINA / EQUIPO]]) | BK42: HACOS 2
B43: =IF(I43="","",CONCATENATE(I43,"-",P43)) | P43: =COUNTIF($I$3:I43,I43) -> 0 | Q43: =IF(Tabla107[[#This Row],[MAQUINA / EQUIPO]]="","",Tabla107[[#This Row],[MAQUINA / EQUIPO]]) | BK43: IMPRESORA LASER MACSA
B44: =IF(I44="","",CONCATENATE(I44,"-",P44)) | P44: =COUNTIF($I$3:I44,I44) -> 0 | Q44: =IF(Tabla107[[#This Row],[MAQUINA / EQUIPO]]="","",Tabla107[[#This Row],[MAQUINA / EQUIPO]]) | BK44: JAF INOX
B45: =IF(I45="","",CONCATENATE(I45,"-",P45)) | P45: =COUNTIF($I$3:I45,I45) -> 0 | Q45: =IF(Tabla107[[#This Row],[MAQUINA / EQUIPO]]="","",Tabla107[[#This Row],[MAQUINA / EQUIPO]]) | BK45: LAMINADORA
... B48: =IF(I48="","",CONCATENATE(I48,"-",P48)) | P48: =COUNTIF($I$3:I48,I48) -> 0 | Q48: =IF(Tabla107[[#This Row],[MAQUINA / EQUIPO]]="","",Tabla107[[#This Row],[MAQUINA / EQUIPO]]) | BK48: METALMAQ
B49: =IF(I49="","",CONCATENATE(I49,"-",P49)) | J49: =IFERROR(VLOOKUP(I49,DATOS!$M$2:$N$219,2,FALSE),"") | P49: =COUNTIF($I$3:I49,I49) -> 0 | Q49: =IF(Tabla107[[#This Row],[MAQUINA / EQUIPO]]="","",Tabla107[[#This Row],[MAQUINA / EQUIPO]]) | BK49: MEZCLADOR LEHMAN
B50: =IF(I50="","",CONCATENATE(I50,"-",P50)) | J50: =IFERROR(VLOOKUP(I50,DATOS!$M$2:$N$219,2,FALSE),"") | P50: =COUNTIF($I$3:I50,I50) -> 0 | Q50: =IF(Tabla107[[#This Row],[MAQUINA / EQUIPO]]="","",Tabla107[[#This Row],[MAQUINA / EQUIPO]]) | BK50: MEZCLADORA BUHLER
B51: =IF(I51="","",CONCATENATE(I51,"-",P51)) | J51: =IFERROR(VLOOKUP(I51,DATOS!$M$2:$N$219,2,FALSE),"") | P51: =COUNTIF($I$3:I51,I51) -> 0 | Q51: =IF(Tabla107[[#This Row],[MAQUINA / EQUIPO]]="","",Tabla107[[#This Row],[MAQUINA / EQUIPO]]) | BK51: MINIFLEX
B52: =IF(I52="","",CONCATENATE(I52,"-",P52)) | J52: =IFERROR(VLOOKUP(I52,DATOS!$M$2:$N$219,2,FALSE),"") | P52: =COUNTIF($I$3:I52,I52) -> 0 | Q52: =IF(Tabla107[[#This Row],[MAQUINA / EQUIPO]]="","",Tabla107[[#This Row],[MAQUINA / EQUIPO]]) | BK52: MOLDEO MANUAL
B53: =IF(I53="","",CONCATENATE(I53,"-",P53)) | J53: =IFERROR(VLOOKUP(I53,DATOS!$M$2:$N$219,2,FALSE),"") | P53: =COUNTIF($I$3:I53,I53) -> 0 | Q53: =IF(Tabla107[[#This Row],[MAQUINA / EQUIPO]]="","",Tabla107[[#This Row],[MAQUINA / EQUIPO]]) | BK53: MOLINO BILLAS
B54: =IF(I54="","",CONCATENATE(I54,"-",P54)) | J54: =IFERROR(VLOOKUP(I54,DATOS!$M$2:$N$219,2,FALSE),"") | P54: =COUNTIF($I$3:I54,I54) -> 0 | Q54: =IF(Tabla107[[#This Row],[MAQUINA / EQUIPO]]="","",Tabla107[[#This Row],[MAQUINA / EQUIPO]]) | BK54: MOLINO DE AZUCAR
B55: =IF(I55="","",CONCATENATE(I55,"-",P55)) | J55: =IFERROR(VLOOKUP(I55,DATOS!$M$2:$N$219,2,FALSE),"") | P55: =COUNTIF($I$3:I55,I55) -> 0 | Q55: =IF(Tabla107[[#This Row],[MAQUINA / EQUIPO]]="","",Tabla107[[#This Row],[MAQUINA / EQUIPO]]) | BK55: MOLINO REBOTE
B56: =IF(I56="","",CONCATENATE(I56,"-",P56)) | J56: =IFERROR(VLOOKUP(I56,DATOS!$M$2:$N$219,2,FALSE),"") | P56: =COUNTIF($I$3:I56,I56) -> 0 | Q56: =IF(Tabla107[[#This Row],[MAQUINA / EQUIPO]]="","",Tabla107[[#This Row],[MAQUINA / EQUIPO]]) | BK56: NAPOLITANA
B57: =IF(I57="","",CONCATENATE(I57,"-",P57)) | J57: =IFERROR(VLOOKUP(I57,DATOS!$M$2:$N$219,2,FALSE),"") | P57: =COUNTIF($I$3:I57,I57) -> 0 | Q57: =IF(Tabla107[[#This Row],[MAQUINA / EQUIPO]]="","",Tabla107[[#This Row],[MAQUINA / EQUIPO]]) | BK57: NETCH
B58: =IF(I58="","",CONCATENATE(I58,"-",P58)) | J58: =IFERROR(VLOOKUP(I58,DATOS!$M$2:$N$219,2,FALSE),"") | P58: =COUNTIF($I$3:I58,I58) -> 0 | Q58: =IF(Tabla107[[#This Row],[MAQUINA / EQUIPO]]="","",Tabla107[[#This Row],[MAQUINA / EQUIPO]]) | BK58: NOVA
B59: =IF(I59="","",CONCATENATE(I59,"-",P59)) | J59: =IFERROR(VLOOKUP(I59,DATOS!$M$2:$N$219,2,FALSE),"") | P59: =COUNTIF($I$3:I59,I59) -> 0 | Q59: =IF(Tabla107[[#This Row],[MAQUINA / EQUIPO]]="","",Tabla107[[#This Row],[MAQUINA / EQUIPO]]) | BK59: OTRO
B60: =IF(I60="","",CONCATENATE(I60,"-",P60)) | J60: =IFERROR(VLOOKUP(I60,DATOS!$M$2:$N$219,2,FALSE),"") | P60: =COUNTIF($I$3:I60,I60) -> 0 | Q60: =IF(Tabla107[[#This Row],[MAQUINA / EQUIPO]]="","",Tabla107[[#This Row],[MAQUINA / EQUIPO]]) | BK60: OTROS
... B62: =IF(I62="","",CONCATENATE(I62,"-",P62)) | J62: =IFERROR(VLOOKUP(I62,DATOS!$M$2:$N$219,2,FALSE),"") | P62: =COUNTIF($I$3:I62,I62) -> 0 | Q62: =IF(Tabla107[[#This Row],[MAQUINA / EQUIPO]]="","",Tabla107[[#This Row],[MAQUINA / EQUIPO]]) | BK62: PETRONCINI
BK63: PICADOR DE CASTAÑA
BK64: PLANTA PILOTO
BK65: PROCESADORA BOXA
BK66: QUEB. DE CACAO
L67: ACUM | M67: 27-2026 | BK67: RAYOS X 1
B68: Suma de T.TOTAL | C68: Etiquetas de columna | BK68: RAYOS X 2
B69: Etiquetas de fila | C69: NO PROGRAMADA | D69: PROGRAMADA | E69: Total general | L69: Cuenta de M/E | M69: Etiquetas de columna | BK69: REFINADOR LEHMAN
B70: LINEA AUTOMATICA HACOS 2 | D70: 0.054861111 | E70: 0.054861111 | M70: NO PROGRAMADA | BK70: REFINADOR BAWERMEISTER
B71: EMP. SACMI | C71: 0.016666667 | E71: 0.016666667 | L71: Etiquetas de fila | M71: ELÉCTRICA | N71: MECÁNICA | BK71: REFINADOR BUHLER
B72: BARQUILLERA FRANZ HAAZ | D72: 0.013888889 | E72: 0.013888889 | L72: 1ER PISO | M72: 1 | BK72: SACMI
B73: CORTADORA DE TURRON | C73: 0.0125 | E73: 0.0125 | L73: CORTADORA DE TURRON | N73: 1 | BK73: SALA DE CORRIDO
B74: POZO DE CHILLER | D74: 0.011805556 | E74: 0.011805556 | L74: EMP. 2 - CARLE MONTANARY | N74: 2 | BK74: SAPAL
B75: CALDERO, CHRILLER Y COMPRESOR | D75: 0.011805556 | E75: 0.011805556 | L75: EMP. SACMI | N75: 1 | BK75: SELLADORA DE BOLSITAS
B76: TEMPERADORA CHOCOLATIER | C76: 0.010416667 | E76: 0.010416667 | L76: ENCELOFANADORA ECCOPAC | N76: 1 | BK76: SELLADORA ECOPACK
B77: PROCESADORA DE MASAS - NETZSCH | D77: 0.010416667 | E77: 0.010416667 | L77: LINEA AUTOMATICA HACOS 1 | N77: 2 | BK77: TANQUE DE CHOCOLATE
B78: RAYOS X 2 | C78: 0.010416667 | E78: 0.010416667 | L78: RAYOS X 2 | N78: 1 | BK78: TANQUE DE PASTA GRUESA
B79: Total general | C79: 0.05 | D79: 0.10277778 | E79: 0.15277778 | L79: TEMPERADORA CHOCOLATIER | M79: 1
B96: P/NP | C96: (Varios elementos)
BK97: TANQUE PASTA FINA
B98: Suma de T.TOTAL | C98: Etiquetas de columna | BK98: TANQUE PASTA FINA
B99: Etiquetas de fila | C99: ELÉCTRICA | D99: MECÁNICA | E99: Total general | BK99: TOSTADOR CM
B100: EMP. SACMI | D100: 0.016666667 | E100: 0.016666667
B101: CORTADORA DE TURRON | D101: 0.0125 | E101: 0.0125
B102: TEMPERADORA CHOCOLATIER | C102: 0.010416667 | E102: 0.010416667
B103: RAYOS X 2 | D103: 0.010416667 | E103: 0.010416667
B104: Total general | C104: 0.010416667 | D104: 0.039583333 | E104: 0.05
B118: Suma de T.TOTAL | C118: Etiquetas de columna
B119: Etiquetas de fila | C119: Ajuste /Calibracion | D119: Encendido / Arranque de linea | E119: Inspección | F119: SET UP | G119: Reparacion | H119: Lubricación | I119: M.General | J119: Total general
B120: LINEA AUTOMATICA HACOS 2 | E120: 0.054861111 | J120: 0.054861111
B121: EMP. SACMI | G121: 0.016666667 | J121: 0.016666667
B122: BARQUILLERA FRANZ HAAZ | E122: 0.013888889 | J122: 0.013888889
B123: CORTADORA DE TURRON | H123: 0.0125 | J123: 0.0125
B124: POZO DE CHILLER | I124: 0.011805556 | J124: 0.011805556
B125: CALDERO, CHRILLER Y COMPRESOR | E125: 0.011805556 | J125: 0.011805556
B126: TEMPERADORA CHOCOLATIER | D126: 0.010416667 | J126: 0.010416667
B127: PROCESADORA DE MASAS - NETZSCH | F127: 0.010416667 | J127: 0.010416667
B128: RAYOS X 2 | C128: 0.010416667 | J128: 0.010416667
B129: Total general | C129: 0.010416667 | D129: 0.010416667 | E129: 0.080555556 | F129: 0.010416667 | G129: 0.016666667 | H129: 0.0125 | I129: 0.011805556 | J129: 0.15277778
B151: Cuenta de TURNO | C151: Etiquetas de columna
B152: Etiquetas de fila | C152: MAÑANA | D152: Total general
B153: LINEA AUTOMATICA HACOS 2 | C153: 3 | D153: 3
...

Sheet PRESENTACION F.
N1: =+CONCATENATE("SEM. - 0",WEEKNUM(TODAY())) -> SEM. - 027
M3: Fecha | P3: =TODAY()-1 -> 46205 | Q3: 📅
M4: RESUMEN DIARIO - MANTENIMIENTO
M5: Fabrica de Chocolates la Iberica | Q5: =IF(Q7="OK","MAÑANA","") -> MAÑANA | R5: =IF(R7="OK","TARDE","") -> TARDE | S5: =IF(S7="OK","NOCHE","") -> NOCHE | V5: P/NP | W5: NO PROGRAMADA | Y5: P/NP | Z5: NO PROGRAMADA
Q6: MAÑANA | R6: TARDE | S6: NOCHE
M7: Horas totales de mantenimiento | P7: =ROUND('TABLA-DIA'!H1*24,1) -> 18.8 | Q7: =+IF(COUNTIF('TABLA-DIA'!E3:E64,"MAÑANA")>0,"OK","") -> OK | R7: =+IF(COUNTIF('TABLA-DIA'!E3:E64,"TARDE")>0,"OK","") -> OK | S7: =+IF(COUNTIF('TABLA-DIA'!E3:E64,"NOCHE")>0,"OK","") -> OK | T7: =+COUNTIF(Q7:S7,"OK") -> 3 | V7: Etiquetas de fila | W7: Suma de T.TOTAL | Y7: OBSERVACION | Z7: Suma de T.TOTAL
M8: Horas no programadas | P8: =ROUND(SUMIF(Tabla107[P/NP],"NO PROGRAMADA",Tabla107[T.TOTAL])*24,2) -> 9.42 | Q8: =+P8/P7 -> 0.50106383 | V8: EMP. SACMI | W8: 0.016666667 | Y8: Punta de pistola desprendida, se retiro punta y se llevó a taller para pegarlo | Z8: 0.016666667
M9: Intervenciones totales | P9: =+COUNTA(Tabla107[FECHA]) -> 31 | V9: CORTADORA DE TURRON | W9: 0.0125 | Y9: Equipo muy duro para empujar | Z9: 0.0125
M10: Equipo crtitico del dia | P10: =+INDEX(V8:V20,MATCH(MAX(W8:W20),W8:W20,0)) -> EMP. SACMI | Q10: =+VLOOKUP(P10,V7:W25,2,FALSE) -> 0.016666667 | R10: =+Q10*24 -> 0.4 | S10: =+R10/P8 -> 0.042462845 | V10: TEMPERADORA CHOCOLATIER | W10: 0.010416667 | Y10: Temperadora no enciende | Z10: 0.010416667
M11: Tasa de actividades programadas | P11: =+COUNTIF(Tabla107[P/NP],"PROGRAMADA") -> 19 | Q11: =+P11/P9 -> 0.61290323 | V11: RAYOS X 2 | W11: 0.010416667 | Y11: Apoyo en máquina. Producto se junta y el equipo lo rechaza | Z11: 0.010416667
N13: Tiempo | O13: Detalle | Q13: Equipo
N14: =LARGE($Z$8:$Z$25,1) -> 0.016666667 | O14: =INDEX(Y8:Y26,MATCH(N14,Z8:Z25,0)) -> Punta de pistola desprendida, se retiro punta y se llevó a taller para pegarlo | Q14: =+VLOOKUP(O14,'TABLA-DIA'!$N$2:$Q$62,4,FALSE) -> #N/A
N15: =LARGE($Z$8:$Z$25,2) -> 0.0125 | O15: =INDEX(Y8:Y26,MATCH(N15,Z8:Z25,0)) -> Equipo muy duro para empujar | Q15: =+VLOOKUP(O15,'TABLA-DIA'!$N$2:$Q$62,4,FALSE) -> #N/A
N16: =LARGE($Z$8:$Z$25,3) -> 0.010416667 | O16: =INDEX(Y8:Y26,MATCH(N16,Z8:Z25,0)) -> Temperadora no enciende | Q16: =+VLOOKUP(O16,'TABLA-DIA'!$N$2:$Q$62,4,FALSE) -> #N/A
N18: Tiempo | O18: Detalle | Q18: Equipo
N19: =LARGE('TABLA-DIA'!H3:H64,1) -> 0.090277778 | O19: =INDEX('TABLA-DIA'!N3:N62,MATCH(N19,'TABLA-DIA'!H3:H62,0)) -> No pega goma en etiqueta | Q19: =+VLOOKUP(O19,'TABLA-DIA'!$N$2:$Q$62,4,FALSE) -> EMP. SAPAL
N22: PARETO
N23: P/NP | O23: NO PROGRAMADA | P23: AJUSTAR VALORES A PARETO - ARRASTRAR
R24: =+SUM(R26:R45) -> 1.2 | V24: Etiquetas de fila | W24: Suma de T.TOTAL
N25: Etiquetas de fila | O25: Suma de T.TOTAL | P25: Equipo | Q25: Total | R25: Tiempo | S25: Porcentaje (%) | T25: Acumulado | V25: NO PROGRAMADA | W25: 0.05
N26: EMP. SACMI | O26: 0.016666667 | P26: =IF(ISBLANK(N26),"",N26) -> EMP. SACMI | Q26: =IF(ISBLANK(O26),"",O26) -> 0.016666667 | R26: =IF(ISBLANK(O26),"",(O26*24)) -> 0.4 | S26: =IFERROR(R26/$R$24,"") -> 0.33333333 | T26: =IFERROR(S26,"") -> 0.33333333 | V26: PROGRAMADA | W26: 0.10277778 | X26: =+X28+X29 -> 3.6666667
N27: CORTADORA DE TURRON | O27: 0.0125 | P27: =IF(ISBLANK(N27),"",N27) -> CORTADORA DE TURRON | Q27: =IF(ISBLANK(O27),"",O27) -> 0.0125 | R27: =IF(ISBLANK(O27),"",(O27*24)) -> 0.3 | S27: =IFERROR(R27/$R$24,"") -> 0.25 | T27: =IFERROR(T26+S27,"") -> 0.58333333 | X27: Hrs (0.00) | Y27: Porcentaje | Z27: Hrs (0.00)
N28: TEMPERADORA CHOCOLATIER | O28: 0.010416667 | P28: =IF(ISBLANK(N28),"",N28) -> TEMPERADORA CHOCOLATIER | Q28: =IF(ISBLANK(O28),"",O28) -> 0.010416667 | R28: =IF(ISBLANK(O28),"",(O28*24)) -> 0.25 | S28: =IFERROR(R28/$R$24,"") -> 0.20833333 | T28: =IFERROR(T27+S28,"") -> 0.79166667 | V28: NO PROGRAMADA | W28: =+VLOOKUP(V28,V24:W26,2,FALSE) -> 0.05 | X28: =+W25*24 -> 1.2 | Y28: ="("& ROUND(X28/$X$26,2)*100&"% )" -> (33% ) | Z28: =ROUND(X28,2)& " h." -> 1.2 h.
N29: RAYOS X 2 | O29: 0.010416667 | P29: =IF(ISBLANK(N29),"",N29) -> RAYOS X 2 | Q29: =IF(ISBLANK(O29),"",O29) -> 0.010416667 | R29: =IF(ISBLANK(O29),"",(O29*24)) -> 0.25 | S29: =IFERROR(R29/$R$24,"") -> 0.20833333 | T29: =IFERROR(T28+S29,"") -> 1 | V29: PROGRAMADA | W29: =+VLOOKUP(V29,V25:W27,2,FALSE) -> 0.10277778 | X29: =+W26*24 -> 2.4666667 | Y29: ="("& ROUND(X29/$X$26,2)*100&"% )" -> (67% ) | Z29: =ROUND(X29,2)& " h." -> 2.47 h.
P30: =IF(ISBLANK(N30),"",N30) | Q30: =IF(ISBLANK(O30),"",O30) | R30: =IF(ISBLANK(O30),"",(O30*24)) | S30: =IFERROR(R30/$R$24,"") | T30: =IFERROR(T29+S30,"")
P31: =IF(ISBLANK(N31),"",N31) | Q31: =IF(ISBLANK(O31),"",O31) | R31: =IF(ISBLANK(O31),"",(O31*24)) | S31: =IFERROR(R31/$R$24,"") | T31: =IFERROR(T30+S31,"")
P32: =IF(ISBLANK(N32),"",N32) | Q32: =IF(ISBLANK(O32),"",O32) | R32: =IF(ISBLANK(O32),"",(O32*24)) | S32: =IFERROR(R32/$R$24,"") | T32: =IFERROR(T31+S32,"") | V32: Etiquetas de fila | W32: Suma de T.TOTAL
P33: =IF(ISBLANK(N33),"",N33) | Q33: =IF(ISBLANK(O33),"",O33) | R33: =IF(ISBLANK(O33),"",(O33*24)) | S33: =IFERROR(R33/$R$24,"") | T33: =IFERROR(T32+S33,"") | V33: ELÉCTRICA | W33: 0.010416667
P34: =IF(ISBLANK(N34),"",N34) | Q34: =IF(ISBLANK(O34),"",O34) | R34: =IF(ISBLANK(O34),"",(O34*24)) | S34: =IFERROR(R34/$R$24,"") | T34: =IFERROR(T33+S34,"") | V34: MECÁNICA | W34: 0.039583333 | X34: =+X36+X37 -> 1.2
P35: =IF(ISBLANK(N35),"",N35) | Q35: =IF(ISBLANK(O35),"",O35) | R35: =IF(ISBLANK(O35),"",(O35*24)) | S35: =IFERROR(R35/$R$24,"") | T35: =IFERROR(T34+S35,"") | V35: (en blanco) | W35: 0.13402778 | X35: Hrs (0.00) | Y35: Porcentaje | Z35: Hrs (0.00)
P36: =IF(ISBLANK(N36),"",N36) | Q36: =IF(ISBLANK(O36),"",O36) | R36: =IF(ISBLANK(O36),"",(O36*24)) | S36: =IFERROR(R36/$R$24,"") | T36: =IFERROR(T35+S36,"") | V36: ELÉCTRICA | W36: =+VLOOKUP(V36,V32:W34,2,FALSE) -> 0.010416667 | X36: =+W33*24 -> 0.25 | Y36: ="("&ROUND(X36/$X$34,2)*100&"% )" -> (21% ) | Z36: =ROUND(X36,2)& " h." -> 0.25 h.
P37: =IF(ISBLANK(N37),"",N37) | Q37: =IF(ISBLANK(O37),"",O37) | R37: =IF(ISBLANK(O37),"",(O37*24)) | S37: =IFERROR(R37/$R$24,"") | T37: =IFERROR(T36+S37,"") | V37: MECÁNICA | W37: =+VLOOKUP(V37,V33:W35,2,FALSE) -> 0.039583333 | X37: =+W34*24 -> 0.95 | Y37: ="("&ROUND(X37/$X$34,2)*100&"% )" -> (79% ) | Z37: =ROUND(X37,2)& " h." -> 0.95 h.
P38: =IF(ISBLANK(N38),"",N38) | Q38: =IF(ISBLANK(O38),"",O38) | R38: =IF(ISBLANK(O38),"",(O38*24)) | S38: =IFERROR(R38/$R$24,"") | T38: =IFERROR(T37+S38,"")
P39: =IF(ISBLANK(N39),"",N39) | Q39: =IF(ISBLANK(O39),"",O39) | R39: =IF(ISBLANK(O39),"",(O39*24)) | S39: =IFERROR(R39/$R$24,"") | T39: =IFERROR(T38+S39,"")
P40: =IF(ISBLANK(N40),"",N40) | Q40: =IF(ISBLANK(O40),"",O40) | R40: =IF(ISBLANK(O40),"",(O40*24)) | S40: =IFERROR(R40/$R$24,"") | T40: =IFERROR(T39+S40,"")
P41: =IF(ISBLANK(N41),"",N41) | Q41: =IF(ISBLANK(O41),"",O41) | R41: =IF(ISBLANK(O41),"",(O41*24)) | S41: =IFERROR(R41/$R$24,"") | T41: =IFERROR(T40+S41,"")
P42: =IF(ISBLANK(N42),"",N42) | Q42: =IF(ISBLANK(O42),"",O42) | R42: =IF(ISBLANK(O42),"",(O42*24)) | S42: =IFERROR(R42/$R$24,"") | T42: =IFERROR(T41+S42,"")
P43: =IF(ISBLANK(N43),"",N43) | Q43: =IF(ISBLANK(O43),"",O43) | R43: =IF(ISBLANK(O43),"",(O43*24)) | S43: =IFERROR(R43/$R$24,"") | T43: =IFERROR(T42+S43,"")
P44: =IF(ISBLANK(N44),"",N44) | Q44: =IF(ISBLANK(O44),"",O44) | R44: =IF(ISBLANK(O44),"",(O44*24)) | S44: =IFERROR(R44/$R$24,"") | T44: =IFERROR(T43+S44,"")
P45: =IF(ISBLANK(N45),"",N45) | Q45: =IF(ISBLANK(O45),"",O45) | R45: =IF(ISBLANK(O45),"",(O45*24)) | S45: =IFERROR(R45/$R$24,"") | T45: =IFERROR(T44+S45,"")
N46: ** Selecciona el grafico y pasa el mouse por la tabla, arrastra hasta donde pertenezca
N49: P/NP | O49: (Varios elementos) | Q49: P/NP | R49: (Varios elementos)
N51: Etiquetas de fila | O51: Suma de T.TOTAL | Q51: Etiquetas de fila | R51: Suma de T.TOTAL
N52: Encendido / Arranque de linea | O52: 0.010416667 | Q52: MAÑANA | R52: 0.15277778
N53: Ajuste /Calibracion | O53: 0.010416667
N54: SET UP | O54: 0.010416667
N55: M.General | O55: 0.011805556 | R55: =+SUM(R56:R58) -> 3.6666667
N56: Lubricación | O56: 0.0125 | Q56: MAÑANA | R56: =IFERROR(VLOOKUP(Q56,$Q$51:$R$54,2,FALSE),0)*24 -> 3.6666667 | S56: =+R56/$R$55 -> 1
N57: Reparacion | O57: 0.016666667 | Q57: TARDE | R57: =IFERROR(VLOOKUP(Q57,$Q$51:$R$54,2,FALSE),0)*24 -> 0 | S57: =+R57/$R$55 -> 0
N58: Inspección | O58: 0.080555556 | Q58: NOCHE | R58: =IFERROR(VLOOKUP(Q58,$Q$51:$R$54,2,FALSE),0)*24 -> 0 | S58: =+R58/$R$55 -> 0
O71: =IF(COUNTIF(Q75:Q84,"<>NORMAL")>0,"🚨 Hay consumos fuera de rango","✅ Todo en orden") -> 🚨 Hay consumos fuera de rango
N73: =TODAY()-1 -> 46205 | O73: =TODAY() -> 46206
O74: CONSUMO | P74: LIMITE | Q74: ESTADO | R74: PORCENTAJE | S74: CONTADOR | T74: CONSUMO FORM
N75: GENERAL | O75: =+VLOOKUP($O$73,Tabla_query___2026_06_23T082334.128[#All],13,FALSE) -> 58 | P75: 75 | Q75: =IF(O75<P75,"NORMAL","EXCEDIDO") -> NORMAL | R75: =+O75/P75 -> 0.77333333 | S75: =+VLOOKUP($O$73,Tabla_query___2026_06_23T082334.128[#All],2,FALSE) -> 71106 | T75: =+O75& " m3" -> 58 m3
N76: BAÑOS | O76: =+VLOOKUP($O$73,Tabla_query___2026_06_23T082334.128[#All],15,FALSE) -> 20 | P76: 30 | Q76: =IF(O76<P76,"NORMAL","EXCEDIDO") -> NORMAL | R76: =+O76/P76 -> 0.66666667 | S76: =+VLOOKUP($O$73,Tabla_query___2026_06_23T082334.128[#All],4,FALSE) -> 16827 | T76: =+O76& " m3" -> 20 m3
N77: CALDERAS | O77: =+VLOOKUP($O$73,Tabla_query___2026_06_23T082334.128[#All],16,FALSE) -> 0.363 | P77: 5 | Q77: =IF(O77<P77,"NORMAL","EXCEDIDO") -> NORMAL | R77: =+O77/P77 -> 0.0726 | S77: =+VLOOKUP($O$73,Tabla_query___2026_06_23T082334.128[#All],5,FALSE) -> 968.41 | T77: =+O77& " m3" -> 0.363 m3
N78: PTAR | O78: =+VLOOKUP($O$73,Tabla_query___2026_06_23T082334.128[#All],17,FALSE) -> 7 | P78: 20 | Q78: =IF(O78<P78,"NORMAL","EXCEDIDO") -> NORMAL | R78: =+O78/P78 -> 0.35 | S78: =+VLOOKUP($O$73,Tabla_query___2026_06_23T082334.128[#All],6,FALSE) -> 9942 | T78: =+O78& " m3" -> 7 m3
N79: TANQUE DIESEL | O79: =+VLOOKUP($O$73,Tabla_query___2026_06_23T082334.128[#All],22,FALSE)/100 -> 0.48 | Q79: {=_xlfn.IFS(O79<0.31,"CRÍTICO",AND(O79>=0.31,O79<0.51),"PRECAUCIÓN",O79>0.5,"NORMAL")} -> PRECAUCIÓN
N80: MV6 | O80: =+VLOOKUP($O$73,Tabla_query___2026_06_23T082334.128[#All],19,FALSE) -> 3.8 | P80: 5 | Q80: =IF(O80<P80,"NORMAL","EXCEDIDO") -> NORMAL | S80: =+VLOOKUP($O$73,Tabla_query___2026_06_23T082334.128[#All],8,FALSE) -> 5487.9
N81: MV9 | O81: =+VLOOKUP($O$73,Tabla_query___2026_06_23T082334.128[#All],20,FALSE) -> 14 | P81: 20 | Q81: =IF(O81<P81,"NORMAL","EXCEDIDO") -> NORMAL | S81: =+VLOOKUP($O$73,Tabla_query___2026_06_23T082334.128[#All],9,FALSE) -> 2617.9
N82: MV12 | O82: =+VLOOKUP($O$73,Tabla_query___2026_06_23T082334.128[#All],21,FALSE) -> 4 | P82: 10 | Q82: =IF(O82<P82,"NORMAL","EXCEDIDO") -> NORMAL | S82: =+VLOOKUP($O$73,Tabla_query___2026_06_23T082334.128[#All],10,FALSE) -> 5733.6
N83: ENERGIA | O83: =+VLOOKUP($O$73,Tabla_query___2026_06_23T082334.128[#All],11,FALSE) -> 7118 | P83: 8000 | Q83: =IF(O83<P83,"NORMAL","EXCEDIDO") -> NORMAL | T83: =+O83& " kWh" -> 7118 kWh
N84: POTENCIA ACTIVA | O84: =+VLOOKUP($O$73,Tabla_query___2026_06_23T082334.128[#All],12,FALSE) -> 297 | P84: 350 | Q84: =IF(O84<P84,"NORMAL","EXCEDIDO") -> NORMAL | T84: =+O84& " kW" -> 297 kW
N94: CONCAT | O94: 2026 - 7 | R94: CONCAT | S94: 2026 - 7 | V94: CONCAT | W94: 2026 - 6
N96: Etiquetas de fila | O96: Suma de GENERAL CAL | P96: Suma de LCC GENERAL | R96: Etiquetas de fila | S96: Suma de ENERGIA | T96: Suma de LCC ENERGIA | V96: Etiquetas de fila | W96: Suma de P.ACTIVA | X96: Suma de LCC P.ACTIVA
N97: 46204 | O97: 70 | P97: 75 | R97: 46204 | S97: 5059 | T97: 8000 | V97: 46174 | W97: 273 | X97: 350
N98: 46205 | O98: 52 | P98: 75 | R98: 46205 | S98: 6998 | T98: 8000 | V98: 46175 | W98: 266 | X98: 350
N99: Total general | O99: 122 | P99: 150 | R99: Total general | S99: 12057 | T99: 16000 | V99: 46176 | W99: 354 | X99: 350
V100: 46177 | W100: 350 | X100: 350
V101: 46178 | W101: 340 | X101: 350
V102: 46179 | W102: 298 | X102: 350
V103: 46181 | W103: 128 | X103: 350
V104: 46182 | W104: 248 | X104: 350
V105: 46183 | W105: 354 | X105: 350
V106: 46184 | W106: 331 | X106: 350
V107: 46185 | W107: 350 | X107: 350
V108: 46186 | W108: 332 | X108: 350
V109: 46188 | W109: 282 | X109: 350
V110: 46189 | W110: 269 | X110: 350
V111: 46190 | W111: 379 | X111: 350
... V121: 46203 | W121: 75 | X121: 350
V122: Total general | W122: 7179 | X122: 8750
N143: 0 | O143: 0.040972222
N144: 0.041666667 | O144: 0.082638889
N145: 0.083333333 | O145: 2
B147: Maquina/ Equipo | C147: Clasif. | D147: Turno | E147: Hora de inicio | F147: Hora de fin | G147: Tiempo de atención | H147: Tipo de Actividad | I147: P/NP | J147: M/E | K147: Descripcion de actividad | L147: Observaciones | M147: Nº | N147: NOMBRE
B148: =+'TABLA-DIA'!B153 -> LINEA AUTOMATICA HACOS 2 | C148: =IFERROR(VLOOKUP(N148,'TABLA-DIA'!$B$2:$P$62,9,FALSE),"") | D148: =IFERROR(VLOOKUP(N148,'TABLA-DIA'!$B$2:$P$62,4,FALSE),"") | E148: =IFERROR(VLOOKUP(N148,'TABLA-DIA'!$B$2:$P$62,5,FALSE),"") | F148: =IFERROR(VLOOKUP(N148,'TABLA-DIA'!$B$2:$P$62,6,FALSE),"") | G148: =IFERROR(VLOOKUP(N148,'TABLA-DIA'!$B$2:$P$62,7,FALSE),"") | H148: =IFERROR(VLOOKUP(N148,'TABLA-DIA'!$B$2:$P$62,10,FALSE),"") | I148: =IFERROR(VLOOKUP(N148,'TABLA-DIA'!$B$2:$P$62,11,FALSE),"") | J148: =IFERROR(VLOOKUP(N148,'TABLA-DIA'!$B$2:$P$62,12,FALSE),"") | K148: =IFERROR(VLOOKUP(N148,'TABLA-DIA'!$B$2:$P$62,13,FALSE),"") | L148: =IFERROR(IF(VLOOKUP(N148,'TABLA-DIA'!$B$2:$P$62,14,FALSE)="","",VLOOKUP(N148,'TABLA-DIA'!$B$2:$P$62,14,FALSE)),"") | M148: 1 | N148: =CONCATENATE($B$148,"-",M148) -> LINEA AUTOMATICA HACOS 2-1 | O148: =COUNTIF(G148:G159,"<>**") -> 0
C149: =IFERROR(VLOOKUP(N149,'TABLA-DIA'!$B$2:$P$62,9,FALSE),"") | D149: =IFERROR(VLOOKUP(N149,'TABLA-DIA'!$B$2:$P$62,4,FALSE),"") | E149: =IFERROR(VLOOKUP(N149,'TABLA-DIA'!$B$2:$P$62,5,FALSE),"") | F149: =IFERROR(VLOOKUP(N149,'TABLA-DIA'!$B$2:$P$62,6,FALSE),"") | G149: =IFERROR(VLOOKUP(N149,'TABLA-DIA'!$B$2:$P$62,7,FALSE),"") | H149: =IFERROR(VLOOKUP(N149,'TABLA-DIA'!$B$2:$P$62,10,FALSE),"") | I149: =IFERROR(VLOOKUP(N149,'TABLA-DIA'!$B$2:$P$62,11,FALSE),"") | J149: =IFERROR(VLOOKUP(N149,'TABLA-DIA'!$B$2:$P$62,12,FALSE),"") | K149: =IFERROR(VLOOKUP(N149,'TABLA-DIA'!$B$2:$P$62,13,FALSE),"") | L149: =IFERROR(IF(VLOOKUP(N149,'TABLA-DIA'!$B$2:$P$62,14,FALSE)="","",VLOOKUP(N149,'TABLA-DIA'!$B$2:$P$62,14,FALSE)),"") | M149: 2 | N149: =CONCATENATE($B$148,"-",M149) -> LINEA AUTOMATICA HACOS 2-2
C150: =IFERROR(VLOOKUP(N150,'TABLA-DIA'!$B$2:$P$62,9,FALSE),"") | D150: =IFERROR(VLOOKUP(N150,'TABLA-DIA'!$B$2:$P$62,4,FALSE),"") | E150: =IFERROR(VLOOKUP(N150,'TABLA-DIA'!$B$2:$P$62,5,FALSE),"") | F150: =IFERROR(VLOOKUP(N150,'TABLA-DIA'!$B$2:$P$62,6,FALSE),"") | G150: =IFERROR(VLOOKUP(N150,'TABLA-DIA'!$B$2:$P$62,7,FALSE),"") | H150: =IFERROR(VLOOKUP(N150,'TABLA-DIA'!$B$2:$P$62,10,FALSE),"") | I150: =IFERROR(VLOOKUP(N150,'TABLA-DIA'!$B$2:$P$62,11,FALSE),"") | J150: =IFERROR(VLOOKUP(N150,'TABLA-DIA'!$B$2:$P$62,12,FALSE),"") | K150: =IFERROR(VLOOKUP(N150,'TABLA-DIA'!$B$2:$P$62,13,FALSE),"") | L150: =IFERROR(IF(VLOOKUP(N150,'TABLA-DIA'!$B$2:$P$62,14,FALSE)="","",VLOOKUP(N150,'TABLA-DIA'!$B$2:$P$62,14,FALSE)),"") | M150: 3 | N150: =CONCATENATE($B$148,"-",M150) -> LINEA AUTOMATICA HACOS 2-3
C151: =IFERROR(VLOOKUP(N151,'TABLA-DIA'!$B$2:$P$62,9,FALSE),"") | D151: =IFERROR(VLOOKUP(N151,'TABLA-DIA'!$B$2:$P$62,4,FALSE),"") | E151: =IFERROR(VLOOKUP(N151,'TABLA-DIA'!$B$2:$P$62,5,FALSE),"") | F151: =IFERROR(VLOOKUP(N151,'TABLA-DIA'!$B$2:$P$62,6,FALSE),"") | G151: =IFERROR(VLOOKUP(N151,'TABLA-DIA'!$B$2:$P$62,7,FALSE),"") | H151: =IFERROR(VLOOKUP(N151,'TABLA-DIA'!$B$2:$P$62,10,FALSE),"") | I151: =IFERROR(VLOOKUP(N151,'TABLA-DIA'!$B$2:$P$62,11,FALSE),"") | J151: =IFERROR(VLOOKUP(N151,'TABLA-DIA'!$B$2:$P$62,12,FALSE),"") | K151: =IFERROR(VLOOKUP(N151,'TABLA-DIA'!$B$2:$P$62,13,FALSE),"") | L151: =IFERROR(IF(VLOOKUP(N151,'TABLA-DIA'!$B$2:$P$62,14,FALSE)="","",VLOOKUP(N151,'TABLA-DIA'!$B$2:$P$62,14,FALSE)),"") | M151: 4 | N151: =CONCATENATE($B$148,"-",M151) -> LINEA AUTOMATICA HACOS 2-4
